Draft_Phuong/unpack_s3/ppa_sk.sv
module sub_2i8_o8(x1, y, out, carry);
    input[7:0] x1;
    input[7:0] y;
    output[7:0] out;
    output carry;
    wire[7:0] x2;
    wire[7:0] g1,p1;
    wire[3:0] g2,g3,g4;
    wire[3:1] p2;
    wire[3:2] p3;

    assign x2 = ~y;

    ha_with_carry_1 HA1 ( .a( x1[0] ), .b( x2[0] ), .g( g1[0] ), .p( p1[0] ) );
    ha HA2 ( .a( x1[1] ), .b( x2[1] ), .g( g1[1] ), .p( p1[1] ) );
    ha HA3 ( .a( x1[2] ), .b( x2[2] ), .g( g1[2] ), .p( p1[2] ) );
    ha HA4 ( .a( x1[3] ), .b( x2[3] ), .g( g1[3] ), .p( p1[3] ) );
    ha HA5 ( .a( x1[4] ), .b( x2[4] ), .g( g1[4] ), .p( p1[4] ) );
    ha HA6 ( .a( x1[5] ), .b( x2[5] ), .g( g1[5] ), .p( p1[5] ) );
    ha HA7 ( .a( x1[6] ), .b( x2[6] ), .g( g1[6] ), .p( p1[6] ) );
    ha HA8 ( .a( x1[7] ), .b( x2[7] ), .g( g1[7] ), .p( p1[7] ) );

    grey_cell A1 (.gi1( g1[1] ), .pi1( p1[1] ), .gi2( g1[0] ), .go( g2[0] ) );
    black_cell A2 (.gi1( g1[3] ), .pi1( p1[3] ), .gi2( g1[2] ), .pi2( p1[2] ), .go( g2[1] ), .po( p2[1] ) );
    black_cell A3 (.gi1( g1[5] ), .pi1( p1[5] ), .gi2( g1[4] ), .pi2( p1[4] ), .go( g2[2] ), .po( p2[2] ) );
    black_cell A4 (.gi1( g1[7] ), .pi1( p1[7] ), .gi2( g1[6] ), .pi2( p1[6] ), .go( g2[3] ), .po( p2[3] ) );
    grey_cell A5 (.gi1( g1[2] ), .pi1( p1[2] ), .gi2( g2[0] ), .go( g3[0] ) );
    grey_cell A6 (.gi1( g2[1] ), .pi1( p2[1] ), .gi2( g2[0] ), .go( g3[1] ) );
    black_cell A7 (.gi1( g1[6] ), .pi1( p1[6] ), .gi2( g2[2] ), .pi2( p2[2] ), .go( g3[2] ), .po( p3[2] ) );
    black_cell A8 (.gi1( g2[3] ), .pi1( p2[3] ), .gi2( g2[2] ), .pi2( p2[2] ), .go( g3[3] ), .po( p3[3] ) );
    grey_cell A9 (.gi1( g1[4] ), .pi1( p1[4] ), .gi2( g3[1] ), .go( g4[0] ) );
    grey_cell A10 (.gi1( g2[2] ), .pi1( p2[2] ), .gi2( g3[1] ), .go( g4[1] ) );
    grey_cell A11 (.gi1( g3[2] ), .pi1( p3[2] ), .gi2( g3[1] ), .go( g4[2] ) );
    grey_cell A12 (.gi1( g3[3] ), .pi1( p3[3] ), .gi2( g3[1] ), .go( g4[3] ) );

    assign out[7:1] = p1[7:1] ^ { g4[2:0], g3[1], g3[0], g2[0], g1[0] };
    assign out[0] = p1[0];
    assign carry = g4[3];

endmodule

module black_cell(gi1, pi1, gi2, pi2, go, po);
//gi1 is a combined generate signal from j to i
//pi1 is a combined propagate signal from j to i
//gi2 is a combined generate signal from m to j-1
//pi2 is a combined propagate signal from m to j-1
//go is a combined generate signal from m to i
//po is a combined propagate signal from m to i
    input gi1, pi1, gi2, pi2;
    output go, po;

    assign po = pi1 & pi2;
    assign go = ( gi2 & pi1 ) | gi1;
endmodule

module grey_cell(gi1, pi1, gi2, go);
//gi1 is a combined generate signal from j to i
//pi1 is a combined propagate signal from j to i
//gi2 is a combined generate signal from m to j-1
//go is a combined generate signal from m to i
//po is a combined propagate signal from m to i
    input gi1, pi1, gi2;
    output go;

    assign go = ( gi2 & pi1 ) | gi1;
endmodule

module ha(a, b, g, p);
    input a, b;
    output g, p;

    assign g = a & b;
    assign p = a ^ b;
endmodule

module ha_with_carry_1(a, b, g, p);
    input a, b;
    output g, p;

    assign g = a | b;
    assign p = ~(a ^ b);
endmodule

Draft_Phuong/add_2i13_o13/add_2i13_o13.sv
`include "ppa_sk.sv"
module add_2i13_o13(x1, x2, out);
	parameter NUM_BIT = 13;

    input[NUM_BIT-1 : 0] x1,check_holder;
    input[NUM_BIT-1 : 0] x2;
    output[NUM_BIT-1 : 0] out;
    wire[NUM_BIT-1 : 0] g0,p0,g1,p1,g2,p2,g3,p3,g4;

	generate
		genvar i;
		for (i = 0; i < NUM_BIT; i = i + 1)
		begin: HA_SLICE
			ha A0 ( .a( x1[i] ), .b( x2[i] ), .g( g0[i] ), .p( p0[i] ) );
		end
	endgenerate

    grey_cell A1_1 ( .gi1( g0[1] ), .pi1( p0[1] ), .gi2( g0[0] ), .go( g1[1] ) );
    black_cell A1_3 ( .gi1( g0[3] ), .pi1( p0[3] ), .gi2( g0[2] ), .pi2( p0[2] ), .go( g1[3] ), .po( p1[3] ) );
    black_cell A1_5 ( .gi1( g0[5] ), .pi1( p0[5] ), .gi2( g0[4] ), .pi2( p0[4] ), .go( g1[5] ), .po( p1[5] ) );
    black_cell A1_7 ( .gi1( g0[7] ), .pi1( p0[7] ), .gi2( g0[6] ), .pi2( p0[6] ), .go( g1[7] ), .po( p1[7] ) );
	black_cell A1_9 ( .gi1( g0[9] ), .pi1( p0[9] ), .gi2( g0[8] ), .pi2( p0[8] ), .go( g1[9] ), .po( p1[9] ) );
	black_cell A1_11 ( .gi1( g0[11] ), .pi1( p0[11] ), .gi2( g0[10] ), .pi2( p0[10] ), .go( g1[11] ), .po( p1[11] ) );

	grey_cell A2_2 ( .gi1( g0[2] ), .pi1( p0[2] ), .gi2( g1[1] ), .go( g2[2] ) );
    grey_cell A2_3 ( .gi1( g1[3] ), .pi1( p1[3] ), .gi2( g1[1] ), .go( g2[3] ) );
    black_cell A2_6 ( .gi1( g0[6] ), .pi1( p0[6] ), .gi2( g1[5] ), .pi2( p1[5] ), .go( g2[6] ), .po( p2[6] ) );
    black_cell A2_7 ( .gi1( g1[7] ), .pi1( p1[7] ), .gi2( g1[5] ), .pi2( p1[5] ), .go( g2[7] ), .po( p2[7] ) );
	black_cell A2_10 ( .gi1( g0[10] ), .pi1( p0[10] ), .gi2( g1[9] ), .pi2( p1[9] ), .go( g2[10] ), .po( p2[10] ) );
	black_cell A2_11 ( .gi1( g1[11] ), .pi1( p1[11] ), .gi2( g1[9] ), .pi2( p1[9] ), .go( g2[11] ), .po( p2[11] ) );

	grey_cell A3_4 (.gi1( g0[4] ), .pi1( p0[4] ), .gi2( g2[3] ), .go( g3[4] ) );
    grey_cell A3_5 (.gi1( g1[5] ), .pi1( p1[5] ), .gi2( g2[3] ), .go( g3[5] ) );
    grey_cell A3_6 (.gi1( g2[6] ), .pi1( p2[6] ), .gi2( g2[3] ), .go( g3[6] ) );
    grey_cell A3_7 (.gi1( g2[7] ), .pi1( p2[7] ), .gi2( g2[3] ), .go( g3[7] ) );
	black_cell A3_12 ( .gi1( g0[12] ), .pi1( p0[12] ), .gi2( g2[11] ), .pi2( p2[11] ), .go( g3[12] ), .po( p3[12] ) );

	grey_cell A4_8 (.gi1( g0[8] ), .pi1( p0[8] ), .gi2( g3[7] ), .go( g4[8] ) );
	grey_cell A4_9 (.gi1( g1[9] ), .pi1( p1[9] ), .gi2( g3[7] ), .go( g4[9] ) );
	grey_cell A4_10 (.gi1( g2[10] ), .pi1( p2[10] ), .gi2( g3[7] ), .go( g4[10] ) );
	grey_cell A4_11 (.gi1( g2[11] ), .pi1( p2[11] ), .gi2( g3[7] ), .go( g4[11] ) );
	grey_cell A4_12 (.gi1( g3[12] ), .pi1( p3[12] ), .gi2( g3[7] ), .go( g4[12] ) );

    assign out[NUM_BIT-1 : 1] = p0[NUM_BIT-1 : 1] ^ { g4[11:8], g3[7:4], g2[3:2], g1[1], g0[0] };
    assign out[0] = p0[0];

	initial begin
		$dumpfile("dump.vcd");
		$dumpvars(1);
	end

endmodule // add_2i13_o13

Draft_Phuong/add_2i13_o13/dump.vcd
$date
	Wed Oct 20 00:08:48 2021
$end
$version
	Icarus Verilog
$end
$timescale
	1ps
$end
$scope module add_2i13_o13 $end
$var wire 13 ! check_holder [12:0] $end
$var wire 13 " x1 [12:0] $end
$var wire 13 # x2 [12:0] $end
$var wire 13 $ p3 [12:0] $end
$var wire 13 % p2 [12:0] $end
$var wire 13 & p1 [12:0] $end
$var wire 13 ' p0 [12:0] $end
$var wire 13 ( out [12:0] $end
$var wire 13 ) g4 [12:0] $end
$var wire 13 * g3 [12:0] $end
$var wire 13 + g2 [12:0] $end
$var wire 13 , g1 [12:0] $end
$var wire 13 - g0 [12:0] $end
$upscope $end
$enddefinitions $end
#0
$dumpvars
b10010000010 -
bz1z0z1z0z0z1z ,
bz11zz10zz00zz +
b0zzzz1000zzzz *
b1111zzzzzzzz )
b1010001101101 (
b101101101001 '
bz0z1z0z0z0zzz &
bz00zz00zzzzzz %
b0zzzzzzzzzzzz $
b110111100010 #
b11010001011 "
bz !
$end
#1000
b0 !
#2000
b0zzzz1100zzzz *
b1011zzzzzzzz )
bz1z0z1z0z0z0z ,
b1010000000101 (
bz10zz11zz00zz +
b1110000101 '
b100001000000 -
b100101000100 "
b101011000001 #
#4000
b10010zzzzzzzz )
bz0z0z0z0z0zzz &
bz00zz11zz11zz +
bz0z1z1z1z1z0z ,
b1zzzz1111zzzz *
b110111011010 (
b100000100010 '
b1001011011100 -
b1001011111110 "
b1101011011100 #
#6000
bz1z0z0z0z0zzz &
b1zzzz0010zzzz *
b1000100 (
bz11zz00zz00zz +
bz0z1z0z1z0z1z ,
b11111zzzzzzzz )
b1111000000010 '
b100100001 -
b10100100001 "
b1101100100011 #
#8000
b10111zzzzzzzz )
b1zzzz0000zzzz *
bz01zz00zz00zz +
bz0z1z0z0z0z0z ,
bz0z0z0z0z1zzz &
b111010101111 (
b1011100000000 -
b10101111 '
b1011100100110 "
b1011110001001 #
#10000
b11zzzzzzzz )
b0zzzz1100zzzz *
bz0z0z1z0z1z1z ,
bz0z1z0z0z0zzz &
bz00zz11zz11zz +
b1110000110101 (
b1000110 -
b1101110101001 '
b11101110 "
b1101101000111 #
#12000
b10000zzzzzzzz )
bz0z0z0z0z0z1z ,
b1zzzz0000zzzz *
bz00zz00zz11zz +
bz0z0z0z0z1zzz &
b100110010001 (
b1000000000010 -
b100110001101 '
b1000010000111 "
b1100100001010 #
#14000
b11101zzzzzzzz )
b1zzzz1111zzzz *
bz1z0z1z1z0z0z ,
b1101111001111 (
bz11zz11zz00zz +
b101111 '
b1110111010000 -
b1110111110001 "
b1110111011110 #
#16000
b10000zzzzzzzz )
b1zzzz0001zzzz *
bz0z0z0z0z1z1z ,
bz0z1z1z0z0zzz &
b101111100101 (
bz00zz00zz10zz +
b101111010001 '
b1000000001010 -
b1000111011011 "
b1101000001010 #
#18000
b1zzzz0100zzzz *
bz0z0z0z0z0z0z ,
bz00zz01zz00zz +
bz1z0z0z1z1zzz &
bz00zz00zzzzzz %
b111010111100 (
b1000001000000 -
b111000111100 '
b1101001011000 "
b1010001100100 #
#20000
b0zzzzzzzz )
b0zzzz0000zzzz *
bz0z0z0z0z1z0z ,
bz00zz00zz10zz +
bz00zz00zzzzzz %
bz0z1z1z0z0zzz &
b1001111110111 (
b1000 -
b1001111100111 '
b1111101101 "
b1000000001010 #
#22000
b0zzzz0000zzzz *
bz00zz00zzzzzz %
bz00zz00zz01zz +
bz0z0z0z0z0z0z ,
b1zzzzzzzz )
bz1z0z0z1z0zzz &
b111010111010 (
b100000100 -
b110010110010 '
b10110110100 "
b100100000110 #
#24000
bz11zz11zz11zz +
b1111zzzzzzzz )
b0zzzz1111zzzz *
bz1z0z0z0z1zzz &
bz00zz00zzzzzz %
b1001010010000 (
bz0z1z1z1z0z1z ,
b110101101100 '
b1010010010 -
b1010110010 "
b111111011110 #
#26000
bz11zz11zz00zz +
b11111zzzzzzzz )
bz0z1z1z0z0z0z ,
b1zzzz1101zzzz *
b1001000101101 (
b110110001101 '
b1001001010000 -
b1111111010100 "
b1001001011001 #
#28000
b10001zzzzzzzz )
bz00zz11zz01zz +
bz1z0z1z0z0zzz &
b1zzzz1110zzzz *
b111000011101 (
bz0z0z0z1z0z1z ,
b110111010001 '
b1000000100110 -
b1010100110110 "
b1100011100111 #
#30000
bz00zz11zz00zz +
b11zzzzzzzz )
bz0z1z1z1z0z0z ,
bz0z0z0z0z1zzz &
b11001011101 (
b0zzzz1110zzzz *
b110011101 '
b1001100000 -
b1111111101 "
b1001100000 #
#32000
b1zzzzzzzz )
bz00zz11zz10zz +
bz0z0z0z1z1z0z ,
bz1z0z1z0z0zzz &
b1111100010100 (
b100101000 -
b1110011000100 '
b101101100 "
b1110110101000 #
#34000
bz1z0z1z1z1z0z ,
bz0z0z0z0z0zzz &
bz11zz11zz11zz +
b1zzzz1111zzzz *
b11100zzzzzzzz )
b110011011 (
b1100001100011 '
b10010011100 -
b1010010011111 "
b110011111100 #
#36000
bz01zz00zz00zz +
bz0z1z0z0z0z0z ,
bz0z0z1z0z1zzz &
b0zzzz0000zzzz *
b111zzzzzzzz )
b1110011101111 (
b10100000000 -
b1001011101111 '
b1011100100001 "
b10111001110 #
#38000
bz11zz10zz00zz +
b0zzzz1010zzzz *
b1111zzzzzzzz )
bz0z1z1z1z0z0z ,
bz1z0z0z0z1zzz &
b1001001011111 (
b1010100000 -
b110100011111 '
b1010110111 "
b111110101000 #
#40000
b111zzzzzzzz )
bz01zz11zz11zz +
bz0z0z1z1z0z1z ,
b0zzzz1111zzzz *
bz0z1z0z0z1zzz &
b1110010010000 (
b10010010010 -
b1001101101100 '
b1010110111010 "
b11011010110 #
#42000
b10100zzzzzzzz )
bz01zz00zz00zz +
bz0z0z0z1z0zzz &
bz0z0z0z0z0z0z ,
b1zzzz0000zzzz *
b101000110110 (
b1010000000000 -
b1000110110 '
b1010000000110 "
b1011000110000 #
#44000
b0zzzzzzzz )
bz0z0z0z0z1zzz &
bz0z0z1z1z0z1z ,
bz00zz11zz11zz +
b0zzzz1111zzzz *
b1100111100000 (
b11100001 -
b1100000011110 '
b1100011101001 "
b11110111 #
#46000
bz00zz11zz00zz +
bz01zz00zzzzzz %
bz0z0z1z1z0z0z ,
b111zzzzzzzz )
bz0z1z0z0z1zzz &
b100001001111 (
b1010000 -
b11110101111 '
b10001010110 "
b1111111001 #
#48000
bz00zz00zz10zz +
b10zzzzzzzz )
b0zzzz0111zzzz *
bz0z1z0z0z1z0z ,
bz00zz01zzzzzz %
bz0z0z0z1z0zzz &
b110010000001 (
b1000001000 -
b100001110001 '
b101000101001 "
b1001011000 #
#50000
b11111zzzzzzzz )
bz10zz11zz00zz +
bz01zz00zzzzzz %
bz0z1z0z1z0zzz &
bz1z0z1z0z0z0z ,
b1zzzz1100zzzz *
b1100000111010 (
b11110111000 '
b1100001000001 -
b1101001000001 "
b1110111111001 #
#52000
b1011zzzzzzzz )
bz1z1z0z0z0z0z ,
bz10zz00zz00zz +
bz0z0z1z1z1zzz &
bz00zz11zzzzzz %
b0zzzz0000zzzz *
b1010011111101 (
b1011111101 '
b100100000000 -
b100110010001 "
b101101101100 #
#54000
b1zzzzzzzz )
bz00zz01zzzzzz %
bz00zz10zz11zz +
b0zzzz1111zzzz *
bz0z0z1z0z0z1z ,
bz1z0z0z1z1zzz &
b1111110000010 (
b110000011 -
b1110001111100 '
b10111010111 "
b1100110101011 #
#56000
bz00zz00zzzzzz %
b1zzzz0000zzzz *
bz1z0z0z0z0z1z ,
b11100zzzzzzzz )
bz11zz00zz00zz +
bz0z0z0z0z0zzz &
b1101100 (
b10000000010 -
b1100001101000 '
b1110000001010 "
b10001100010 #
#58000
b1100zzzzzzzz )
b0zzzz0000zzzz *
bz1z0z0z0z0z0z ,
b1000101011010 (
b10000000000 -
b100101011010 '
b110001010000 "
b10100001010 #
#60000
b0zzzz1111zzzz *
bz00zz11zzzzzz %
b1111zzzzzzzz )
bz11zz00zz10zz +
bz1z0z1z1z0zzz &
b1001100000110 (
bz0z1z0z0z1z0z ,
b110011110110 '
b1100001000 -
b101111011000 "
b11100101110 #
#62000
b0zzzz1001zzzz *
bz00zz00zzzzzz %
bz11zz10zz11zz +
bz1z1z1z0z1z0z ,
bz0z0z0z0z0zzz &
b1010101100011 (
b10110000100 -
b101001011011 '
b10110011101 "
b111111000110 #
#64000
b0zzzz0001zzzz *
bz11zz00zz00zz +
bz1z0z0z0z1zzz &
b1001001101111 (
bz0z1z0z0z0z0z ,
b110001001111 '
b1100010000 -
b101101011000 "
b11100010111 #
#66000
bz01zz00zzzzzz %
b111zzzzzzzz )
b0zzzz1100zzzz *
bz00zz11zz00zz +
bz0z0z1z0z0z0z ,
bz0z1z0z0z1zzz &
b100000011111 (
b1000000 -
b11110011111 '
b1001011101 "
b10111000010 #
#68000
bz11zz00zzzzzz %
b11111zzzzzzzz )
bz00zz10zz00zz +
bz1z1z0z1z0zzz &
b1000000110111 (
b1zzzz1000zzzz *
b111100110111 '
b1000010000000 -
b1000010110111 "
b1111110000000 #
#70000
bz00zz11zz10zz +
b10000zzzzzzzz )
b1zzzz1111zzzz *
bz0z0z0z1z1z1z ,
bz0z0z1z0z0zzz &
bz00zz00zzzzzz %
b100100110100 (
b1000000111001 -
b100011000010 '
b1000010111011 "
b1100001111001 #
#72000
b11111zzzzzzzz )
b1zzzz1111zzzz *
bz1z0z1z1z1z1z ,
bz0z1z0z0z0zzz &
b10010101100 (
bz11zz11zz11zz +
b1101101010010 '
b10010101101 -
b10011101101 "
b1111110111111 #
#74000
b0zzzz1111zzzz *
b1zzzzzzzz )
bz0z0z0z1z0z1z ,
bz0z0z1z0z0zzz &
bz00zz11zz00zz +
b1001100101101 (
b100110010 -
b1000011001001 '
b1000110111010 "
b101110011 #
#76000
bz10zz00zz11zz +
b11000zzzzzzzz )
bz1z0z0z0z1z1z ,
b1zzzz0001zzzz *
b1011011100110 (
b1100000000111 -
b11011011000 '
b1101001011111 "
b1110010000111 #
#78000
b1zzzz1000zzzz *
bz11zz10zz00zz +
b11111zzzzzzzz )
bz0z0z0z1z1zzz &
bz1z1z1z0z0z0z ,
b1101000111100 (
b1101010000000 -
b10100111100 '
b1111110110000 "
b1101010001100 #
#80000
b1111zzzzzzzz )
bz11zz11zz00zz +
bz0z1z1z1z0z0z ,
bz1z0z0z0z0zzz &
b1001011000110 (
b0zzzz1111zzzz *
b110100100100 '
b1011010001 -
b101011110101 "
b11111010001 #
#82000
b0zzzzzzzz )
bz0z0z1z1z1z1z ,
bz00zz11zz11zz +
b0zzzz1111zzzz *
b1111101100100 (
b1100101 -
b1111010011010 '
b10011110101 "
b1101001101111 #
#84000
b0zzzz1101zzzz *
bz0z0z0z0z0zzz &
bz00zz11zz10zz +
bz0z0z1z0z1z0z ,
b101100100010 (
b1001000 -
b101010010010 '
b100001011000 "
b1011001010 #
#86000
b1zzzz0001zzzz *
bz11zz00zz00zz +
b11111zzzzzzzz )
bz1z1z0z0z0z0z ,
b100010101010 (
b100100010001 -
b1011010001000 '
b1100100011001 "
b111110010001 #
#88000
b1zzzz1011zzzz *
b10011zzzzzzzz )
bz0z1z0z0z0zzz &
bz00zz10zz11zz +
bz0z0z1z1z1z1z ,
b10001100100 (
b1000010100101 -
b1100011010 '
b1000010101111 "
b1001110110101 #
#90000
b11zzzzzzzz )
bz00zz11zz11zz +
bz0z0z0z1z1z0z ,
bz0z1z1z0z0zzz &
b110000101010 (
b0zzzz1111zzzz *
b101111010010 '
b101100 -
b101010111110 "
b101101100 #
#92000
b0zzzz1000zzzz *
b0zzzzzzzz )
bz00zz00zzzzzz %
bz00zz10zz10zz +
bz0z0z1z0z1z1z ,
bz1z0z0z0z0zzz &
b1110101010100 (
b10001001 -
b1110001000010 '
b1010010001011 "
b100011001001 #
#94000
b1zzzz1110zzzz *
b11101zzzzzzzz )
bz1z0z1z1z0z1z ,
bz11zz11zz01zz +
bz0z0z0z0z0zzz &
b1010011001 (
b10010100010 -
b1100101010101 '
b1110010110111 "
b10111100010 #
#96000
b1zzzzzzzz )
b0zzzz1001zzzz *
bz00zz10zz11zz +
bz0z0z1z0z1z1z ,
b1011000100100 (
b10000101 -
b1010100011010 '
b1000110000111 "
b10010011101 #
#98000
b11111zzzzzzzz )
bz0z0z0z1z0zzz &
bz11zz10zz10zz +
bz1z1z1z0z1z0z ,
b1zzzz1011zzzz *
b1011001000001 (
b1011010001000 -
b100100110001 '
b1111010111000 "
b1011110001001 #
#100000
bz11zz11zz11zz +
b1zzzz1110zzzz *
bz00zz00zzzzzz %
bz0z1z0z1z0z1z ,
bz1z0z1z0z1zzz &
b1001100010010 (
b1001100100011 -
b110011001100 '
b1111110101111 "
b1001101100011 #
#102000
b10011zzzzzzzz )
b1zzzz0000zzzz *
bz00zz00zz00zz +
bz0z0z0z0z1zzz &
bz0z1z0z0z0z0z ,
b11001101101 (
b1101101 '
b1001100000000 -
b1001101001000 "
b1001100100101 #
#104000
bz00zz01zz11zz +
b0zzzzzzzz )
bz0z0z0z1z1z1z ,
bz0z1z0z0z0zzz &
b1110011101 (
b0zzzz0111zzzz *
b1101100001 '
b11110 -
b1101111110 "
b11111 #
#106000
b1zzzz0001zzzz *
b11100zzzzzzzz )
bz0z0z0z0z0zzz &
bz11zz00zz00zz +
bz1z0z0z0z0z0z ,
b100000100111 (
b110000010000 -
b1000000000111 '
b110000010111 "
b1110000010000 #
#108000
b1zzzz1110zzzz *
bz1z0z0z0z0zzz &
bz11zz11zz00zz +
b1001101011011 (
b11111zzzzzzzz )
bz0z1z1z1z0z0z ,
b110010011011 '
b1001101100000 -
b1001101100000 "
b1111111111011 #
#110000
b1zzzzzzzzzzzz $
bz11zz00zzzzzz %
b0zzzz1111zzzz *
bz00zz11zz11zz +
bz0z0z0z1z1z1z ,
bz1z1z1z0z0zzz &
b10101 (
b10110 -
b1111111101001 '
b1001011111 "
b1110110110110 #
#112000
b0zzzz1100zzzz *
b111zzzzzzzz )
b0zzzzzzzzzzzz $
bz00zz00zzzzzz %
bz01zz11zz00zz +
bz0z1z1z0z0z0z ,
bz0z0z0z1z0zzz &
b1111100111011 (
b11101000000 -
b1000010111011 '
b1011111111000 "
b11101000011 #
#114000
b0zzzz0000zzzz *
bz0z1z0z0z0z0z ,
bz01zz00zz00zz +
bz00zz00zzzzzz %
bz0z0z1z0z1zzz &
b1101011001110 (
b1100000000 -
b1010011001110 '
b1001110001010 "
b11101000100 #
#116000
bz00zz00zz00zz +
b0zzzz0011zzzz *
bz0z0z0z1z0z0z ,
b0zzzzzzzz )
bz0z1z0z0z0zzz &
b1101111100101 (
b110000 -
b1101110000101 '
b100110101 "
b1101010110000 #
#118000
bz00zz11zzzzzz %
bz00zz00zz00zz +
b0zzzz0000zzzz *
bz0z1z0z0z0z1z ,
b11zzzzzzzz )
bz0z0z1z1z0zzz &
b11011111100 (
b1100000001 -
b11111010 '
b1101001001 "
b1110110011 #
#120000
b1zzzz1000zzzz *
bz00zz01zzzzzz %
bz10zz10zz00zz +
b11011zzzzzzzz )
bz0z1z0z1z0zzz &
bz1z0z1z0z0z0z ,
b10001110111 (
b1001101110111 '
b100010000000 -
b1100110010011 "
b101011100100 #
#122000
b1zzzz0000zzzz *
bz00zz00zzzzzz %
b11100zzzzzzzz )
bz1z0z0z0z0z0z ,
bz0z1z1z0z0zzz &
bz11zz00zz01zz +
b1001111101011 (
b1010000000100 -
b101111100011 '
b1111001000111 "
b1010110100100 #
#124000
b1111zzzzzzzz )
bz11zz11zz01zz +
bz00zz00zzzzzz %
bz1z1z0z1z0z1z ,
bz0z0z1z0z0zzz &
b0zzzz1111zzzz *
b1101000001110 (
b10111100000 '
b101000010111 -
b101000110111 "
b111111010111 #
#126000
b11100zzzzzzzz )
b1zzzz0011zzzz *
bz11zz00zz11zz +
bz1z0z0z1z1z0z ,
bz0z1z0z0z0zzz &
b1111111010 (
b10000111100 -
b1101110000010 '
b1111000111100 "
b10110111110 #
#128000
b0zzzz0001zzzz *
b0zzzzzzzz )
bz0z0z0z0z1z1z ,
bz0z1z1z0z0zzz &
bz00zz00zz11zz +
bz01zz00zzzzzz %
b1011111101001 (
b1010 -
b1011111010101 '
b1010010011110 "
b1101001011 #
#130000
b0zzzz1111zzzz *
bz00zz11zz01zz +
bz00zz00zzzzzz %
b1zzzzzzzz )
bz0z0z0z1z0z1z ,
bz0z0z1z0z0zzz &
b1011100001100 (
b100010101 -
b1010011100010 '
b1000110110111 "
b10101010101 #
#132000
bz11zz11zz11zz +
bz1z0z1z1z0z1z ,
bz0z0z0z0z1zzz &
b1100zzzzzzzz )
b1001110010001 (
b101001101101 '
b10010010010 -
b111010111010 "
b10011010111 #
#134000
b0zzzzzzzz )
bz0z0z1z0z1z0z ,
bz0z0z0z0z0zzz &
bz00zz10zz11zz +
b10101110011 (
b0zzzz1000zzzz *
b10001101011 '
b10000100 -
b10001100 "
b10011100111 #
#136000
b10110zzzzzzzz )
bz01zz00zz00zz +
b100010011001 (
bz0z1z0z0z0z0z ,
b1zzzz0000zzzz *
b10010011001 '
b1001000000000 -
b1011000001001 "
b1001010010000 #
#138000
bz10zz10zz00zz +
b1000zzzzzzzz )
b1011101000111 (
bz1z0z1z0z0z0z ,
b0zzzz1000zzzz *
b11001000111 '
b100010000000 -
b100010000011 "
b111011000100 #
#140000
b0zzzz0110zzzz *
bz0z0z0z0z1zzz &
bz01zz01zz11zz +
b111zzzzzzzz )
bz0z1z0z1z0z1z ,
b1100011010000 (
b101100001 -
b1011000001110 '
b101101011 "
b1011101100101 #
#142000
b11101zzzzzzzz )
bz11zz11zz00zz +
bz1z0z0z1z0z1z ,
b1zzzz1111zzzz *
bz0z0z1z0z0zzz &
b1100001101 (
b10100010010 -
b1100011101001 '
b1010111011011 "
b110100110010 #
#144000
b11111zzzzzzzz )
bz1z1z0z0z1z1z ,
b1zzzz0001zzzz *
bz11zz00zz11zz +
b1100011101000 (
b1100100001001 -
b11011010110 '
b1111101011111 "
b1100110001001 #
#146000
b1zzzz0000zzzz *
bz10zz00zz00zz +
bz0z0z0z1z0zzz &
bz1z0z0z0z0z0z ,
b11000zzzzzzzz )
b1001010111011 (
b1010111011 '
b1100000000000 -
b1101010111010 "
b1100000000001 #
#148000
b0zzzzzzzz )
bz00zz11zz10zz +
bz00zz00zzzzzz %
b0zzzz1111zzzz *
bz0z0z1z1z1z0z ,
bz1z0z0z0z0zzz &
b1110110110011 (
b10111000 -
b1110001000011 '
b1110011111010 "
b10111001 #
#150000
b11110zzzzzzzz )
bz11zz00zz01zz +
bz0z1z0z0z0z0z ,
b1zzzz0000zzzz *
b1000101011011 (
b1001000000100 -
b110101010011 '
b1111000000101 "
b1001101010110 #
#152000
bz00zz01zzzzzz %
bz11zz00zz11zz +
b1111zzzzzzzz )
bz1z1z0z0z0z1z ,
bz0z0z0z1z1zzz &
b0zzzz0111zzzz *
b1111010000000 (
b1111110 '
b111100000001 -
b111100101001 "
b111101010111 #
#154000
b0zzzz0001zzzz *
bz00zz00zzzzzz %
bz00zz00zz11zz +
bz0z0z1z0z1zzz &
b0zzzzzzzz )
bz0z0z0z0z0z1z ,
b10111100001 (
b10111011101 '
b10 -
b10111010010 "
b1111 #
#156000
b1zzzz1001zzzz *
b11100zzzzzzzz )
bz1z0z1z0z1z0z ,
bz0z0z0z0z0zzz &
bz11zz10zz10zz +
b100100101 (
b10010001000 -
b1100000010101 '
b1010010011001 "
b110010001100 #
#158000
b0zzzz1000zzzz *
b111zzzzzzzz )
bz0z1z1z0z0z0z ,
bz01zz10zz00zz +
b1101001010111 (
b1010000000 -
b1010101010111 '
b11110000110 "
b1001011010001 #
#160000
bz00zz11zz11zz +
b10000zzzzzzzz )
b1zzzz1110zzzz *
bz0z0z0z1z1z1z ,
bz1z0z1z0z0zzz &
b111100011000 (
b1000000101010 -
b111011000100 '
b1001001101010 "
b1110010101110 #
#162000
b10110zzzzzzzz )
bz01zz01zz00zz +
b1zzzz0101zzzz *
bz0z1z0z0z0z0z ,
bz0z0z0z0z0zzz &
b110010100000 (
b1011001010000 -
b0 '
b1011001010000 "
b1011001010000 #
#164000
b0zzzzzzzz )
bz0z0z0z0z1z1z ,
bz00zz00zz11zz +
bz0z0z1z0z0zzz &
b0zzzz0000zzzz *
b11011111001 (
b11011100101 '
b1010 -
b1001011 "
b11010101110 #
#166000
bz11zz01zzzzzz %
b0zzzz0111zzzz *
bz0z0z0z0z1z0z ,
bz1z1z0z1z0zzz &
b111110001001 (
b1100 -
b111101110001 '
b1101001101 "
b110000111100 #
#168000
b11100zzzzzzzz )
bz0z1z1z1z0zzz &
bz00zz11zzzzzz %
bz11zz00zz00zz +
b1001111110111 (
bz1z0z0z0z0z0z ,
b1zzzz0000zzzz *
b101111110111 '
b1010000000000 -
b1010011100100 "
b1111100010011 #
#170000
b0zzzz0001zzzz *
b0zzzzzzzz )
bz00zz00zz10zz +
bz00zz00zzzzzz %
bz0z0z0z0z1z0z ,
bz1z0z0z0z0zzz &
b1111001100101 (
b1000 -
b1111001010101 '
b100000001000 "
b1011001011101 #
#172000
b0zzzz0111zzzz *
bz01zz00zzzzzz %
bz00zz01zz00zz +
bz0z0z0z1z0z0z ,
bz0z1z0z0z1zzz &
b1011111101111 (
b1110000 -
b1011100001111 '
b10001111100 "
b1001101110011 #
#174000
b0zzzz0101zzzz *
b100zzzzzzzz )
bz0z1z0z0z0zzz &
bz0z0z0z0z1z1z ,
bz01zz01zz11zz +
bz00zz00zzzzzz %
b1101110111001 (
b10001011010 -
b1001100000101 '
b11001011010 "
b1010101011111 #
#176000
b1zzzzzzzz )
b0zzzz1001zzzz *
bz0z0z0z0z0zzz &
bz00zz00zzzzzz %
bz00zz10zz11zz +
bz0z0z1z0z1z0z ,
b1011001100010 (
b1010101011010 '
b10000100 -
b1000111011100 "
b10010000110 #
