Draft_Phuong/unpack_s3/ppa_sk.sv
module sub_2i8_o8(x1, y, out, carry);
    input[7:0] x1;
    input[7:0] y;
    output[7:0] out;
    output carry;
    wire[7:0] x2;
    wire[7:0] g1,p1;
    wire[3:0] g2,g3,g4;
    wire[3:1] p2;
    wire[3:2] p3;

    assign x2 = ~y;

    ha_with_carry_1 HA1 ( .a( x1[0] ), .b( x2[0] ), .g( g1[0] ), .p( p1[0] ) );
    ha HA2 ( .a( x1[1] ), .b( x2[1] ), .g( g1[1] ), .p( p1[1] ) );
    ha HA3 ( .a( x1[2] ), .b( x2[2] ), .g( g1[2] ), .p( p1[2] ) );
    ha HA4 ( .a( x1[3] ), .b( x2[3] ), .g( g1[3] ), .p( p1[3] ) );
    ha HA5 ( .a( x1[4] ), .b( x2[4] ), .g( g1[4] ), .p( p1[4] ) );
    ha HA6 ( .a( x1[5] ), .b( x2[5] ), .g( g1[5] ), .p( p1[5] ) );
    ha HA7 ( .a( x1[6] ), .b( x2[6] ), .g( g1[6] ), .p( p1[6] ) );
    ha HA8 ( .a( x1[7] ), .b( x2[7] ), .g( g1[7] ), .p( p1[7] ) );

    grey_cell A1 (.gi1( g1[1] ), .pi1( p1[1] ), .gi2( g1[0] ), .go( g2[0] ) );
    black_cell A2 (.gi1( g1[3] ), .pi1( p1[3] ), .gi2( g1[2] ), .pi2( p1[2] ), .go( g2[1] ), .po( p2[1] ) );
    black_cell A3 (.gi1( g1[5] ), .pi1( p1[5] ), .gi2( g1[4] ), .pi2( p1[4] ), .go( g2[2] ), .po( p2[2] ) );
    black_cell A4 (.gi1( g1[7] ), .pi1( p1[7] ), .gi2( g1[6] ), .pi2( p1[6] ), .go( g2[3] ), .po( p2[3] ) );
    grey_cell A5 (.gi1( g1[2] ), .pi1( p1[2] ), .gi2( g2[0] ), .go( g3[0] ) );
    grey_cell A6 (.gi1( g2[1] ), .pi1( p2[1] ), .gi2( g2[0] ), .go( g3[1] ) );
    black_cell A7 (.gi1( g1[6] ), .pi1( p1[6] ), .gi2( g2[2] ), .pi2( p2[2] ), .go( g3[2] ), .po( p3[2] ) );
    black_cell A8 (.gi1( g2[3] ), .pi1( p2[3] ), .gi2( g2[2] ), .pi2( p2[2] ), .go( g3[3] ), .po( p3[3] ) );
    grey_cell A9 (.gi1( g1[4] ), .pi1( p1[4] ), .gi2( g3[1] ), .go( g4[0] ) );
    grey_cell A10 (.gi1( g2[2] ), .pi1( p2[2] ), .gi2( g3[1] ), .go( g4[1] ) );
    grey_cell A11 (.gi1( g3[2] ), .pi1( p3[2] ), .gi2( g3[1] ), .go( g4[2] ) );
    grey_cell A12 (.gi1( g3[3] ), .pi1( p3[3] ), .gi2( g3[1] ), .go( g4[3] ) );

    assign out[7:1] = p1[7:1] ^ { g4[2:0], g3[1], g3[0], g2[0], g1[0] };
    assign out[0] = p1[0];
    assign carry = g4[3];

endmodule

module black_cell(gi1, pi1, gi2, pi2, go, po);
//gi1 is a combined generate signal from j to i
//pi1 is a combined propagate signal from j to i
//gi2 is a combined generate signal from m to j-1
//pi2 is a combined propagate signal from m to j-1
//go is a combined generate signal from m to i
//po is a combined propagate signal from m to i
    input gi1, pi1, gi2, pi2;
    output go, po;

    assign po = pi1 & pi2;
    assign go = ( gi2 & pi1 ) | gi1;
endmodule

module grey_cell(gi1, pi1, gi2, go);
//gi1 is a combined generate signal from j to i
//pi1 is a combined propagate signal from j to i
//gi2 is a combined generate signal from m to j-1
//go is a combined generate signal from m to i
//po is a combined propagate signal from m to i
    input gi1, pi1, gi2;
    output go;

    assign go = ( gi2 & pi1 ) | gi1;
endmodule

module ha(a, b, g, p);
    input a, b;
    output g, p;

    assign g = a & b;
    assign p = a ^ b;
endmodule

module ha_with_carry_1(a, b, g, p);
    input a, b;
    output g, p;

    assign g = a | b;
    assign p = ~(a ^ b);
endmodule

Draft_Phuong/unpack_Rq0/add_2i13_o13.sv
`include "ppa_sk.sv"
module add_2i13_o13(x1, x2, out);
	parameter NUM_BIT = 13;

    input[NUM_BIT-1 : 0] x1;
    input[NUM_BIT-1 : 0] x2;
    output[NUM_BIT-1 : 0] out;
    wire[NUM_BIT-1 : 0] g0,p0,g1,p1,g2,p2,g3,p3,g4;

	generate
		genvar i;
		for (i = 0; i < NUM_BIT; i = i + 1)
		begin: HA_SLICE
			ha A0 ( .a( x1[i] ), .b( x2[i] ), .g( g0[i] ), .p( p0[i] ) );
		end
	endgenerate

    grey_cell A1_1 ( .gi1( g0[1] ), .pi1( p0[1] ), .gi2( g0[0] ), .go( g1[1] ) );
    black_cell A1_3 ( .gi1( g0[3] ), .pi1( p0[3] ), .gi2( g0[2] ), .pi2( p0[2] ), .go( g1[3] ), .po( p1[3] ) );
    black_cell A1_5 ( .gi1( g0[5] ), .pi1( p0[5] ), .gi2( g0[4] ), .pi2( p0[4] ), .go( g1[5] ), .po( p1[5] ) );
    black_cell A1_7 ( .gi1( g0[7] ), .pi1( p0[7] ), .gi2( g0[6] ), .pi2( p0[6] ), .go( g1[7] ), .po( p1[7] ) );
	black_cell A1_9 ( .gi1( g0[9] ), .pi1( p0[9] ), .gi2( g0[8] ), .pi2( p0[8] ), .go( g1[9] ), .po( p1[9] ) );
	black_cell A1_11 ( .gi1( g0[11] ), .pi1( p0[11] ), .gi2( g0[10] ), .pi2( p0[10] ), .go( g1[11] ), .po( p1[11] ) );

	grey_cell A2_2 ( .gi1( g0[2] ), .pi1( p0[2] ), .gi2( g1[1] ), .go( g2[2] ) );
    grey_cell A2_3 ( .gi1( g1[3] ), .pi1( p1[3] ), .gi2( g1[1] ), .go( g2[3] ) );
    black_cell A2_6 ( .gi1( g0[6] ), .pi1( p0[6] ), .gi2( g1[5] ), .pi2( p1[5] ), .go( g2[6] ), .po( p2[6] ) );
    black_cell A2_7 ( .gi1( g1[7] ), .pi1( p1[7] ), .gi2( g1[5] ), .pi2( p1[5] ), .go( g2[7] ), .po( p2[7] ) );
	black_cell A2_10 ( .gi1( g0[10] ), .pi1( p0[10] ), .gi2( g1[9] ), .pi2( p1[9] ), .go( g2[10] ), .po( p2[10] ) );
	black_cell A2_11 ( .gi1( g1[11] ), .pi1( p1[11] ), .gi2( g1[9] ), .pi2( p1[9] ), .go( g2[11] ), .po( p2[11] ) );

	grey_cell A3_4 (.gi1( g0[4] ), .pi1( p0[4] ), .gi2( g2[3] ), .go( g3[4] ) );
    grey_cell A3_5 (.gi1( g1[5] ), .pi1( p1[5] ), .gi2( g2[3] ), .go( g3[5] ) );
    grey_cell A3_6 (.gi1( g2[6] ), .pi1( p2[6] ), .gi2( g2[3] ), .go( g3[6] ) );
    grey_cell A3_7 (.gi1( g2[7] ), .pi1( p2[7] ), .gi2( g2[3] ), .go( g3[7] ) );
	black_cell A3_12 ( .gi1( g0[12] ), .pi1( p0[12] ), .gi2( g2[11] ), .pi2( p2[11] ), .go( g3[12] ), .po( p3[12] ) );

	grey_cell A4_8 (.gi1( g0[8] ), .pi1( p0[8] ), .gi2( g3[7] ), .go( g4[8] ) );
	grey_cell A4_9 (.gi1( g1[9] ), .pi1( p1[9] ), .gi2( g3[7] ), .go( g4[9] ) );
	grey_cell A4_10 (.gi1( g2[10] ), .pi1( p2[10] ), .gi2( g3[7] ), .go( g4[10] ) );
	grey_cell A4_11 (.gi1( g2[11] ), .pi1( p2[11] ), .gi2( g3[7] ), .go( g4[11] ) );
	grey_cell A4_12 (.gi1( g3[12] ), .pi1( p3[12] ), .gi2( g3[7] ), .go( g4[12] ) );

    assign out[NUM_BIT-1 : 1] = p0[NUM_BIT-1 : 1] ^ { g4[11:8], g3[7:4], g2[3:2], g1[1], g0[0] };
    assign out[0] = p0[0];

endmodule // add_2i13_o13

Draft_Phuong/unpack_Rq0/unpack_rq0.sv
`include "add_2i13_o13.sv"
module unpack_rq0 (clk, rst, x, out);
	input clk, rst;
	input [12:0] x, check_holder;
	output [12:0] out;
	reg [12:0] store;
	wire [12:0] next;

	always @ ( posedge clk ) begin
		if (rst) begin
			store <= 13'b1_1111_1111_1111;
		end
		else begin
			store <= next;
		end
	end

	add_2i13_o13 ADD ( .x1( x ), .x2( store ), .out( next ) );
	assign out = ~store;

	initial begin
		$dumpfile("dump.vcd");
		$dumpvars(1);
	end
endmodule // unpack_rq0

Draft_Phuong/unpack_Rq0/dump.vcd
$date
	Wed Oct 20 00:55:14 2021
$end
$version
	Icarus Verilog
$end
$timescale
	1ps
$end
$scope module unpack_rq0 $end
$var wire 13 ! check_holder [12:0] $end
$var wire 1 " clk $end
$var wire 13 # out [12:0] $end
$var wire 1 $ rst $end
$var wire 13 % x [12:0] $end
$var wire 13 & next [12:0] $end
$var reg 13 ' store [12:0] $end
$upscope $end
$enddefinitions $end
#0
$dumpvars
b1111111111111 '
bx &
bz %
1$
b0 #
1"
bz !
$end
#500
0"
#1000
1"
#1300
b1000111010100 &
0$
b1000111010101 %
#1500
0"
#2000
b1110101001 &
b111000101011 #
b1000111010100 '
b111000101011 !
1"
#2300
b1101101010101 &
b100110000001 %
#2500
0"
#3000
b10011010110 &
b10010101010 #
b1101101010101 '
b10010101010 !
1"
#3300
b1100100001010 &
b1110110110101 %
#3500
0"
#4000
b1011010111111 &
b11011110101 #
b1100100001010 '
b11011110101 !
1"
#4300
b1100111110111 &
b11101101 %
#4500
0"
#5000
b1101011100100 &
b11000001000 #
b1100111110111 '
b11000001000 !
1"
#5300
b11010100100 &
b110010101101 %
#5500
0"
#6000
b1001101010001 &
b1100101011011 #
b11010100100 '
b1100101011011 !
1"
#6300
b111011101 &
b1101100111001 %
#6500
0"
#7000
b1110100010110 &
b1111000100010 #
b111011101 '
b1111000100010 !
1"
#7300
b110010010010 &
b101010110101 %
#7500
0"
#8000
b1011101000111 &
b1001101101101 #
b110010010010 '
b1001101101101 !
1"
#8300
b1101101110011 &
b111011100001 %
#8500
0"
#9000
b101001010100 &
b10010001100 #
b1101101110011 '
b10010001100 !
1"
#9300
b1100000101000 &
b1110010110101 %
#9500
0"
#10000
b1010011011101 &
b11111010111 #
b1100000101000 '
b11111010111 !
1"
#10300
b100101101100 &
b1000101000100 %
#10500
0"
#11000
b1101010110000 &
b1011010010011 #
b100101101100 '
b1011010010011 !
1"
#11300
b100100110110 &
b1111111001010 %
#11500
0"
#12000
b100100000000 &
b1011011001001 #
b100100110110 '
b1011011001001 !
1"
#12300
b1011001111110 &
b110101001000 %
#12500
0"
#13000
b1111000110 &
b100110000001 #
b1011001111110 '
b100110000001 !
1"
#13300
b1001111001101 &
b1110101001111 %
#13500
0"
#14000
b1000100011100 &
b110000110010 #
b1001111001101 '
b110000110010 !
1"
#14300
b1010001001101 &
b10000000 %
#14500
0"
#15000
b1010011001101 &
b101110110010 #
b1010001001101 '
b101110110010 !
1"
#15300
b111010110101 &
b1101001101000 %
#15500
0"
#16000
b100100011101 &
b1000101001010 #
b111010110101 '
b1000101001010 !
1"
#16300
b1100100001111 &
b101001011010 %
#16500
0"
#17000
b1101101001 &
b11011110000 #
b1100100001111 '
b11011110000 !
1"
#17300
b1011111111111 &
b1111011110000 %
#17500
0"
#18000
b1011011101111 &
b100000000000 #
b1011111111111 '
b100000000000 !
1"
#18300
b100001011000 &
b1000001011001 %
#18500
0"
#19000
b1100010110001 &
b1011110100111 #
b100001011000 '
b1011110100111 !
1"
#19300
b111110 &
b1011111100110 %
#19500
0"
#20000
b1100000100100 &
b1111111000001 #
b111110 '
b1111111000001 !
1"
#20300
b1101111110011 &
b1101110110101 %
#20500
0"
#21000
b1011110101000 &
b10000001100 #
b1101111110011 '
b10000001100 !
1"
#21300
b10111101011 &
b100111111000 %
#21500
0"
#22000
b111111100011 &
b1101000010100 #
b10111101011 '
b1101000010100 !
1"
#22300
b10101001001 &
b1111101011110 %
#22500
0"
#23000
b10010100111 &
b1101010110110 #
b10101001001 '
b1101010110110 !
1"
#23300
b1111110110001 &
b1101001101000 %
#23500
0"
#24000
b1101000011001 &
b1001110 #
b1111110110001 '
b1001110 !
1"
#24300
b1001111011000 &
b1010000100111 %
#24500
0"
#25000
b11111111111 &
b110000100111 #
b1001111011000 '
b110000100111 !
1"
#25300
b1110110110010 &
b100111011010 %
#25500
0"
#26000
b11110001100 &
b1001001101 #
b1110110110010 '
b1001001101 !
1"
#26300
b11110000110 &
b100111010100 %
#26500
0"
#27000
b1000101011010 &
b1100001111001 #
b11110000110 '
b1100001111001 !
1"
#27300
b1110100110110 &
b1010110110000 %
#27500
0"
#28000
b1001011100110 &
b1011001001 #
b1110100110110 '
b1011001001 !
1"
#28300
b1111111001000 &
b1010010010 %
#28500
0"
#29000
b1001011010 &
b110111 #
b1111111001000 '
b110111 !
1"
#29300
b10101111 &
b11100111 %
#29500
0"
#30000
b110010110 &
b1111101010000 #
b10101111 '
b1111101010000 !
1"
#30300
b11100110001 &
b11010000010 %
#30500
0"
#31000
b110110110011 &
b1100011001110 #
b11100110001 '
b1100011001110 !
1"
#31300
b100100100011 &
b111110010 %
#31500
0"
#32000
b101100010101 &
b1011011011100 #
b100100100011 '
b1011011011100 !
1"
#32300
b1100100101101 &
b1000000001010 %
#32500
0"
#33000
b100100110111 &
b11011010010 #
b1100100101101 '
b11011010010 !
1"
#33300
b1100101101010 &
b111101 %
#33500
0"
#34000
b1100110100111 &
b11010010101 #
b1100101101010 '
b11010010101 !
1"
#34300
b1011000000101 &
b1110010011011 %
#34500
0"
#35000
b1001010100000 &
b100111111010 #
b1011000000101 '
b100111111010 !
1"
#35300
b1100000111101 &
b1000111000 %
#35500
0"
#36000
b1101001110101 &
b11111000010 #
b1100000111101 '
b11111000010 !
1"
#36300
b11110001101 &
b111101010000 %
#36500
0"
#37000
b1011011011101 &
b1100001110010 #
b11110001101 '
b1100001110010 !
1"
#37300
b1100100110100 &
b1000110100111 %
#37500
0"
#38000
b101011011011 &
b11011001011 #
b1100100110100 '
b11011001011 !
1"
#38300
b1100011101000 &
b1111110110100 %
#38500
0"
#39000
b1100010011100 &
b11100010111 #
b1100011101000 '
b11100010111 !
1"
#39300
b100011101101 &
b1000000000101 %
#39500
0"
#40000
b1100011110010 &
b1011100010010 #
b100011101101 '
b1011100010010 !
1"
#40300
b1000000 &
b1011101010011 %
#40500
0"
#41000
b1011110010011 &
b1111110111111 #
b1000000 '
b1111110111111 !
1"
#41300
b1100010100011 &
b1100001100011 %
#41500
0"
#42000
b1000100000110 &
b11101011100 #
b1100010100011 '
b11101011100 !
1"
#42300
b1011101110110 &
b1111011010011 %
#42500
0"
#43000
b1011001001001 &
b100010001001 #
b1011101110110 '
b100010001001 !
1"
#43300
b1000110100010 &
b1101000101100 %
#43500
0"
#44000
b101111001110 &
b111001011101 #
b1000110100010 '
b111001011101 !
1"
#44300
b1110110110 &
b1001000010100 %
#44500
0"
#45000
b1010111001010 &
b1110001001001 #
b1110110110 '
b1110001001001 !
1"
#45300
b1001000110100 &
b111001111110 %
#45500
0"
#46000
b10110010 &
b110111001011 #
b1001000110100 '
b110111001011 !
1"
#46300
b1000111 &
b111000010011 %
#46500
0"
#47000
b111001011010 &
b1111110111000 #
b1000111 '
b1111110111000 !
1"
#47300
b100100011111 &
b100011011000 %
#47500
0"
#48000
b1000111110111 &
b1011011100000 #
b100100011111 '
b1011011100000 !
1"
#48300
b1011111000111 &
b111010101000 %
#48500
0"
#49000
b11001101111 &
b100000111000 #
b1011111000111 '
b100000111000 !
1"
#49300
b1111001100111 &
b11010100000 %
#49500
0"
#50000
b10100000111 &
b110011000 #
b1111001100111 '
b110011000 !
1"
#50300
b110011111110 &
b111010010111 %
#50500
0"
#51000
b1101110010101 &
b1001100000001 #
b110011111110 '
b1001100000001 !
1"
#51300
b110101011110 &
b1100000 %
#51500
0"
#52000
b110110111110 &
b1001010100001 #
b110101011110 '
b1001010100001 !
1"
#52300
b1010100010 &
b1010101000100 %
#52500
0"
#53000
b1011111100110 &
b1110101011101 #
b1010100010 '
b1110101011101 !
1"
#53300
b1011110000011 &
b1010011100001 %
#53500
0"
#54000
b110001100100 &
b100001111100 #
b1011110000011 '
b100001111100 !
1"
#54300
b10110100111 &
b111000100100 %
#54500
0"
#55000
b1001111001011 &
b1101001011000 #
b10110100111 '
b1101001011000 !
1"
#55300
b1000100110100 &
b101110001101 %
#55500
0"
#56000
b1110011000001 &
b111011001011 #
b1000100110100 '
b111011001011 !
1"
#56300
b110111110010 &
b1110010111110 %
#56500
0"
#57000
b101010110000 &
b1001000001101 #
b110111110010 '
b1001000001101 !
1"
#57300
b1111110100000 &
b1000110101110 %
#57500
0"
#58000
b1000101001110 &
b1011111 #
b1111110100000 '
b1011111 !
1"
#58300
b1100011100010 &
b1100101000010 %
#58500
0"
#59000
b1001000100100 &
b11100011101 #
b1100011100010 '
b11100011101 !
1"
#59300
b111101101 &
b100100001011 %
#59500
0"
#60000
b101011111000 &
b1111000010010 #
b111101101 '
b1111000010010 !
1"
#60300
b1101010001000 &
b1100010011011 %
#60500
0"
#61000
b1001100100011 &
b10101110111 #
b1101010001000 '
b10101110111 !
1"
#61300
b1000001001 &
b11110000001 %
#61500
0"
#62000
b100110001010 &
b1110111110110 #
b1000001001 '
b1110111110110 !
1"
#62300
b100111100101 &
b11111011100 %
#62500
0"
#63000
b1000111000001 &
b1011000011010 #
b100111100101 '
b1011000011010 !
1"
#63300
b1101110001001 &
b1000110100100 %
#63500
0"
#64000
b110100101101 &
b10001110110 #
b1101110001001 '
b10001110110 !
1"
#64300
b10110010011 &
b101000001010 %
#64500
0"
#65000
b111110011101 &
b1101001101100 #
b10110010011 '
b1101001101100 !
1"
#65300
b1101101101011 &
b1010111011000 %
#65500
0"
#66000
b1000101000011 &
b10010010100 #
b1101101101011 '
b10010010100 !
1"
#66300
b1010011100001 &
b1100101110110 %
#66500
0"
#67000
b111001010111 &
b101100011110 #
b1010011100001 '
b101100011110 !
1"
#67300
b1100100000 &
b111000111111 %
#67500
0"
#68000
b1000101011111 &
b1110011011111 #
b1100100000 '
b1110011011111 !
1"
#68300
b1101001001001 &
b1011100101001 %
#68500
0"
#69000
b1000101110010 &
b10110110110 #
b1101001001001 '
b10110110110 !
1"
#69300
b100101111010 &
b111100110001 %
#69500
0"
#70000
b1100010101011 &
b1011010000101 #
b100101111010 '
b1011010000101 !
1"
#70300
b10010111011 &
b1101101000001 %
#70500
0"
#71000
b1111111111100 &
b1101101000100 #
b10010111011 '
b1101101000100 !
1"
#71300
b1100101010 &
b1111001101111 %
#71500
0"
#72000
b110011001 &
b1110011010101 #
b1100101010 '
b1110011010101 !
1"
#72300
b1000000010000 &
b110011100110 %
#72500
0"
#73000
b1110011110110 &
b111111101111 #
b1000000010000 '
b111111101111 !
1"
#73300
b1100001100101 &
b100001010101 %
#73500
0"
#74000
b10111010 &
b11110011010 #
b1100001100101 '
b11110011010 !
1"
#74300
b1111111000100 &
b11101011111 %
#74500
0"
#75000
b11100100011 &
b111011 #
b1111111000100 '
b111011 !
1"
#75300
b1110110101001 &
b1110111100101 %
#75500
0"
#76000
b1101110001110 &
b1001010110 #
b1110110101001 '
b1001010110 !
1"
#76300
b110010000100 &
b111011011011 %
#76500
0"
#77000
b1101101011111 &
b1001101111011 #
b110010000100 '
b1001101111011 !
1"
#77300
b101100011010 &
b1111010010110 %
#77500
0"
#78000
b100110110000 &
b1010011100101 #
b101100011010 '
b1010011100101 !
1"
#78300
b101011101 &
b1011001000011 %
#78500
0"
#79000
b1011110100000 &
b1111010100010 #
b101011101 '
b1111010100010 !
1"
#79300
b1000010101010 &
b111101001101 %
#79500
0"
#80000
b1111111110111 &
b111101010101 #
b1000010101010 '
b111101010101 !
1"
#80300
b1101111010111 &
b101100101101 %
#80500
0"
#81000
b11100000100 &
b10000101000 #
b1101111010111 '
b10000101000 !
1"
#81300
b1001011001011 &
b1011011110100 %
#81500
0"
#82000
b100110111111 &
b110100110100 #
b1001011001011 '
b110100110100 !
1"
#82300
b1010101000110 &
b1001111011 %
#82500
0"
#83000
b1011111000001 &
b101010111001 #
b1010101000110 '
b101010111001 !
1"
#83300
b1001111011010 &
b1111010010100 %
#83500
0"
#84000
b1001001101110 &
b110000100101 #
b1001111011010 '
b110000100101 !
1"
#84300
b1111011111001 &
b101100011111 %
#84500
0"
#85000
b101000011000 &
b100000110 #
b1111011111001 '
b100000110 !
1"
#85300
b111111011110 &
b1000011100101 %
#85500
0"
#86000
b11000011 &
b1000000100001 #
b111111011110 '
b1000000100001 !
1"
#86300
b1001111111001 &
b10000011011 %
#86500
0"
#87000
b1100000010100 &
b110000000110 #
b1001111111001 '
b110000000110 !
1"
#87300
b1111111000 &
b111111111111 %
#87500
0"
#88000
b1001111110111 &
b1110000000111 #
b1111111000 '
b1110000000111 !
1"
#88300
b1100011110 &
b1111100100110 %
#88500
0"
#89000
b1001000100 &
b1110011100001 #
b1100011110 '
b1110011100001 !
1"
#89300
b1001111111 &
b1111101100001 %
#89500
0"
#90000
b111100000 &
b1110110000000 #
b1001111111 '
b1110110000000 !
1"
#90300
b110010111101 &
b101000111110 %
#90500
0"
#91000
b1011011111011 &
b1001101000010 #
b110010111101 '
b1001101000010 !
1"
#91300
b1111101111010 &
b1001010111101 %
#91500
0"
#92000
b1001000110111 &
b10000101 #
b1111101111010 '
b10000101 !
1"
#92300
b1010110000001 &
b1011000000111 %
#92500
0"
#93000
b101110001000 &
b101001111110 #
b1010110000001 '
b101001111110 !
1"
#93300
b101000000 &
b101110111111 %
#93500
0"
#94000
b110011111111 &
b1111010111111 #
b101000000 '
b1111010111111 !
1"
#94300
b1011100111011 &
b1010111111011 %
#94500
0"
#95000
b110100110110 &
b100011000100 #
b1011100111011 '
b100011000100 !
1"
#95300
b101000011100 &
b1001011100001 %
#95500
0"
#96000
b1110011111101 &
b1010111100011 #
b101000011100 '
b1010111100011 !
1"
#96300
b1010000011010 &
b100111111110 %
#96500
0"
#97000
b1111000011000 &
b101111100101 #
b1010000011010 '
b101111100101 !
1"
#97300
b11101100000 &
b1001101000110 %
#97500
0"
#98000
b1101010100110 &
b1100010011111 #
b11101100000 '
b1100010011111 !
1"
#98300
b1001000010001 &
b101010110001 %
#98500
0"
#99000
b1110011000010 &
b110111101110 #
b1001000010001 '
b110111101110 !
1"
#99300
b1100111001000 &
b11110110111 %
#99500
0"
#100000
b101111111 &
b11000110111 #
b1100111001000 '
b11000110111 !
1"
#100300
b111001111011 &
b1010010110011 %
#100500
0"
#101000
b1100101110 &
b1000110000100 #
b111001111011 '
b1000110000100 !
1"
#101300
b100100110110 &
b1101010111011 %
#101500
0"
#102000
b1111110001 &
b1011011001001 #
b100100110110 '
b1011011001001 !
1"
#102300
b1111110000010 &
b1011001001100 %
#102500
0"
#103000
b1010111001110 &
b1111101 #
b1111110000010 '
b1111101 !
1"
#103300
b111001001000 &
b111011000110 %
#103500
0"
#104000
b1110100001110 &
b1000110110111 #
b111001001000 '
b1000110110111 !
1"
#104300
b1011010010011 &
b100001001011 %
#104500
0"
#105000
b1111011011110 &
b100101101100 #
b1011010010011 '
b100101101100 !
1"
#105300
b1110000111001 &
b10110100110 %
#105500
0"
#106000
b111011111 &
b1111000110 #
b1110000111001 '
b1111000110 !
1"
#106300
b101001001001 &
b111000010000 %
#106500
0"
#107000
b1100001011001 &
b1010110110110 #
b101001001001 '
b1010110110110 !
1"
#107300
b1000011001001 &
b11010000000 %
#107500
0"
#108000
b1011101001001 &
b111100110110 #
b1000011001001 '
b111100110110 !
1"
#108300
b10001101000 &
b1001110011111 %
#108500
0"
#109000
b1100000000111 &
b1101110010111 #
b10001101000 '
b1101110010111 !
1"
#109300
b1100001010111 &
b1001111101111 %
#109500
0"
#110000
b110001000110 &
b11110101000 #
b1100001010111 '
b11110101000 !
1"
#110300
b1100011110111 &
b10100000 %
#110500
0"
#111000
b1100110010111 &
b11100001000 #
b1100011110111 '
b11100001000 !
1"
#111300
b1100101101001 &
b1110010 %
#111500
0"
#112000
b1100111011011 &
b11010010110 #
b1100101101001 '
b11010010110 !
1"
#112300
b1110010111011 &
b1101010010 %
#112500
0"
#113000
b1101 &
b1101000100 #
b1110010111011 '
b1101000100 !
1"
#113300
b11100111101 &
b101010000010 %
#113500
0"
#114000
b1000110111111 &
b1100011000010 #
b11100111101 '
b1100011000010 !
1"
#114300
b10100010010 &
b1110111010101 %
#114500
0"
#115000
b1011100111 &
b1101011101101 #
b10100010010 '
b1101011101101 !
1"
#115300
b101001100010 &
b10101010000 %
#115500
0"
#116000
b111110110010 &
b1010110011101 #
b101001100010 '
b1010110011101 !
1"
#116300
b110000011110 &
b110111100 %
#116500
0"
#117000
b110111011010 &
b1001111100001 #
b110000011110 '
b1001111100001 !
1"
#117300
b1010011101110 &
b100011010000 %
#117500
0"
#118000
b1110110111110 &
b101100010001 #
b1010011101110 '
b101100010001 !
1"
#118300
b100101111011 &
b1010010001101 %
#118500
0"
#119000
b1111000001000 &
b1011010000100 #
b100101111011 '
b1011010000100 !
1"
#119300
b1111001001111 &
b1010011010100 %
#119500
0"
#120000
b1001100100011 &
b110110000 #
b1111001001111 '
b110110000 !
1"
#120300
b101000000010 &
b101110110011 %
#120500
0"
#121000
b1010110110101 &
b1010111111101 #
b101000000010 '
b1010111111101 !
1"
#121300
b1111010100001 &
b1010010011111 %
#121500
0"
#122000
b1001101000000 &
b101011110 #
b1111010100001 '
b101011110 !
1"
#122300
b1001000001001 &
b1001101101000 %
#122500
0"
#123000
b10101110001 &
b110111110110 #
b1001000001001 '
b110111110110 !
1"
#123300
b100001111 &
b111100000110 %
#123500
0"
#124000
b1000000010101 &
b1111011110000 #
b100001111 '
b1111011110000 !
1"
#124300
b1011100000110 &
b1010111110111 %
#124500
0"
#125000
b110011111101 &
b100011111001 #
b1011100000110 '
b100011111001 !
1"
#125300
b111100110000 &
b1100000101010 %
#125500
0"
#126000
b11101011010 &
b1000011001111 #
b111100110000 '
b1000011001111 !
1"
#126300
b1000111111010 &
b1011001010 %
#126500
0"
#127000
b1010011000100 &
b111000000101 #
b1000111111010 '
b111000000101 !
1"
#127300
b111111011100 &
b1110111100010 %
#127500
0"
#128000
b110110111110 &
b1000000100011 #
b111111011100 '
b1000000100011 !
1"
#128300
b1110001000110 &
b110001101010 %
#128500
0"
#129000
b100010110000 &
b1110111001 #
b1110001000110 '
b1110111001 !
1"
#129300
b1110110111000 &
b101110010 %
#129500
0"
#130000
b1111100101010 &
b1001000111 #
b1110110111000 '
b1001000111 !
1"
#130300
b111011010000 &
b1000100011000 %
#130500
0"
#131000
b1111111101000 &
b1000100101111 #
b111011010000 '
b1000100101111 !
1"
#131300
b111000110000 &
b1111101100000 %
#131500
0"
#132000
b110110010000 &
b1000111001111 #
b111000110000 '
b1000111001111 !
1"
#132300
b1000111100010 &
b1110110010 %
#132500
0"
#133000
b1010110010100 &
b111000011101 #
b1000111100010 '
b111000011101 !
1"
#133300
b1001000000010 &
b100000 %
#133500
0"
#134000
b1001000100010 &
b110111111101 #
b1001000000010 '
b110111111101 !
1"
#134300
b1111010011 &
b1000111010001 %
#134500
0"
#135000
b1010110100100 &
b1110000101100 #
b1111010011 '
b1110000101100 !
1"
#135300
b1000011110010 &
b110100011111 %
#135500
0"
#136000
b1111000010001 &
b111100001101 #
b1000011110010 '
b111100001101 !
1"
#136300
b10110111001 &
b1010011000111 %
#136500
0"
#137000
b1101010000000 &
b1101001000110 #
b10110111001 '
b1101001000110 !
1"
#137300
b1111111101101 &
b1101000110100 %
#137500
0"
#138000
b1101000100001 &
b10010 #
b1111111101101 '
b10010 !
1"
#138300
b10000100011 &
b10000110110 %
#138500
0"
#139000
b100001011001 &
b1101111011100 #
b10000100011 '
b1101111011100 !
1"
#139300
b111001010101 &
b101000110010 %
#139500
0"
#140000
b1100010000111 &
b1000110101010 #
b111001010101 '
b1000110101010 !
1"
#140300
b101001101011 &
b1110000010110 %
#140500
0"
#141000
b11010000001 &
b1010110010100 #
b101001101011 '
b1010110010100 !
1"
#141300
b10010101111 &
b1101001000100 %
#141500
0"
#142000
b1111011110011 &
b1101101010000 #
b10010101111 '
b1101101010000 !
1"
#142300
b1011001010 &
b1111000011011 %
#142500
0"
#143000
b11100101 &
b1110100110101 #
b1011001010 '
b1110100110101 !
1"
#143300
b1011101001101 &
b1010010000011 %
#143500
0"
#144000
b101111010000 &
b100010110010 #
b1011101001101 '
b100010110010 !
1"
#144300
b1011111111001 &
b10101100 %
#144500
0"
#145000
b1100010100101 &
b100000000110 #
b1011111111001 '
b100000000110 !
1"
#145300
b11101110010 &
b111101111001 %
#145500
0"
#146000
b1011011101011 &
b1100010001101 #
b11101110010 '
b1100010001101 !
1"
#146300
b1100110101010 &
b1001000111000 %
#146500
0"
#147000
b101111100010 &
b11001010101 #
b1100110101010 '
b11001010101 !
1"
#147300
b100110010110 &
b111111101100 %
#147500
0"
#148000
b1100110000010 &
b1011001101001 #
b100110010110 '
b1011001101001 !
1"
#148300
b1011001010100 &
b110010111110 %
#148500
0"
#149000
b1100010010 &
b100110101011 #
b1011001010100 '
b100110101011 !
1"
#149300
b1110100100010 &
b11011001110 %
#149500
0"
#150000
b1111110000 &
b1011011101 #
b1110100100010 '
b1011011101 !
1"
#150300
b101110110000 &
b111010001110 %
#150500
0"
#151000
b1101000111110 &
b1010001001111 #
b101110110000 '
b1010001001111 !
1"
#151300
b1001011100001 &
b11100110001 %
#151500
0"
#152000
b1101000010010 &
b110100011110 #
b1001011100001 '
b110100011110 !
1"
#152300
b101110001010 &
b1100010101001 %
#152500
0"
#153000
b10000110011 &
b1010001110101 #
b101110001010 '
b1010001110101 !
1"
#153300
b110101101001 &
b111011111 %
#153500
0"
#154000
b111101001000 &
b1001010010110 #
b110101101001 '
b1001010010110 !
1"
#154300
b1011011010101 &
b100101101100 %
#154500
0"
