Draft_Phuong/unpack_s3/ppa_sk.sv
module sub_2i8_o8(x1, y, out, carry);
    input[7:0] x1;
    input[7:0] y;
    output[7:0] out;
    output carry;
    wire[7:0] x2;
    wire[7:0] g1,p1;
    wire[3:0] g2,g3,g4;
    wire[3:1] p2;
    wire[3:2] p3;

    assign x2 = ~y;

    ha_with_carry_1 HA1 ( .a( x1[0] ), .b( x2[0] ), .g( g1[0] ), .p( p1[0] ) );
    ha HA2 ( .a( x1[1] ), .b( x2[1] ), .g( g1[1] ), .p( p1[1] ) );
    ha HA3 ( .a( x1[2] ), .b( x2[2] ), .g( g1[2] ), .p( p1[2] ) );
    ha HA4 ( .a( x1[3] ), .b( x2[3] ), .g( g1[3] ), .p( p1[3] ) );
    ha HA5 ( .a( x1[4] ), .b( x2[4] ), .g( g1[4] ), .p( p1[4] ) );
    ha HA6 ( .a( x1[5] ), .b( x2[5] ), .g( g1[5] ), .p( p1[5] ) );
    ha HA7 ( .a( x1[6] ), .b( x2[6] ), .g( g1[6] ), .p( p1[6] ) );
    ha HA8 ( .a( x1[7] ), .b( x2[7] ), .g( g1[7] ), .p( p1[7] ) );

    grey_cell A1 (.gi1( g1[1] ), .pi1( p1[1] ), .gi2( g1[0] ), .go( g2[0] ) );
    black_cell A2 (.gi1( g1[3] ), .pi1( p1[3] ), .gi2( g1[2] ), .pi2( p1[2] ), .go( g2[1] ), .po( p2[1] ) );
    black_cell A3 (.gi1( g1[5] ), .pi1( p1[5] ), .gi2( g1[4] ), .pi2( p1[4] ), .go( g2[2] ), .po( p2[2] ) );
    black_cell A4 (.gi1( g1[7] ), .pi1( p1[7] ), .gi2( g1[6] ), .pi2( p1[6] ), .go( g2[3] ), .po( p2[3] ) );
    grey_cell A5 (.gi1( g1[2] ), .pi1( p1[2] ), .gi2( g2[0] ), .go( g3[0] ) );
    grey_cell A6 (.gi1( g2[1] ), .pi1( p2[1] ), .gi2( g2[0] ), .go( g3[1] ) );
    black_cell A7 (.gi1( g1[6] ), .pi1( p1[6] ), .gi2( g2[2] ), .pi2( p2[2] ), .go( g3[2] ), .po( p3[2] ) );
    black_cell A8 (.gi1( g2[3] ), .pi1( p2[3] ), .gi2( g2[2] ), .pi2( p2[2] ), .go( g3[3] ), .po( p3[3] ) );
    grey_cell A9 (.gi1( g1[4] ), .pi1( p1[4] ), .gi2( g3[1] ), .go( g4[0] ) );
    grey_cell A10 (.gi1( g2[2] ), .pi1( p2[2] ), .gi2( g3[1] ), .go( g4[1] ) );
    grey_cell A11 (.gi1( g3[2] ), .pi1( p3[2] ), .gi2( g3[1] ), .go( g4[2] ) );
    grey_cell A12 (.gi1( g3[3] ), .pi1( p3[3] ), .gi2( g3[1] ), .go( g4[3] ) );

    assign out[7:1] = p1[7:1] ^ { g4[2:0], g3[1], g3[0], g2[0], g1[0] };
    assign out[0] = p1[0];
    assign carry = g4[3];

endmodule

module black_cell(gi1, pi1, gi2, pi2, go, po);
//gi1 is a combined generate signal from j to i
//pi1 is a combined propagate signal from j to i
//gi2 is a combined generate signal from m to j-1
//pi2 is a combined propagate signal from m to j-1
//go is a combined generate signal from m to i
//po is a combined propagate signal from m to i
    input gi1, pi1, gi2, pi2;
    output go, po;

    assign po = pi1 & pi2;
    assign go = ( gi2 & pi1 ) | gi1;
endmodule

module grey_cell(gi1, pi1, gi2, go);
//gi1 is a combined generate signal from j to i
//pi1 is a combined propagate signal from j to i
//gi2 is a combined generate signal from m to j-1
//go is a combined generate signal from m to i
//po is a combined propagate signal from m to i
    input gi1, pi1, gi2;
    output go;

    assign go = ( gi2 & pi1 ) | gi1;
endmodule

module ha(a, b, g, p);
    input a, b;
    output g, p;

    assign g = a & b;
    assign p = a ^ b;
endmodule

module ha_with_carry_1(a, b, g, p);
    input a, b;
    output g, p;

    assign g = a | b;
    assign p = ~(a ^ b);
endmodule

Draft_Phuong/unpack_Rq0/add_2i13_o13.sv
`include "ppa_sk.sv"
module add_2i13_o13(x1, x2, out);
	parameter NUM_BIT = 13;

    input[NUM_BIT-1 : 0] x1;
    input[NUM_BIT-1 : 0] x2;
    output[NUM_BIT-1 : 0] out;
    wire[NUM_BIT-1 : 0] g0,p0,g1,p1,g2,p2,g3,p3,g4;

	generate
		genvar i;
		for (i = 0; i < NUM_BIT; i = i + 1)
		begin: HA_SLICE
			ha A0 ( .a( x1[i] ), .b( x2[i] ), .g( g0[i] ), .p( p0[i] ) );
		end
	endgenerate

    grey_cell A1_1 ( .gi1( g0[1] ), .pi1( p0[1] ), .gi2( g0[0] ), .go( g1[1] ) );
    black_cell A1_3 ( .gi1( g0[3] ), .pi1( p0[3] ), .gi2( g0[2] ), .pi2( p0[2] ), .go( g1[3] ), .po( p1[3] ) );
    black_cell A1_5 ( .gi1( g0[5] ), .pi1( p0[5] ), .gi2( g0[4] ), .pi2( p0[4] ), .go( g1[5] ), .po( p1[5] ) );
    black_cell A1_7 ( .gi1( g0[7] ), .pi1( p0[7] ), .gi2( g0[6] ), .pi2( p0[6] ), .go( g1[7] ), .po( p1[7] ) );
	black_cell A1_9 ( .gi1( g0[9] ), .pi1( p0[9] ), .gi2( g0[8] ), .pi2( p0[8] ), .go( g1[9] ), .po( p1[9] ) );
	black_cell A1_11 ( .gi1( g0[11] ), .pi1( p0[11] ), .gi2( g0[10] ), .pi2( p0[10] ), .go( g1[11] ), .po( p1[11] ) );

	grey_cell A2_2 ( .gi1( g0[2] ), .pi1( p0[2] ), .gi2( g1[1] ), .go( g2[2] ) );
    grey_cell A2_3 ( .gi1( g1[3] ), .pi1( p1[3] ), .gi2( g1[1] ), .go( g2[3] ) );
    black_cell A2_6 ( .gi1( g0[6] ), .pi1( p0[6] ), .gi2( g1[5] ), .pi2( p1[5] ), .go( g2[6] ), .po( p2[6] ) );
    black_cell A2_7 ( .gi1( g1[7] ), .pi1( p1[7] ), .gi2( g1[5] ), .pi2( p1[5] ), .go( g2[7] ), .po( p2[7] ) );
	black_cell A2_10 ( .gi1( g0[10] ), .pi1( p0[10] ), .gi2( g1[9] ), .pi2( p1[9] ), .go( g2[10] ), .po( p2[10] ) );
	black_cell A2_11 ( .gi1( g1[11] ), .pi1( p1[11] ), .gi2( g1[9] ), .pi2( p1[9] ), .go( g2[11] ), .po( p2[11] ) );

	grey_cell A3_4 (.gi1( g0[4] ), .pi1( p0[4] ), .gi2( g2[3] ), .go( g3[4] ) );
    grey_cell A3_5 (.gi1( g1[5] ), .pi1( p1[5] ), .gi2( g2[3] ), .go( g3[5] ) );
    grey_cell A3_6 (.gi1( g2[6] ), .pi1( p2[6] ), .gi2( g2[3] ), .go( g3[6] ) );
    grey_cell A3_7 (.gi1( g2[7] ), .pi1( p2[7] ), .gi2( g2[3] ), .go( g3[7] ) );
	black_cell A3_12 ( .gi1( g0[12] ), .pi1( p0[12] ), .gi2( g2[11] ), .pi2( p2[11] ), .go( g3[12] ), .po( p3[12] ) );

	grey_cell A4_8 (.gi1( g0[8] ), .pi1( p0[8] ), .gi2( g3[7] ), .go( g4[8] ) );
	grey_cell A4_9 (.gi1( g1[9] ), .pi1( p1[9] ), .gi2( g3[7] ), .go( g4[9] ) );
	grey_cell A4_10 (.gi1( g2[10] ), .pi1( p2[10] ), .gi2( g3[7] ), .go( g4[10] ) );
	grey_cell A4_11 (.gi1( g2[11] ), .pi1( p2[11] ), .gi2( g3[7] ), .go( g4[11] ) );
	grey_cell A4_12 (.gi1( g3[12] ), .pi1( p3[12] ), .gi2( g3[7] ), .go( g4[12] ) );

    assign out[NUM_BIT-1 : 1] = p0[NUM_BIT-1 : 1] ^ { g4[11:8], g3[7:4], g2[3:2], g1[1], g0[0] };
    assign out[0] = p0[0];

endmodule // add_2i13_o13

Draft_Phuong/unpack_Rq0_ver2/unpack_rq0.sv
`include "add_2i13_o13.sv"
module unpack_rq0 (clk, rst, even, odd, h_mem);
	parameter H_BITS = 9113;
	input clk, rst, last_n, done_n;
	input [12:0] even, odd, check_holder;
	output [H_BITS:1] h_mem;
	wire [12:0] out;
	reg [12:0] store_even, store_odd;
	wire [12:0] next, next_even, next_odd;

	always @ ( posedge clk ) begin
		if (rst) begin
			store_even <= 13'b1_1111_1111_1111;
			store_odd <= 13'b0;
		end
		else begin #0.2
			store_even <= next_even;
			store_odd <= next_odd;
		end
	end

	add_2i13_o13 ADD1 ( .x1( even ), .x2( store_even ), .out( next_even ) );
	add_2i13_o13 ADD2 ( .x1( odd ), .x2( store_odd ), .out( next_odd ) );
	add_2i13_o13 ADD3 ( .x1( store_even ), .x2( store_odd ), .out( next ) );
	sipoH SIPOH ( .ovr_rst(rst), .clk(clk), .last_n(last_n), .done_n(done_n), .init1( {odd, even} ), .init2(out), .out(h_mem) );
	assign out = ~next;

	initial begin
		$dumpfile("dump.vcd");
		$dumpvars(1);
	end
endmodule // unpack_rq0

module sipoH (ovr_rst, clk, last_n, done_n, init1, init2, out);
	parameter H_BITS = 9113, EVEN_HALF_H_BITS = 4563;
	input ovr_rst, clk, last_n, done_n;
	input[25:0] init1;
	input[12:0] init2;
	output reg[H_BITS:1] out;
	wire[12:0] even, odd;

	always @ ( posedge ovr_rst or posedge clk1 ) begin
		if(ovr_rst) begin
			out[EVEN_HALF_H_BITS:1] <= 0;
		end
		else begin
			#0.1 out[EVEN_HALF_H_BITS:1] <= { even, out[EVEN_HALF_H_BITS:14] };
		end
	end

	always @ ( posedge ovr_rst or posedge clk2 ) begin
		if(ovr_rst) begin
			out[H_BITS : EVEN_HALF_H_BITS+1] <= 0;
		end
		else begin
			#0.1 out[H_BITS : EVEN_HALF_H_BITS+1] <= { odd, out[H_BITS : EVEN_HALF_H_BITS+14] };
		end
	end

	assign even = last_n ? init1[12:0] : init2;
	assign odd = init1[25:13];
	assign clk1 = clk & done_n;
	assign clk2 = clk1 & last_n;
endmodule

Draft_Phuong/unpack_Rq0_ver2/dump.vcd
$date
	Wed Oct 20 14:12:36 2021
$end
$version
	Icarus Verilog
$end
$timescale
	1ps
$end
$scope module unpack_rq0 $end
$var wire 13 ! check_holder [12:0] $end
$var wire 1 " clk $end
$var wire 1 # done_n $end
$var wire 13 $ even [12:0] $end
$var wire 1 % last_n $end
$var wire 13 & odd [12:0] $end
$var wire 13 ' out [12:0] $end
$var wire 1 ( rst $end
$var wire 13 ) next_odd [12:0] $end
$var wire 13 * next_even [12:0] $end
$var wire 13 + next [12:0] $end
$var wire 9113 , h_mem [9113:1] $end
$var reg 13 - store_even [12:0] $end
$var reg 13 . store_odd [12:0] $end
$upscope $end
$enddefinitions $end
#0
$dumpvars
b0 .
b1111111111111 -
b0 ,
b1111111111111 +
bx *
bx )
1(
b0 '
bz &
1%
bz $
1#
1"
bz !
$end
#500
0"
#1000
1"
#1200
b1111001100010 *
b1111011111100 )
b1111001100011 $
b1111011111100 &
b0 !
#1300
0(
#1500
0"
#2000
1"
#2100
b11110111111000000000000000000000000000000000000000000000000000000000000000000000000000000000000000000000000000000000000000000000000000000000000000000000000000000000000000000000000000000000000000000000000000000000000000000000000000000000000000000000000000000000000000000000000000000000000000000000000000000000000000000000000000000000000000000000000000000000000000000000000000000000000000000000000000000000000000000000000000000000000000000000000000000000000000000000000000000000000000000000000000000000000000000000000000000000000000000000000000000000000000000000000000000000000000000000000000000000000000000000000000000000000000000000000000000000000000000000000000000000000000000000000000000000000000000000000000000000000000000000000000000000000000000000000000000000000000000000000000000000000000000000000000000000000000000000000000000000000000000000000000000000000000000000000000000000000000000000000000000000000000000000000000000000000000000000000000000000000000000000000000000000000000000000000000000000000000000000000000000000000000000000000000000000000000000000000000000000000000000000000000000000000000000000000000000000000000000000000000000000000000000000000000000000000000000000000000000000000000000000000000000000000000000000000000000000000000000000000000000000000000000000000000000000000000000000000000000000000000000000000000000000000000000000000000000000000000000000000000000000000000000000000000000000000000000000000000000000000000000000000000000000000000000000000000000000000000000000000000000000000000000000000000000000000000000000000000000000000000000000000000000000000000000000000000000000000000000000000000000000000000000000000000000000000000000000000000000000000000000000000000000000000000000000000000000000000000000000000000000000000000000000000000000000000000000000000000000000000000000000000000000000000000000000000000000000000000000000000000000000000000000000000000000000000000000000000000000000000000000000000000000000000000000000000000000000000000000000000000000000000000000000000000000000000000000000000000000000000000000000000000000000000000000000000000000000000000000000000000000000000000000000000000000000000000000000000000000000000000000000000000000000000000000000000000000000000000000000000000000000000000000000000000000000000000000000000000000000000000000000000000000000000000000000000000000000000000000000000000000000000000000000000000000000000000000000000000000000000000000000000000000000000000000000000000000000000000000000000000000000000000000000000000000000000000000000000000000000000000000000000000000000000000000000000000000000000000000000000000000000000000000000000000000000000000000000000000000000000000000000000000000000000000000000000000000000000000000000000000000000000000000000000000000000000000000000000000000000000000000000000000000000000000000000000000000000000000000000000000000000000000000000000000000000000000000000000000000000000000000000000000000000000000000000000000000000000000000000000000000000000000000000000000000000000000000000000000000000000000000000000000000000000000000000000000000000000000000000000000000000000000000000000000000000000000000000000000000000000000000000000000000000000000000000000000000000000000000000000000000000000000000000000000000000000000000000000000000000000000000000000000000000000000000000000000000000000000000000000000000000000000000000000000000000000000000000000000000000000000000000000000000000000000000000000000000000000000000000000000000000000000000000000000000000000000000000000000000000000000000000000000000000000000000000000000000000000000000000000000000000000000000000000000000000000000000000000000000000000000000000000000000000000000000000000000000000000000000000000000000000000000000000000000000000000000000000000000000000000000000000000000000000000000000000000000000000000000000000000000000000000000000000000000000000000000000000000000000000000000000000000000000000000000000000000000000000000000000000000000000000000000000000000000000000000000000000000000000000000000000000000000000000000000000000000000000000000000000000000000000000000000000000000000000000000000000000000000000000000000000000000000000000000000000000000000000000000000000000000000000000000000000000000000000000000000000000000000000000000000000000000000000000000000000000000000000000000000000000000000000000000000000000000000000000000000000000000000000000000000000000000000000000000000000000000000000000000000000000000000000000000000000000000000000000000000000000000000000000000000000000000000000000000000000000000000000000000000000000000000000000000000000000000000000000000000000000000000111100110001100000000000000000000000000000000000000000000000000000000000000000000000000000000000000000000000000000000000000000000000000000000000000000000000000000000000000000000000000000000000000000000000000000000000000000000000000000000000000000000000000000000000000000000000000000000000000000000000000000000000000000000000000000000000000000000000000000000000000000000000000000000000000000000000000000000000000000000000000000000000000000000000000000000000000000000000000000000000000000000000000000000000000000000000000000000000000000000000000000000000000000000000000000000000000000000000000000000000000000000000000000000000000000000000000000000000000000000000000000000000000000000000000000000000000000000000000000000000000000000000000000000000000000000000000000000000000000000000000000000000000000000000000000000000000000000000000000000000000000000000000000000000000000000000000000000000000000000000000000000000000000000000000000000000000000000000000000000000000000000000000000000000000000000000000000000000000000000000000000000000000000000000000000000000000000000000000000000000000000000000000000000000000000000000000000000000000000000000000000000000000000000000000000000000000000000000000000000000000000000000000000000000000000000000000000000000000000000000000000000000000000000000000000000000000000000000000000000000000000000000000000000000000000000000000000000000000000000000000000000000000000000000000000000000000000000000000000000000000000000000000000000000000000000000000000000000000000000000000000000000000000000000000000000000000000000000000000000000000000000000000000000000000000000000000000000000000000000000000000000000000000000000000000000000000000000000000000000000000000000000000000000000000000000000000000000000000000000000000000000000000000000000000000000000000000000000000000000000000000000000000000000000000000000000000000000000000000000000000000000000000000000000000000000000000000000000000000000000000000000000000000000000000000000000000000000000000000000000000000000000000000000000000000000000000000000000000000000000000000000000000000000000000000000000000000000000000000000000000000000000000000000000000000000000000000000000000000000000000000000000000000000000000000000000000000000000000000000000000000000000000000000000000000000000000000000000000000000000000000000000000000000000000000000000000000000000000000000000000000000000000000000000000000000000000000000000000000000000000000000000000000000000000000000000000000000000000000000000000000000000000000000000000000000000000000000000000000000000000000000000000000000000000000000000000000000000000000000000000000000000000000000000000000000000000000000000000000000000000000000000000000000000000000000000000000000000000000000000000000000000000000000000000000000000000000000000000000000000000000000000000000000000000000000000000000000000000000000000000000000000000000000000000000000000000000000000000000000000000000000000000000000000000000000000000000000000000000000000000000000000000000000000000000000000000000000000000000000000000000000000000000000000000000000000000000000000000000000000000000000000000000000000000000000000000000000000000000000000000000000000000000000000000000000000000000000000000000000000000000000000000000000000000000000000000000000000000000000000000000000000000000000000000000000000000000000000000000000000000000000000000000000000000000000000000000000000000000000000000000000000000000000000000000000000000000000000000000000000000000000000000000000000000000000000000000000000000000000000000000000000000000000000000000000000000000000000000000000000000000000000000000000000000000000000000000000000000000000000000000000000000000000000000000000000000000000000000000000000000000000000000000000000000000000000000000000000000000000000000000000000000000000000000000000000000000000000000000000000000000000000000000000000000000000000000000000000000000000000000000000000000000000000000000000000000000000000000000000000000000000000000000000000000000000000000000000000000000000000000000000000000000000000000000000000000000000000000000000000000000000000000000000000000000000000000000000000000000000000000000000000000000000000000000000000000000000000000000000000000000000000000000000000000000000000000000000000000000000000000000000000000000000000000000000000000000000000000000000000000000000000000000000000000000000000000000000000000000000000000000000000000000000000000000000000000000000000000000000000000000000000000000000000000000000000000000000000000000000000000000000000000000000000000000000000000000000000000000000000000000000000000000000000000000000000000000000000000000000000000 ,
#2200
b1101110110100 $
b1101111101001 &
b1010100001 !
b1101011100101 )
b1010100001 '
b1101000010110 *
b1110101011110 +
b1111011111100 .
b1111001100010 -
#2500
0"
#3000
1"
#3100
b11011111010011111011111100000000000000000000000000000000000000000000000000000000000000000000000000000000000000000000000000000000000000000000000000000000000000000000000000000000000000000000000000000000000000000000000000000000000000000000000000000000000000000000000000000000000000000000000000000000000000000000000000000000000000000000000000000000000000000000000000000000000000000000000000000000000000000000000000000000000000000000000000000000000000000000000000000000000000000000000000000000000000000000000000000000000000000000000000000000000000000000000000000000000000000000000000000000000000000000000000000000000000000000000000000000000000000000000000000000000000000000000000000000000000000000000000000000000000000000000000000000000000000000000000000000000000000000000000000000000000000000000000000000000000000000000000000000000000000000000000000000000000000000000000000000000000000000000000000000000000000000000000000000000000000000000000000000000000000000000000000000000000000000000000000000000000000000000000000000000000000000000000000000000000000000000000000000000000000000000000000000000000000000000000000000000000000000000000000000000000000000000000000000000000000000000000000000000000000000000000000000000000000000000000000000000000000000000000000000000000000000000000000000000000000000000000000000000000000000000000000000000000000000000000000000000000000000000000000000000000000000000000000000000000000000000000000000000000000000000000000000000000000000000000000000000000000000000000000000000000000000000000000000000000000000000000000000000000000000000000000000000000000000000000000000000000000000000000000000000000000000000000000000000000000000000000000000000000000000000000000000000000000000000000000000000000000000000000000000000000000000000000000000000000000000000000000000000000000000000000000000000000000000000000000000000000000000000000000000000000000000000000000000000000000000000000000000000000000000000000000000000000000000000000000000000000000000000000000000000000000000000000000000000000000000000000000000000000000000000000000000000000000000000000000000000000000000000000000000000000000000000000000000000000000000000000000000000000000000000000000000000000000000000000000000000000000000000000000000000000000000000000000000000000000000000000000000000000000000000000000000000000000000000000000000000000000000000000000000000000000000000000000000000000000000000000000000000000000000000000000000000000000000000000000000000000000000000000000000000000000000000000000000000000000000000000000000000000000000000000000000000000000000000000000000000000000000000000000000000000000000000000000000000000000000000000000000000000000000000000000000000000000000000000000000000000000000000000000000000000000000000000000000000000000000000000000000000000000000000000000000000000000000000000000000000000000000000000000000000000000000000000000000000000000000000000000000000000000000000000000000000000000000000000000000000000000000000000000000000000000000000000000000000000000000000000000000000000000000000000000000000000000000000000000000000000000000000000000000000000000000000000000000000000000000000000000000000000000000000000000000000000000000000000000000000000000000000000000000000000000000000000000000000000000000000000000000000000000000000000000000000000000000000000000000000000000000000000000000000000000000000000000000000000000000000000000000000000000000000000000000000000000000000000000000000000000000000000000000000000000000000000000000000000000000000000000000000000000000000000000000000000000000000000000000000000000000000000000000000000000000000000000000000000000000000000000000000000000000000000000000000000000000000000000000000000000000000000000000000000000000000000000000000000000000000000000000000000000000000000000000000000000000000000000000000000000000000000000000000000000000000000000000000000000000000000000000000000000000000000000000000000000000000000000000000000000000000000000000000000000000000000000000000000000000000000000000000000000000000000000000000000000000000000000000000000000000000000000000000000000000000000000000000000000000000000000000000000000000000000000000000000000000000000000000000000000000000000000000000000000000000000000000000000000000000000000000000000000000000000000000000000000000000000000000000000000000000000000000000000000000000000000000000000000000000000000000000000000000000000000000000000000000000000000000000000000000000000000000000000000000000000000000000000000000000000000000000000000000000000000000000000000000000000000000000000000000000000000000000000000000000000000000000000000000000000000000000000110111011010011110011000110000000000000000000000000000000000000000000000000000000000000000000000000000000000000000000000000000000000000000000000000000000000000000000000000000000000000000000000000000000000000000000000000000000000000000000000000000000000000000000000000000000000000000000000000000000000000000000000000000000000000000000000000000000000000000000000000000000000000000000000000000000000000000000000000000000000000000000000000000000000000000000000000000000000000000000000000000000000000000000000000000000000000000000000000000000000000000000000000000000000000000000000000000000000000000000000000000000000000000000000000000000000000000000000000000000000000000000000000000000000000000000000000000000000000000000000000000000000000000000000000000000000000000000000000000000000000000000000000000000000000000000000000000000000000000000000000000000000000000000000000000000000000000000000000000000000000000000000000000000000000000000000000000000000000000000000000000000000000000000000000000000000000000000000000000000000000000000000000000000000000000000000000000000000000000000000000000000000000000000000000000000000000000000000000000000000000000000000000000000000000000000000000000000000000000000000000000000000000000000000000000000000000000000000000000000000000000000000000000000000000000000000000000000000000000000000000000000000000000000000000000000000000000000000000000000000000000000000000000000000000000000000000000000000000000000000000000000000000000000000000000000000000000000000000000000000000000000000000000000000000000000000000000000000000000000000000000000000000000000000000000000000000000000000000000000000000000000000000000000000000000000000000000000000000000000000000000000000000000000000000000000000000000000000000000000000000000000000000000000000000000000000000000000000000000000000000000000000000000000000000000000000000000000000000000000000000000000000000000000000000000000000000000000000000000000000000000000000000000000000000000000000000000000000000000000000000000000000000000000000000000000000000000000000000000000000000000000000000000000000000000000000000000000000000000000000000000000000000000000000000000000000000000000000000000000000000000000000000000000000000000000000000000000000000000000000000000000000000000000000000000000000000000000000000000000000000000000000000000000000000000000000000000000000000000000000000000000000000000000000000000000000000000000000000000000000000000000000000000000000000000000000000000000000000000000000000000000000000000000000000000000000000000000000000000000000000000000000000000000000000000000000000000000000000000000000000000000000000000000000000000000000000000000000000000000000000000000000000000000000000000000000000000000000000000000000000000000000000000000000000000000000000000000000000000000000000000000000000000000000000000000000000000000000000000000000000000000000000000000000000000000000000000000000000000000000000000000000000000000000000000000000000000000000000000000000000000000000000000000000000000000000000000000000000000000000000000000000000000000000000000000000000000000000000000000000000000000000000000000000000000000000000000000000000000000000000000000000000000000000000000000000000000000000000000000000000000000000000000000000000000000000000000000000000000000000000000000000000000000000000000000000000000000000000000000000000000000000000000000000000000000000000000000000000000000000000000000000000000000000000000000000000000000000000000000000000000000000000000000000000000000000000000000000000000000000000000000000000000000000000000000000000000000000000000000000000000000000000000000000000000000000000000000000000000000000000000000000000000000000000000000000000000000000000000000000000000000000000000000000000000000000000000000000000000000000000000000000000000000000000000000000000000000000000000000000000000000000000000000000000000000000000000000000000000000000000000000000000000000000000000000000000000000000000000000000000000000000000000000000000000000000000000000000000000000000000000000000000000000000000000000000000000000000000000000000000000000000000000000000000000000000000000000000000000000000000000000000000000000000000000000000000000000000000000000000000000000000000000000000000000000000000000000000000000000000000000000000000000000000000000000000000000000000000000000000000000000000000000000000000000000000000000000000000000000000000000000000000000000000000000000000000000000000000000000000000000000000000000000000000000000000000000000000000000000000000000000000000000000000000000000000000000000000000000000000000000000000000000000000000000000000000000000000000000000000000 ,
#3200
b1101010100 $
b11010011100 &
b101100000100 !
b101100000100 '
b1110101101010 *
b110000001 )
b1010011111011 +
b1101011100101 .
b1101000010110 -
#3500
0"
#4000
1"
#4100
b110100111001101111101001111101111110000000000000000000000000000000000000000000000000000000000000000000000000000000000000000000000000000000000000000000000000000000000000000000000000000000000000000000000000000000000000000000000000000000000000000000000000000000000000000000000000000000000000000000000000000000000000000000000000000000000000000000000000000000000000000000000000000000000000000000000000000000000000000000000000000000000000000000000000000000000000000000000000000000000000000000000000000000000000000000000000000000000000000000000000000000000000000000000000000000000000000000000000000000000000000000000000000000000000000000000000000000000000000000000000000000000000000000000000000000000000000000000000000000000000000000000000000000000000000000000000000000000000000000000000000000000000000000000000000000000000000000000000000000000000000000000000000000000000000000000000000000000000000000000000000000000000000000000000000000000000000000000000000000000000000000000000000000000000000000000000000000000000000000000000000000000000000000000000000000000000000000000000000000000000000000000000000000000000000000000000000000000000000000000000000000000000000000000000000000000000000000000000000000000000000000000000000000000000000000000000000000000000000000000000000000000000000000000000000000000000000000000000000000000000000000000000000000000000000000000000000000000000000000000000000000000000000000000000000000000000000000000000000000000000000000000000000000000000000000000000000000000000000000000000000000000000000000000000000000000000000000000000000000000000000000000000000000000000000000000000000000000000000000000000000000000000000000000000000000000000000000000000000000000000000000000000000000000000000000000000000000000000000000000000000000000000000000000000000000000000000000000000000000000000000000000000000000000000000000000000000000000000000000000000000000000000000000000000000000000000000000000000000000000000000000000000000000000000000000000000000000000000000000000000000000000000000000000000000000000000000000000000000000000000000000000000000000000000000000000000000000000000000000000000000000000000000000000000000000000000000000000000000000000000000000000000000000000000000000000000000000000000000000000000000000000000000000000000000000000000000000000000000000000000000000000000000000000000000000000000000000000000000000000000000000000000000000000000000000000000000000000000000000000000000000000000000000000000000000000000000000000000000000000000000000000000000000000000000000000000000000000000000000000000000000000000000000000000000000000000000000000000000000000000000000000000000000000000000000000000000000000000000000000000000000000000000000000000000000000000000000000000000000000000000000000000000000000000000000000000000000000000000000000000000000000000000000000000000000000000000000000000000000000000000000000000000000000000000000000000000000000000000000000000000000000000000000000000000000000000000000000000000000000000000000000000000000000000000000000000000000000000000000000000000000000000000000000000000000000000000000000000000000000000000000000000000000000000000000000000000000000000000000000000000000000000000000000000000000000000000000000000000000000000000000000000000000000000000000000000000000000000000000000000000000000000000000000000000000000000000000000000000000000000000000000000000000000000000000000000000000000000000000000000000000000000000000000000000000000000000000000000000000000000000000000000000000000000000000000000000000000000000000000000000000000000000000000000000000000000000000000000000000000000000000000000000000000000000000000000000000000000000000000000000000000000000000000000000000000000000000000000000000000000000000000000000000000000000000000000000000000000000000000000000000000000000000000000000000000000000000000000000000000000000000000000000000000000000000000000000000000000000000000000000000000000000000000000000000000000000000000000000000000000000000000000000000000000000000000000000000000000000000000000000000000000000000000000000000000000000000000000000000000000000000000000000000000000000000000000000000000000000000000000000000000000000000000000000000000000000000000000000000000000000000000000000000000000000000000000000000000000000000000000000000000000000000000000000000000000000000000000000000000000000000000000000000000000000000000000000000000000000000000000000000000000000000000000000000000000000000000000000000000000000000000000000000000000000000000000000000000000000000000000000000000000000000000000000000000000000000000000000000000000000000000000000000000000000000000000000000000000000110101010011011101101001111001100011000000000000000000000000000000000000000000000000000000000000000000000000000000000000000000000000000000000000000000000000000000000000000000000000000000000000000000000000000000000000000000000000000000000000000000000000000000000000000000000000000000000000000000000000000000000000000000000000000000000000000000000000000000000000000000000000000000000000000000000000000000000000000000000000000000000000000000000000000000000000000000000000000000000000000000000000000000000000000000000000000000000000000000000000000000000000000000000000000000000000000000000000000000000000000000000000000000000000000000000000000000000000000000000000000000000000000000000000000000000000000000000000000000000000000000000000000000000000000000000000000000000000000000000000000000000000000000000000000000000000000000000000000000000000000000000000000000000000000000000000000000000000000000000000000000000000000000000000000000000000000000000000000000000000000000000000000000000000000000000000000000000000000000000000000000000000000000000000000000000000000000000000000000000000000000000000000000000000000000000000000000000000000000000000000000000000000000000000000000000000000000000000000000000000000000000000000000000000000000000000000000000000000000000000000000000000000000000000000000000000000000000000000000000000000000000000000000000000000000000000000000000000000000000000000000000000000000000000000000000000000000000000000000000000000000000000000000000000000000000000000000000000000000000000000000000000000000000000000000000000000000000000000000000000000000000000000000000000000000000000000000000000000000000000000000000000000000000000000000000000000000000000000000000000000000000000000000000000000000000000000000000000000000000000000000000000000000000000000000000000000000000000000000000000000000000000000000000000000000000000000000000000000000000000000000000000000000000000000000000000000000000000000000000000000000000000000000000000000000000000000000000000000000000000000000000000000000000000000000000000000000000000000000000000000000000000000000000000000000000000000000000000000000000000000000000000000000000000000000000000000000000000000000000000000000000000000000000000000000000000000000000000000000000000000000000000000000000000000000000000000000000000000000000000000000000000000000000000000000000000000000000000000000000000000000000000000000000000000000000000000000000000000000000000000000000000000000000000000000000000000000000000000000000000000000000000000000000000000000000000000000000000000000000000000000000000000000000000000000000000000000000000000000000000000000000000000000000000000000000000000000000000000000000000000000000000000000000000000000000000000000000000000000000000000000000000000000000000000000000000000000000000000000000000000000000000000000000000000000000000000000000000000000000000000000000000000000000000000000000000000000000000000000000000000000000000000000000000000000000000000000000000000000000000000000000000000000000000000000000000000000000000000000000000000000000000000000000000000000000000000000000000000000000000000000000000000000000000000000000000000000000000000000000000000000000000000000000000000000000000000000000000000000000000000000000000000000000000000000000000000000000000000000000000000000000000000000000000000000000000000000000000000000000000000000000000000000000000000000000000000000000000000000000000000000000000000000000000000000000000000000000000000000000000000000000000000000000000000000000000000000000000000000000000000000000000000000000000000000000000000000000000000000000000000000000000000000000000000000000000000000000000000000000000000000000000000000000000000000000000000000000000000000000000000000000000000000000000000000000000000000000000000000000000000000000000000000000000000000000000000000000000000000000000000000000000000000000000000000000000000000000000000000000000000000000000000000000000000000000000000000000000000000000000000000000000000000000000000000000000000000000000000000000000000000000000000000000000000000000000000000000000000000000000000000000000000000000000000000000000000000000000000000000000000000000000000000000000000000000000000000000000000000000000000000000000000000000000000000000000000000000000000000000000000000000000000000000000000000000000000000000000000000000000000000000000000000000000000000000000000000000000000000000000000000000000000000000000000000000000000000000000000000000000000000000000000000000000000000000000000000000000000000000000000000000000000000000000000000000000000000000000000000000000000000000000000000000000000000000000000000000000000000000000 ,
#4200
b101110010110 $
b1100011000101 &
b100010100 !
b100010100 '
b1101001000110 )
b100100000000 *
b1111011101011 +
b110000001 .
b1110101101010 -
#4500
0"
#5000
1"
