Draft_Phuong/poly_lift_ver2/ter_arith.sv
module sub_ter (x, y, z);
    input [1:0] x,y;
    output [1:0] z;

    assign z[0] = (x[1] ^ y[1]) | (x[0] ^ y[0]);
    assign z[1] = ( x[1] & (~y[0]) ) | ( (~x[0]) & (~y[1]) & y[0] )
    | ((~x[1]) & x[0] & y[1]);

endmodule // sub_ter

module sub_2i2_o13 (x, y, z);
    input [1:0] x;
    input [1:0] y;
    output [12:0] z;

    assign z[0] = x[0] ^ y[0];
    assign z[1] = ( x[1] & (~y[1]) ) | ( (~x[0]) & (~y[1]) & y[0] )
    | ((~x[1]) & x[0] & y[1]);
    assign z[2] = ( x[1] & (~y[1]) ) | ( (~x[0]) & (~y[1]) & y[0] );
    assign z[12:3] = {10{z[2]}};

endmodule // sub_2i2_o3

module add_ter (x, y, z);
    input [1:0] x,y;
    output [1:0] z;

    assign z[1] = ( x[1] ^ y[0] ) & ( x[0] ^ y[1] );
    assign z[0] = (x[0] ^ y[0]) | (x[1]&y[1]) | ( (~(x[1]|y[1])) & y[0] );

endmodule // add_ter

module mul_ter (x, y, z);
    input [1:0] x,y;
    output [1:0] z;

    assign z[1] = (x[1] & (~y[1]) & y[0]) | ((~x[1]) & y[1] & x[0]);
    assign z[0] = x[0] & y[0];

endmodule // mul_ter

module inverse_phi1 (clk, rst, z);
    input clk, rst;
    output reg [1402:1] z;

    always @ ( posedge clk ) begin
        if (rst) begin
            #0.2 z <= 1402'b0001110001110001110001110001110001110001110001110001110001110001110001110001110001110001110001110001110001110001110001110001110001110001110001110001110001110001110001110001110001110001110001110001110001110001110001110001110001110001110001110001110001110001110001110001110001110001110001110001110001110001110001110001110001110001110001110001110001110001110001110001110001110001110001110001110001110001110001110001110001110001110001110001110001110001110001110001110001110001110001110001110001110001110001110001110001110001110001110001110001110001110001110001110001110001110001110001110001110001110001110001110001110001110001110001110001110001110001110001110001110001110001110001110001110001110001110001110001110001110001110001110001110001110001110001110001110001110001110001110001110001110001110001110001110001110001110001110001110001110001110001110001110001110001110001110001110001110001110001110001110001110001110001110001110001110001110001110001110001110001110001110001110001110001110001110001110001110001110001110001110001110001110001110001110001110001110001110001110001110001110001110001110001110001110001110001110001110001110001110001110001110001110001110001110001110001110001110001110001110001110001110001110001110001110001110001110001110001110001110001110001110001110001110001110001110001110001110001110001110001110001110001110001110001110001110001110001110001110001110001110001110001110001110001;
        end else begin
            #0.2 z <= {z[1398:1],z[1402:1399]};
        end
    end
endmodule // inverse_phi1

Draft_Phuong/poly_lift_ver2/poly_lift.sv
`include "ter_arith.sv"
module poly_lift (clk ,rst, en, m_in, m0);
    parameter M_BITS = 1402, RQ_BITS = 9113, N_SUB_1_DIV_3 = 233, Q_BITS = 13;
    parameter M_INPUT_BITS = 4, NTRU_N = 701;
    input clk, rst, en;
    input [M_INPUT_BITS:1] m_in;
    output [RQ_BITS:1] m0;

    wire [M_INPUT_BITS:1] m;
    wire [M_BITS:1] m1, m2, z;

    initial begin
        $dumpfile("dump.vcd");
        $dumpvars(1);
    end

    assign m = (en) ? m_in : 4'b0;

    inverse_phi1 IV ( .clk(clk), .rst(rst), .z(z) );

    lift_slice HEAD_SLICE ( .clk(clk), .rst(rst),
    .z( { z[2:1], z[M_BITS:M_BITS-1] } ),
    .m(m), .m1( m1[2:1] ) );

    generate
        genvar i;
        for (i = 0; i < NTRU_N-1; i = i + 1)
        begin: CALC_M1

            lift_slice SLICE ( .clk(clk), .rst(rst),
            .z( { z[2*i+4:2*i+1] } ),
            .m(m), .m1( m1[ 2*i+4 : 2*i+3 ] ) );

        end
    endgenerate

    generate
        for (i = 1; i < NTRU_N+1; i = i + 1)
        begin: SUB_LOOP1
            sub_ter SUB_TER ( .x( m1[2*i : 2*i-1] ), .y( m1[M_BITS : M_BITS-1] ),
            .z( m2[2*i : 2*i-1] ) );
        end
    endgenerate

    assign m0[13:1] = { {12{ m2[2] ^ m2[1] }}, m2[1] };

    generate
        for (i = 1; i < NTRU_N; i = i + 1)
        begin: SUB_LOOP2
            sub_2i2_o13 SUB ( .x( m2[2*i : 2*i-1] ), .y( m2[2*i+2 : 2*i+1] ),
            .z( m0[Q_BITS*i+Q_BITS : Q_BITS*i+1] ) );
        end
    endgenerate

endmodule // poly_lift

module lift_slice (clk, rst, z, m, m1);
    input clk, rst;
    input [3:0] z, m;
    output reg [1:0] m1;
    wire [1:0] z1, z2, z3, m_next;

    always @ ( posedge clk ) begin
        if (rst) begin
            m1 <= 0;
        end else begin
            m1 <= m_next;
        end
    end

    mul_ter MUL1 ( .x( m[1:0] ), .y( z[3:2] ), .z(z1) );
    mul_ter MUL2 ( .x( m[3:2] ), .y( z[1:0] ), .z(z2) );

    add_ter ADD1 ( .x( z1 ), .y( z2 ), .z( z3 ) );
    add_ter ADD2 ( .x( m1 ), .y( z3 ), .z( m_next ) );

endmodule // lift_slice

Draft_Phuong/poly_lift_ver2/dump.vcd
$date
	Sat Oct 30 07:19:12 2021
$end
$version
	Icarus Verilog
$end
$timescale
	1ps
$end
$scope module poly_lift $end
$var wire 1 ! clk $end
$var wire 1 " en $end
$var wire 4 # m_in [4:1] $end
$var wire 1 $ rst $end
$var wire 1402 % z [1402:1] $end
$var wire 1402 & m2 [1402:1] $end
$var wire 1402 ' m1 [1402:1] $end
$var wire 9113 ( m0 [9113:1] $end
$var wire 4 ) m [4:1] $end
$upscope $end
$enddefinitions $end
#0
$dumpvars
bx )
bx (
bx '
bx &
bx %
0$
bz #
z"
1!
$end
#200
1$
#500
0!
#1000
b0 (
b0 &
b0 '
1!
#1200
b1101 )
0$
1"
b1101 #
b1110001110001110001110001110001110001110001110001110001110001110001110001110001110001110001110001110001110001110001110001110001110001110001110001110001110001110001110001110001110001110001110001110001110001110001110001110001110001110001110001110001110001110001110001110001110001110001110001110001110001110001110001110001110001110001110001110001110001110001110001110001110001110001110001110001110001110001110001110001110001110001110001110001110001110001110001110001110001110001110001110001110001110001110001110001110001110001110001110001110001110001110001110001110001110001110001110001110001110001110001110001110001110001110001110001110001110001110001110001110001110001110001110001110001110001110001110001110001110001110001110001110001110001110001110001110001110001110001110001110001110001110001110001110001110001110001110001110001110001110001110001110001110001110001110001110001110001110001110001110001110001110001110001110001110001110001110001110001110001110001110001110001110001110001110001110001110001110001110001110001110001110001110001110001110001110001110001110001110001110001110001110001110001110001110001110001110001110001110001110001110001110001110001110001110001110001110001110001110001110001110001110001110001110001110001110001110001110001110001110001110001110001110001110001110001110001110001110001110001110001110001110001110001110001110001110001110001110001110001110001110001110001110001 %
#1500
0!
#2000
b11111111111110000000000001 (
b11 &
b1111111111111111111111111111111111111111111111111111111111111111111111111111111111111111111111111111111111111111111111111111111111111111111111111111111111111111111111111111111111111111111111111111111111111111111111111111111111111111111111111111111111111111111111111111111111111111111111111111111111111111111111111111111111111111111111111111111111111111111111111111111111111111111111111111111111111111111111111111111111111111111111111111111111111111111111111111111111111111111111111111111111111111111111111111111111111111111111111111111111111111111111111111111111111111111111111111111111111111111111111111111111111111111111111111111111111111111111111111111111111111111111111111111111111111111111111111111111111111111111111111111111111111111111111111111111111111111111111111111111111111111111111111111111111111111111111111111111111111111111111111111111111111111111111111111111111111111111111111111111111111111111111111111111111111111111111111111111111111111111111111111111111111111111111111111111111111111111111111111111111111111111111111111111111111111111111111111111111111111111111111111111111111111111111111111111111111111111111111111111111111111111111111111111111111111111111111111111111111111111111111111111111111111111111111111111111111111111111111111111111111111111111111111111111111111111111111111111111111111111111111111111111111111111111111111111111111111111111111111111111111111111111111111101 '
1!
#2200
b0 )
b0 #
b1100011100011100011100011100011100011100011100011100011100011100011100011100011100011100011100011100011100011100011100011100011100011100011100011100011100011100011100011100011100011100011100011100011100011100011100011100011100011100011100011100011100011100011100011100011100011100011100011100011100011100011100011100011100011100011100011100011100011100011100011100011100011100011100011100011100011100011100011100011100011100011100011100011100011100011100011100011100011100011100011100011100011100011100011100011100011100011100011100011100011100011100011100011100011100011100011100011100011100011100011100011100011100011100011100011100011100011100011100011100011100011100011100011100011100011100011100011100011100011100011100011100011100011100011100011100011100011100011100011100011100011100011100011100011100011100011100011100011100011100011100011100011100011100011100011100011100011100011100011100011100011100011100011100011100011100011100011100011100011100011100011100011100011100011100011100011100011100011100011100011100011100011100011100011100011100011100011100011100011100011100011100011100011100011100011100011100011100011100011100011100011100011100011100011100011100011100011100011100011100011100011100011100011100011100011100011100011100011100011100011100011100011100011100011100011100011100011100011100011100011100011100011100011100011100011100011100011100011100011100011100011100011100010001 %
#2500
0!
#3000
1!
#3200
b100 )
b100 #
b111000111000111000111000111000111000111000111000111000111000111000111000111000111000111000111000111000111000111000111000111000111000111000111000111000111000111000111000111000111000111000111000111000111000111000111000111000111000111000111000111000111000111000111000111000111000111000111000111000111000111000111000111000111000111000111000111000111000111000111000111000111000111000111000111000111000111000111000111000111000111000111000111000111000111000111000111000111000111000111000111000111000111000111000111000111000111000111000111000111000111000111000111000111000111000111000111000111000111000111000111000111000111000111000111000111000111000111000111000111000111000111000111000111000111000111000111000111000111000111000111000111000111000111000111000111000111000111000111000111000111000111000111000111000111000111000111000111000111000111000111000111000111000111000111000111000111000111000111000111000111000111000111000111000111000111000111000111000111000111000111000111000111000111000111000111000111000111000111000111000111000111000111000111000111000111000111000111000111000111000111000111000111000111000111000111000111000111000111000111000111000111000111000111000111000111000111000111000111000111000111000111000111000111000111000111000111000111000111000111000111000111000111000111000111000111000111000111000111000111000111000111000111000111000111000111000111000111000111000111000111000111000100011100 %
#3500
0!
#4000
b11111111111110000000000000100000000000011111111111110000000000000100000000000011111111111110000000000000100000000000011111111111110000000000000100000000000011111111111110000000000000100000000000011111111111110000000000000100000000000011111111111110000000000000100000000000011111111111110000000000000100000000000011111111111110000000000000100000000000011111111111110000000000000100000000000011111111111110000000000000100000000000011111111111110000000000000100000000000011111111111110000000000000100000000000011111111111110000000000000100000000000011111111111110000000000000100000000000011111111111110000000000000100000000000011111111111110000000000000100000000000011111111111110000000000000100000000000011111111111110000000000000100000000000011111111111110000000000000100000000000011111111111110000000000000100000000000011111111111110000000000000100000000000011111111111110000000000000100000000000011111111111110000000000000100000000000011111111111110000000000000100000000000011111111111110000000000000100000000000011111111111110000000000000100000000000011111111111110000000000000100000000000011111111111110000000000000100000000000011111111111110000000000000100000000000011111111111110000000000000100000000000011111111111110000000000000100000000000011111111111110000000000000100000000000011111111111110000000000000100000000000011111111111110000000000000100000000000011111111111110000000000000100000000000011111111111110000000000000100000000000011111111111110000000000000100000000000011111111111110000000000000100000000000011111111111110000000000000100000000000011111111111110000000000000100000000000011111111111110000000000000100000000000011111111111110000000000000100000000000011111111111110000000000000100000000000011111111111110000000000000100000000000011111111111110000000000000100000000000011111111111110000000000000100000000000011111111111110000000000000100000000000011111111111110000000000000100000000000011111111111110000000000000100000000000011111111111110000000000000100000000000011111111111110000000000000100000000000011111111111110000000000000100000000000011111111111110000000000000100000000000011111111111110000000000000100000000000011111111111110000000000000100000000000011111111111110000000000000100000000000011111111111110000000000000100000000000011111111111110000000000000100000000000011111111111110000000000000100000000000011111111111110000000000000100000000000011111111111110000000000000100000000000011111111111110000000000000100000000000011111111111110000000000000100000000000011111111111110000000000000100000000000011111111111110000000000000100000000000011111111111110000000000000100000000000011111111111110000000000000100000000000011111111111110000000000000100000000000011111111111110000000000000100000000000011111111111110000000000000100000000000011111111111110000000000000100000000000011111111111110000000000000100000000000011111111111110000000000000100000000000011111111111110000000000000100000000000011111111111110000000000000100000000000011111111111110000000000000100000000000011111111111110000000000000100000000000011111111111110000000000000100000000000011111111111110000000000000100000000000011111111111110000000000000100000000000011111111111110000000000000100000000000011111111111110000000000000100000000000011111111111110000000000000100000000000011111111111110000000000000100000000000011111111111110000000000000100000000000011111111111110000000000000100000000000011111111111110000000000000100000000000011111111111110000000000000100000000000011111111111110000000000000100000000000011111111111110000000000000100000000000011111111111110000000000000100000000000011111111111110000000000000100000000000011111111111110000000000000100000000000011111111111110000000000000100000000000011111111111110000000000000100000000000011111111111110000000000000100000000000011111111111110000000000000100000000000011111111111110000000000000100000000000011111111111110000000000000100000000000011111111111110000000000000100000000000011111111111110000000000000100000000000011111111111110000000000000100000000000011111111111110000000000000100000000000011111111111110000000000000100000000000011111111111110000000000000100000000000011111111111110000000000000100000000000011111111111110000000000000100000000000011111111111110000000000000100000000000011111111111110000000000000100000000000011111111111110000000000000100000000000011111111111110000000000000100000000000011111111111110000000000000100000000000011111111111110000000000000100000000000011111111111110000000000000100000000000011111111111110000000000000100000000000011111111111110000000000000100000000000011111111111110000000000000100000000000011111111111110000000000000100000000000011111111111110000000000000100000000000011111111111110000000000000100000000000011111111111110000000000000100000000000011111111111110000000000000100000000000011111111111110000000000000100000000000011111111111110000000000000100000000000011111111111110000000000000100000000000011111111111110000000000000100000000000011111111111110000000000000100000000000011111111111110000000000000100000000000011111111111110000000000000100000000000011111111111110000000000000100000000000011111111111110000000000000100000000000011111111111110000000000000100000000000011111111111110000000000000100000000000011111111111110000000000000100000000000011111111111110000000000000100000000000011111111111110000000000000100000000000011111111111110000000000000100000000000011111111111110000000000000100000000000011111111111110000000000000100000000000011111111111110000000000000100000000000011111111111110000000000000100000000000011111111111110000000000000100000000000011111111111110000000000000100000000000011111111111110000000000000100000000000011111111111110000000000000100000000000011111111111110000000000000100000000000011111111111110000000000000100000000000011111111111110000000000000100000000000011111111111110000000000000100000000000011111111111110000000000000100000000000011111111111110000000000000100000000000011111111111110000000000000100000000000011111111111110000000000000100000000000011111111111110000000000000100000000000011111111111110000000000000100000000000011111111111110000000000000100000000000011111111111110000000000000100000000000011111111111110000000000000100000000000011111111111110000000000000100000000000011111111111110000000000000100000000000011111111111110000000000000100000000000011111111111110000000000000100000000000011111111111110000000000000100000000000011111111111110000000000000100000000000011111111111110000000000000100000000000011111111111110000000000000100000000000011111111111110000000000000100000000000011111111111110000000000000100000000000011111111111110000000000000100000000000011111111111110000000000000100000000000011111111111110000000000000100000000000011111111111110000000000000100000000000011111111111110000000000000100000000000011111111111110000000000000100000000000011111111111110000000000000100000000000011111111111110000000000000100000000000011111111111110000000000000100000000000011111111111110000000000000100000000000011111111111110000000000000100000000000011111111111110000000000000100000000000011111111111110000000000000100000000000011111111111110000000000000100000000000011111111111110000000000000100000000000011111111111110000000000000100000000000011111111111110000000000000100000000000011111111111110000000000000100000000000011111111111110000000000000100000000000011111111111110000000000000100000000000011111111111110000000000000100000000000011111111111110000000000000100000000000011111111111110000000000000100000000000011111111111110000000000000100000000000011111111111110000000000000100000000000011111111111110000000000000100000000000011111111111110000000000000100000000000011111111111110000000000000100000000000011111111111110000000000000100000000000011111111111110000000000000100000000000011111111111110000000000000100000000000011111111111110000000000000100000000000011111111111110000000000000100000000000011111111111110000000000000100000000000011111111111110000000000000100000000000011111111111110000000000000100000000000011111111111110000000000000100000000000011111111111110000000000000100000000000011111111111110000000000000100000000000011111111111110000000000000100000000000011111111111110000000000000100000000000011111111111110000000000000100000000000011111111111110000000000000100000000000011111111111110000000000000100000000000011111111111110000000000000100000000000011111111111110000000000000100000000000011111111111110000000000000100000000000011111111111110000000000000100000000000011111111111110000000000000100000000000011111111111110000000000000100000000000011111111111110000000000000100000000000011111111111110000000000000100000000000011111111111110000000000000100000000000011111111111110000000000000100000000000011111111111110000000000000100000000000011111111111110000000000000100000000000011111111111110000000000000100000000000011111111111110000000000000100000000000011111111111110000000000000100000000000011111111111110000000000000100000000000011111111111110000000000000100000000000011111111111110000000000000100000000000011111111111110000000000001011111111111100000000000001000000000000100000000000001111111111111 (
b1110001110001110001110001110001110001110001110001110001110001110001110001110001110001110001110001110001110001110001110001110001110001110001110001110001110001110001110001110001110001110001110001110001110001110001110001110001110001110001110001110001110001110001110001110001110001110001110001110001110001110001110001110001110001110001110001110001110001110001110001110001110001110001110001110001110001110001110001110001110001110001110001110001110001110001110001110001110001110001110001110001110001110001110001110001110001110001110001110001110001110001110001110001110001110001110001110001110001110001110001110001110001110001110001110001110001110001110001110001110001110001110001110001110001110001110001110001110001110001110001110001110001110001110001110001110001110001110001110001110001110001110001110001110001110001110001110001110001110001110001110001110001110001110001110001110001110001110001110001110001110001110001110001110001110001110001110001110001110001110001110001110001110001110001110001110001110001110001110001110001110001110001110001110001110001110001110001110001110001110001110001110001110001110001110001110001110001110001110001110001110001110001110001110001110001110001110001110001110001110001110001110001110001110001110001110001110001110001110001110001110001110001110001110001110001110001110001110001110001110001110001110001110001110001110001110001110001110001110001110001110001110111000101 &
b111000111000111000111000111000111000111000111000111000111000111000111000111000111000111000111000111000111000111000111000111000111000111000111000111000111000111000111000111000111000111000111000111000111000111000111000111000111000111000111000111000111000111000111000111000111000111000111000111000111000111000111000111000111000111000111000111000111000111000111000111000111000111000111000111000111000111000111000111000111000111000111000111000111000111000111000111000111000111000111000111000111000111000111000111000111000111000111000111000111000111000111000111000111000111000111000111000111000111000111000111000111000111000111000111000111000111000111000111000111000111000111000111000111000111000111000111000111000111000111000111000111000111000111000111000111000111000111000111000111000111000111000111000111000111000111000111000111000111000111000111000111000111000111000111000111000111000111000111000111000111000111000111000111000111000111000111000111000111000111000111000111000111000111000111000111000111000111000111000111000111000111000111000111000111000111000111000111000111000111000111000111000111000111000111000111000111000111000111000111000111000111000111000111000111000111000111000111000111000111000111000111000111000111000111000111000111000111000111000111000111000111000111000111000111000111000111000111000111000111000111000111000111000111000111000111000111000111000111000111000111000111001100011111 '
1!
#4200
b0 )
b0 #
b1110001110001110001110001110001110001110001110001110001110001110001110001110001110001110001110001110001110001110001110001110001110001110001110001110001110001110001110001110001110001110001110001110001110001110001110001110001110001110001110001110001110001110001110001110001110001110001110001110001110001110001110001110001110001110001110001110001110001110001110001110001110001110001110001110001110001110001110001110001110001110001110001110001110001110001110001110001110001110001110001110001110001110001110001110001110001110001110001110001110001110001110001110001110001110001110001110001110001110001110001110001110001110001110001110001110001110001110001110001110001110001110001110001110001110001110001110001110001110001110001110001110001110001110001110001110001110001110001110001110001110001110001110001110001110001110001110001110001110001110001110001110001110001110001110001110001110001110001110001110001110001110001110001110001110001110001110001110001110001110001110001110001110001110001110001110001110001110001110001110001110001110001110001110001110001110001110001110001110001110001110001110001110001110001110001110001110001110001110001110001110001110001110001110001110001110001110001110001110001110001110001110001110001110001110001110001110001110001110001110001110001110001110001110001110001110001110001110001110001110001110001110001110001110001110001110001110001110001110001110001110001000111000111 %
#4500
0!
#5000
1!
#5200
b1100011100011100011100011100011100011100011100011100011100011100011100011100011100011100011100011100011100011100011100011100011100011100011100011100011100011100011100011100011100011100011100011100011100011100011100011100011100011100011100011100011100011100011100011100011100011100011100011100011100011100011100011100011100011100011100011100011100011100011100011100011100011100011100011100011100011100011100011100011100011100011100011100011100011100011100011100011100011100011100011100011100011100011100011100011100011100011100011100011100011100011100011100011100011100011100011100011100011100011100011100011100011100011100011100011100011100011100011100011100011100011100011100011100011100011100011100011100011100011100011100011100011100011100011100011100011100011100011100011100011100011100011100011100011100011100011100011100011100011100011100011100011100011100011100011100011100011100011100011100011100011100011100011100011100011100011100011100011100011100011100011100011100011100011100011100011100011100011100011100011100011100011100011100011100011100011100011100011100011100011100011100011100011100011100011100011100011100011100011100011100011100011100011100011100011100011100011100011100011100011100011100011100011100011100011100011100011100011100011100011100011100011100011100011100011100011100011100011100011100011100011100011100011100011100011100011100011100011100011100011100010001110001110001 %
#5500
0!
#6000
1!
#6200
b1 )
b1 #
b111000111000111000111000111000111000111000111000111000111000111000111000111000111000111000111000111000111000111000111000111000111000111000111000111000111000111000111000111000111000111000111000111000111000111000111000111000111000111000111000111000111000111000111000111000111000111000111000111000111000111000111000111000111000111000111000111000111000111000111000111000111000111000111000111000111000111000111000111000111000111000111000111000111000111000111000111000111000111000111000111000111000111000111000111000111000111000111000111000111000111000111000111000111000111000111000111000111000111000111000111000111000111000111000111000111000111000111000111000111000111000111000111000111000111000111000111000111000111000111000111000111000111000111000111000111000111000111000111000111000111000111000111000111000111000111000111000111000111000111000111000111000111000111000111000111000111000111000111000111000111000111000111000111000111000111000111000111000111000111000111000111000111000111000111000111000111000111000111000111000111000111000111000111000111000111000111000111000111000111000111000111000111000111000111000111000111000111000111000111000111000111000111000111000111000111000111000111000111000111000111000111000111000111000111000111000111000111000111000111000111000111000111000111000111000111000111000111000111000111000111000111000111000111000111000111000111000111000111000111000100011100011100011100 %
#6500
0!
#7000
b11111111111110000000000010111111111111111111111111110000000000010111111111111111111111111110000000000010111111111111111111111111110000000000010111111111111111111111111110000000000010111111111111111111111111110000000000010111111111111111111111111110000000000010111111111111111111111111110000000000010111111111111111111111111110000000000010111111111111111111111111110000000000010111111111111111111111111110000000000010111111111111111111111111110000000000010111111111111111111111111110000000000010111111111111111111111111110000000000010111111111111111111111111110000000000010111111111111111111111111110000000000010111111111111111111111111110000000000010111111111111111111111111110000000000010111111111111111111111111110000000000010111111111111111111111111110000000000010111111111111111111111111110000000000010111111111111111111111111110000000000010111111111111111111111111110000000000010111111111111111111111111110000000000010111111111111111111111111110000000000010111111111111111111111111110000000000010111111111111111111111111110000000000010111111111111111111111111110000000000010111111111111111111111111110000000000010111111111111111111111111110000000000010111111111111111111111111110000000000010111111111111111111111111110000000000010111111111111111111111111110000000000010111111111111111111111111110000000000010111111111111111111111111110000000000010111111111111111111111111110000000000010111111111111111111111111110000000000010111111111111111111111111110000000000010111111111111111111111111110000000000010111111111111111111111111110000000000010111111111111111111111111110000000000010111111111111111111111111110000000000010111111111111111111111111110000000000010111111111111111111111111110000000000010111111111111111111111111110000000000010111111111111111111111111110000000000010111111111111111111111111110000000000010111111111111111111111111110000000000010111111111111111111111111110000000000010111111111111111111111111110000000000010111111111111111111111111110000000000010111111111111111111111111110000000000010111111111111111111111111110000000000010111111111111111111111111110000000000010111111111111111111111111110000000000010111111111111111111111111110000000000010111111111111111111111111110000000000010111111111111111111111111110000000000010111111111111111111111111110000000000010111111111111111111111111110000000000010111111111111111111111111110000000000010111111111111111111111111110000000000010111111111111111111111111110000000000010111111111111111111111111110000000000010111111111111111111111111110000000000010111111111111111111111111110000000000010111111111111111111111111110000000000010111111111111111111111111110000000000010111111111111111111111111110000000000010111111111111111111111111110000000000010111111111111111111111111110000000000010111111111111111111111111110000000000010111111111111111111111111110000000000010111111111111111111111111110000000000010111111111111111111111111110000000000010111111111111111111111111110000000000010111111111111111111111111110000000000010111111111111111111111111110000000000010111111111111111111111111110000000000010111111111111111111111111110000000000010111111111111111111111111110000000000010111111111111111111111111110000000000010111111111111111111111111110000000000010111111111111111111111111110000000000010111111111111111111111111110000000000010111111111111111111111111110000000000010111111111111111111111111110000000000010111111111111111111111111110000000000010111111111111111111111111110000000000010111111111111111111111111110000000000010111111111111111111111111110000000000010111111111111111111111111110000000000010111111111111111111111111110000000000010111111111111111111111111110000000000010111111111111111111111111110000000000010111111111111111111111111110000000000010111111111111111111111111110000000000010111111111111111111111111110000000000010111111111111111111111111110000000000010111111111111111111111111110000000000010111111111111111111111111110000000000010111111111111111111111111110000000000010111111111111111111111111110000000000010111111111111111111111111110000000000010111111111111111111111111110000000000010111111111111111111111111110000000000010111111111111111111111111110000000000010111111111111111111111111110000000000010111111111111111111111111110000000000010111111111111111111111111110000000000010111111111111111111111111110000000000010111111111111111111111111110000000000010111111111111111111111111110000000000010111111111111111111111111110000000000010111111111111111111111111110000000000010111111111111111111111111110000000000010111111111111111111111111110000000000010111111111111111111111111110000000000010111111111111111111111111110000000000010111111111111111111111111110000000000010111111111111111111111111110000000000010111111111111111111111111110000000000010111111111111111111111111110000000000010111111111111111111111111110000000000010111111111111111111111111110000000000010111111111111111111111111110000000000010111111111111111111111111110000000000010111111111111111111111111110000000000010111111111111111111111111110000000000010111111111111111111111111110000000000010111111111111111111111111110000000000010111111111111111111111111110000000000010111111111111111111111111110000000000010111111111111111111111111110000000000010111111111111111111111111110000000000010111111111111111111111111110000000000010111111111111111111111111110000000000010111111111111111111111111110000000000010111111111111111111111111110000000000010111111111111111111111111110000000000010111111111111111111111111110000000000010111111111111111111111111110000000000010111111111111111111111111110000000000010111111111111111111111111110000000000010111111111111111111111111110000000000010111111111111111111111111110000000000010111111111111111111111111110000000000010111111111111111111111111110000000000010111111111111111111111111110000000000010111111111111111111111111110000000000010111111111111111111111111110000000000010111111111111111111111111110000000000010111111111111111111111111110000000000010111111111111111111111111110000000000010111111111111111111111111110000000000010111111111111111111111111110000000000010111111111111111111111111110000000000010111111111111111111111111110000000000010111111111111111111111111110000000000010111111111111111111111111110000000000010111111111111111111111111110000000000010111111111111111111111111110000000000010111111111111111111111111110000000000010111111111111111111111111110000000000010111111111111111111111111110000000000010111111111111111111111111110000000000010111111111111111111111111110000000000010111111111111111111111111110000000000010111111111111111111111111110000000000010111111111111111111111111110000000000010111111111111111111111111110000000000010111111111111111111111111110000000000010111111111111111111111111110000000000010111111111111111111111111110000000000010111111111111111111111111110000000000010111111111111111111111111110000000000010111111111111111111111111110000000000010111111111111111111111111110000000000010111111111111111111111111110000000000010111111111111111111111111110000000000010111111111111111111111111110000000000010111111111111111111111111110000000000010111111111111111111111111110000000000010111111111111111111111111110000000000010111111111111111111111111110000000000010111111111111111111111111110000000000010111111111111111111111111110000000000010111111111111111111111111110000000000010111111111111111111111111110000000000010111111111111111111111111110000000000010111111111111111111111111110000000000010111111111111111111111111110000000000010111111111111111111111111110000000000010111111111111111111111111110000000000010111111111111111111111111110000000000010111111111111111111111111110000000000010111111111111111111111111110000000000010111111111111111111111111110000000000010111111111111111111111111110000000000010111111111111111111111111110000000000010111111111111111111111111110000000000010111111111111111111111111110000000000010111111111111111111111111110000000000010111111111111111111111111110000000000010111111111111111111111111110000000000010111111111111111111111111110000000000010111111111111111111111111110000000000010111111111111111111111111110000000000010111111111111111111111111110000000000010111111111111111111111111110000000000010111111111111111111111111110000000000010111111111111111111111111110000000000010111111111111111111111111110000000000010111111111111111111111111110000000000010111111111111111111111111110000000000010111111111111111111111111110000000000010111111111111111111111111110000000000010111111111111111111111111110000000000010111111111111111111111111110000000000010111111111111111111111111110000000000010111111111111111111111111110000000000010111111111111111111111111110000000000010111111111111111111111111110000000000010111111111111111111111111110000000000010111111111111111111111111110000000000010111111111111111111111111110000000000010111111111111111111111111110000000000010111111111111111111111111110000000000010111111111111111111111111110000000000010111111111111111111111111110000000000010111111111111100000000000001111111111111000000000001011111111111111111111111111000000000000000000000000101111111111111111111111111100000000000010000000000000 (
b11010011010011010011010011010011010011010011010011010011010011010011010011010011010011010011010011010011010011010011010011010011010011010011010011010011010011010011010011010011010011010011010011010011010011010011010011010011010011010011010011010011010011010011010011010011010011010011010011010011010011010011010011010011010011010011010011010011010011010011010011010011010011010011010011010011010011010011010011010011010011010011010011010011010011010011010011010011010011010011010011010011010011010011010011010011010011010011010011010011010011010011010011010011010011010011010011010011010011010011010011010011010011010011010011010011010011010011010011010011010011010011010011010011010011010011010011010011010011010011010011010011010011010011010011010011010011010011010011010011010011010011010011010011010011010011010011010011010011010011010011010011010011010011010011010011010011010011010011010011010011010011010011010011010011010011010011010011010011010011010011010011010011010011010011010011010011010011010011010011010011010011010011010011010011010011010011010011010011010011010011010011010011010011010011010011010011010011010011010011010011010011010011010011010011010011010011010011010011010011010011010011010011010011010011010011010011010011010011010011010011010011010011010011010011010011010011010011010011010011010011010011010011010011010011010011010011010011010011010011010000110100111101001100 &
b1101001101001101001101001101001101001101001101001101001101001101001101001101001101001101001101001101001101001101001101001101001101001101001101001101001101001101001101001101001101001101001101001101001101001101001101001101001101001101001101001101001101001101001101001101001101001101001101001101001101001101001101001101001101001101001101001101001101001101001101001101001101001101001101001101001101001101001101001101001101001101001101001101001101001101001101001101001101001101001101001101001101001101001101001101001101001101001101001101001101001101001101001101001101001101001101001101001101001101001101001101001101001101001101001101001101001101001101001101001101001101001101001101001101001101001101001101001101001101001101001101001101001101001101001101001101001101001101001101001101001101001101001101001101001101001101001101001101001101001101001101001101001101001101001101001101001101001101001101001101001101001101001101001101001101001101001101001101001101001101001101001101001101001101001101001101001101001101001101001101001101001101001101001101001101001101001101001101001101001101001101001101001101001101001101001101001101001101001101001101001101001101001101001101001101001101001101001101001101001101001101001101001101001101001101001101001101001101001101001101001101001101001101001101001101001101001101001101001101001101001101001101001101001101001101001101001101001101001101001101001111010011010100110111 '
1!
#7200
b111 )
b111 #
b1110001110001110001110001110001110001110001110001110001110001110001110001110001110001110001110001110001110001110001110001110001110001110001110001110001110001110001110001110001110001110001110001110001110001110001110001110001110001110001110001110001110001110001110001110001110001110001110001110001110001110001110001110001110001110001110001110001110001110001110001110001110001110001110001110001110001110001110001110001110001110001110001110001110001110001110001110001110001110001110001110001110001110001110001110001110001110001110001110001110001110001110001110001110001110001110001110001110001110001110001110001110001110001110001110001110001110001110001110001110001110001110001110001110001110001110001110001110001110001110001110001110001110001110001110001110001110001110001110001110001110001110001110001110001110001110001110001110001110001110001110001110001110001110001110001110001110001110001110001110001110001110001110001110001110001110001110001110001110001110001110001110001110001110001110001110001110001110001110001110001110001110001110001110001110001110001110001110001110001110001110001110001110001110001110001110001110001110001110001110001110001110001110001110001110001110001110001110001110001110001110001110001110001110001110001110001110001110001110001110001110001110001110001110001110001110001110001110001110001110001110001110001110001110001110001110001110001110001110001000111000111000111000111 %
#7500
0!
