Draft_Phuong/poly_lift/ter_arith.sv
module add_ter (x, y, z);
    input [1:0] x,y;
    output [1:0] z;

    assign z[1] = ( x[1] ^ y[0] ) & ( x[0] ^ y[1] );
    assign z[0] = (x[0] ^ y[0]) | (x[1]&y[1]) | ( (~(x[1]|y[1])) & y[0] );

endmodule // add_ter

module mul_ter (x, y, z);
    input [1:0] x,y;
    output [1:0] z;

    assign z[1] = (x[1] & (~y[1]) & y[0]) | ((~x[1]) & y[1] & x[0]);
    assign z[0] = x[0] & y[0];

endmodule // mul_ter

module inverse_phi1 (clk, rst, spe_case, init, prev_state, state);
    input clk, rst;
    input [1:0] spe_case;
    input [3:0] init;
    output reg [1:0] state, prev_state;
    wire [1:0] next_state, next2_state;

    always @ ( posedge clk ) begin
        if (rst) begin
            #0.2 state <= init[3:2];
        end else begin
            #0.2 state <= next2_state;
        end
    end

    always @ ( posedge clk ) begin
        if (rst) begin
            #0.2 prev_state <= init[1:0];
        end else begin
            #0.2 prev_state <= next_state;
        end
    end

    inverse_phi1_next_state NEXT1 ( .spe_case( spe_case[1] ), .state( state ),
    .next_state( next_state ) );
    inverse_phi1_next_state NEXT2 ( .spe_case( spe_case[0] ), .state( next_state ),
    .next_state( next2_state ) );

endmodule // inverse_phi

module inverse_phi1_next_state(spe_case, state, next_state);
    input spe_case;
    input [1:0] state;
    output [1:0] next_state;

    assign next_state[1] = ~(spe_case | state[1]) & state[0];
    assign next_state[0] = ~(spe_case | state[1]) | ( ~state[0] );
endmodule // inverse_phi

Draft_Phuong/poly_lift/inverse_phi1/dump.vcd
$date
	Thu Oct 28 21:38:03 2021
$end
$version
	Icarus Verilog
$end
$timescale
	1ps
$end
$scope module inverse_phi1 $end
$var wire 1 ! clk $end
$var wire 4 " init [3:0] $end
$var wire 1 # rst $end
$var wire 2 $ spe_case [1:0] $end
$var wire 2 % next_state [1:0] $end
$var wire 2 & next2_state [1:0] $end
$var reg 2 ' prev_state [1:0] $end
$var reg 2 ( state [1:0] $end
$upscope $end
$enddefinitions $end
#0
$dumpvars
bx (
bx '
bx &
bx %
bz $
0#
bz "
1!
$end
#200
1#
b0 "
#500
0!
#1000
1!
#1200
b11 &
0#
b10 $
b1 %
b0 '
b0 (
#1500
0!
#2000
1!
#2200
b0 $
b1 &
b0 %
b11 (
b1 '
#2500
0!
#3000
1!
#3200
b0 &
b11 %
b0 '
b1 (
#3500
0!
#4000
1!
#4200
b11 &
b1 %
b0 (
b11 '
#4500
0!
#5000
1!
#5200
b1 &
b0 %
b1 '
b11 (
#5500
0!
#6000
1!
#6200
b10 $
b1 &
b0 %
b1 (
b0 '
#6500
0!
#7000
1!
#7200
b0 &
b11 %
b0 $
#7500
0!
#8000
1!
#8200
b11 &
b1 %
b0 (
b11 '
#8500
0!
#9000
1!
#9200
b1 &
b0 %
b1 '
b11 (
#9500
0!
#10000
1!
#10200
b0 &
b11 %
b1 (
b0 '
#10500
0!
#11000
1!
#11200
b1 $
b0 &
b1 %
b11 '
b0 (
#11500
0!
#12000
1!
#12200
b11 &
b0 $
b1 '
#12500
0!
#13000
1!
#13200
b1 &
b0 %
b11 (
#13500
0!
#14000
1!
#14200
b0 &
b11 %
b1 (
b0 '
#14500
0!
#15000
1!
#15200
b11 &
b1 %
b11 '
b0 (
#15500
0!
#16000
1!
#16200
b10 $
b1 &
b0 %
b11 (
b1 '
#16500
0!
#17000
1!
#17200
b0 &
b11 %
b0 $
b0 '
b1 (
#17500
0!
#18000
1!
#18200
b11 &
b1 %
b0 (
b11 '
#18500
0!
#19000
1!
#19200
b1 &
b0 %
b1 '
b11 (
#19500
0!
#20000
1!
#20200
b0 &
b11 %
b1 (
b0 '
#20500
0!
#21000
1!
#21200
b10 $
b11 &
b1 %
b11 '
b0 (
#21500
0!
#22000
1!
#22200
b0 $
b1 &
b0 %
b11 (
b1 '
#22500
0!
#23000
1!
#23200
b0 &
b11 %
b0 '
b1 (
#23500
0!
#24000
1!
#24200
b11 &
b1 %
b0 (
b11 '
#24500
0!
#25000
1!
#25200
b1 &
b0 %
b1 '
b11 (
#25500
0!
#26000
1!
#26200
1#
b1 "
b0 &
b11 %
b1 (
b0 '
#26500
0!
#27000
1!
#27200
0#
b1 $
b0 &
b1 %
b1 '
b0 (
#27500
0!
#28000
1!
#28200
b11 &
b0 $
#28500
0!
#29000
1!
#29200
b1 &
b0 %
b11 (
#29500
0!
#30000
1!
#30200
b0 &
b11 %
b1 (
b0 '
#30500
0!
#31000
1!
#31200
b11 &
b1 %
b11 '
b0 (
#31500
0!
#32000
1!
#32200
b10 $
b1 &
b0 %
b11 (
b1 '
#32500
0!
#33000
1!
#33200
b0 &
b11 %
b0 $
b0 '
b1 (
#33500
0!
#34000
1!
#34200
b11 &
b1 %
b0 (
b11 '
#34500
0!
#35000
1!
#35200
b1 &
b0 %
b1 '
b11 (
#35500
0!
#36000
1!
#36200
b0 &
b11 %
b1 (
b0 '
#36500
0!
#37000
1!
#37200
b10 $
b11 &
b1 %
b11 '
b0 (
#37500
0!
#38000
1!
#38200
b0 $
b1 &
b0 %
b11 (
b1 '
#38500
0!
#39000
1!
#39200
b0 &
b11 %
b0 '
b1 (
#39500
0!
#40000
1!
#40200
b11 &
b1 %
b0 (
b11 '
#40500
0!
#41000
1!
#41200
b1 &
b0 %
b1 '
b11 (
#41500
0!
#42000
1!
#42200
b1 $
b0 &
b11 %
b1 (
b0 '
#42500
0!
#43000
1!
#43200
b11 &
b0 $
b1 %
b11 '
b0 (
#43500
0!
#44000
1!
#44200
b1 &
b0 %
b11 (
b1 '
#44500
0!
#45000
1!
#45200
b0 &
b11 %
b0 '
b1 (
#45500
0!
#46000
1!
#46200
b11 &
b1 %
b0 (
b11 '
#46500
0!
#47000
1!
#47200
b10 $
b1 &
b0 %
b1 '
b11 (
#47500
0!
#48000
1!
#48200
b0 &
b11 %
b0 $
b1 (
b0 '
#48500
0!
#49000
1!
#49200
b11 &
b1 %
b11 '
b0 (
#49500
0!
#50000
1!
#50200
b1 &
b0 %
b11 (
b1 '
#50500
0!
#51000
1!
#51200
b0 &
b11 %
b0 '
b1 (
#51500
0!
#52000
1!
#52200
1#
b11 "
b11 &
b1 %
b0 (
b11 '
#52500
0!
#53000
1!
#53200
b0 &
0#
b1 $
#53500
0!
#54000
1!
#54200
b11 &
b0 $
b1 '
#54500
0!
#55000
1!
#55200
b1 &
b0 %
b11 (
#55500
0!
#56000
1!
#56200
b0 &
b11 %
b1 (
b0 '
#56500
0!
#57000
1!
#57200
b11 &
b1 %
b11 '
b0 (
#57500
0!
#58000
1!
#58200
b10 $
b1 &
b0 %
b11 (
b1 '
#58500
0!
#59000
1!
#59200
b0 &
b11 %
b0 $
b0 '
b1 (
#59500
0!
#60000
1!
#60200
b11 &
b1 %
b0 (
b11 '
#60500
0!
#61000
1!
#61200
b1 &
b0 %
b1 '
b11 (
#61500
0!
#62000
1!
#62200
b0 &
b11 %
b1 (
b0 '
#62500
0!
#63000
1!
#63200
b10 $
b11 &
b1 %
b11 '
b0 (
#63500
0!
#64000
1!
#64200
b0 $
b1 &
b0 %
b11 (
b1 '
#64500
0!
#65000
1!
#65200
b0 &
b11 %
b0 '
b1 (
#65500
0!
#66000
1!
#66200
b11 &
b1 %
b0 (
b11 '
#66500
0!
#67000
1!
#67200
b1 &
b0 %
b1 '
b11 (
#67500
0!
#68000
1!
#68200
b10 $
b1 &
b0 %
b1 (
b0 '
#68500
0!
#69000
1!
#69200
b0 &
b11 %
b0 $
#69500
0!
#70000
1!
#70200
b11 &
b1 %
b0 (
b11 '
#70500
0!
#71000
1!
#71200
b1 &
b0 %
b1 '
b11 (
#71500
0!
#72000
1!
#72200
b0 &
b11 %
b1 (
b0 '
#72500
0!
#73000
1!
#73200
b1 $
b0 &
b1 %
b11 '
b0 (
#73500
0!
#74000
1!
#74200
b11 &
b0 $
b1 '
#74500
0!
#75000
1!
#75200
b1 &
b0 %
b11 (
#75500
0!
#76000
1!
#76200
b0 &
b11 %
b1 (
b0 '
#76500
0!
#77000
1!
#77200
b11 &
b1 %
b11 '
b0 (
#77500
0!
#78000
1!
#78200
1#
b100 "
b1 &
b0 %
b11 (
b1 '
#78500
0!
#79000
1!
#79200
0#
b1 $
b0 &
b11 %
b0 '
b1 (
#79500
0!
#80000
1!
#80200
b11 &
b0 $
b1 %
b0 (
b11 '
#80500
0!
#81000
1!
#81200
b1 &
b0 %
b1 '
b11 (
#81500
0!
#82000
1!
#82200
b0 &
b11 %
b1 (
b0 '
#82500
0!
#83000
1!
#83200
b11 &
b1 %
b11 '
b0 (
#83500
0!
#84000
1!
#84200
b10 $
b1 &
b0 %
b11 (
b1 '
#84500
0!
#85000
1!
#85200
b0 &
b11 %
b0 $
b0 '
b1 (
#85500
0!
#86000
1!
#86200
b11 &
b1 %
b0 (
b11 '
#86500
0!
#87000
1!
#87200
b1 &
b0 %
b1 '
b11 (
#87500
0!
#88000
1!
#88200
b0 &
b11 %
b1 (
b0 '
#88500
0!
#89000
1!
#89200
b10 $
b11 &
b1 %
b11 '
b0 (
#89500
0!
#90000
1!
#90200
b0 $
b1 &
b0 %
b11 (
b1 '
#90500
0!
#91000
1!
#91200
b0 &
b11 %
b0 '
b1 (
#91500
0!
#92000
1!
#92200
b11 &
b1 %
b0 (
b11 '
#92500
0!
#93000
1!
#93200
b1 &
b0 %
b1 '
b11 (
#93500
0!
#94000
1!
#94200
b10 $
b1 &
b0 %
b1 (
b0 '
#94500
0!
#95000
1!
#95200
b0 &
b11 %
b0 $
#95500
0!
#96000
1!
#96200
b11 &
b1 %
b0 (
b11 '
#96500
0!
#97000
1!
#97200
b1 &
b0 %
b1 '
b11 (
#97500
0!
#98000
1!
#98200
b0 &
b11 %
b1 (
b0 '
#98500
0!
#99000
1!
#99200
b1 $
b0 &
b1 %
b11 '
b0 (
#99500
0!
#100000
1!
#100200
b11 &
b0 $
b1 '
#100500
0!
#101000
1!
#101200
b1 &
b0 %
b11 (
#101500
0!
#102000
1!
#102200
b0 &
b11 %
b1 (
b0 '
#102500
0!
#103000
1!
#103200
b11 &
b1 %
b11 '
b0 (
#103500
0!
#104000
1!
#104200
1#
b101 "
b1 &
b0 %
b11 (
b1 '
#104500
0!
#105000
1!
#105200
0#
b10 $
b1 &
b0 %
b1 (
#105500
0!
#106000
1!
#106200
b0 &
b11 %
b0 $
b0 '
#106500
0!
#107000
1!
#107200
b11 &
b1 %
b11 '
b0 (
#107500
0!
#108000
1!
#108200
b1 &
b0 %
b11 (
b1 '
#108500
0!
#109000
1!
#109200
b0 &
b11 %
b0 '
b1 (
#109500
0!
#110000
1!
#110200
b10 $
b11 &
b1 %
b0 (
b11 '
#110500
0!
#111000
1!
#111200
b0 $
b1 &
b0 %
b1 '
b11 (
#111500
0!
#112000
1!
#112200
b0 &
b11 %
b1 (
b0 '
#112500
0!
#113000
1!
#113200
b11 &
b1 %
b11 '
b0 (
#113500
0!
#114000
1!
#114200
b1 &
b0 %
b11 (
b1 '
#114500
0!
#115000
1!
#115200
b1 $
b0 &
b11 %
b0 '
b1 (
#115500
0!
#116000
1!
#116200
b11 &
b0 $
b1 %
b0 (
b11 '
#116500
0!
#117000
1!
#117200
b1 &
b0 %
b1 '
b11 (
#117500
0!
#118000
1!
#118200
b0 &
b11 %
b1 (
b0 '
#118500
0!
#119000
1!
#119200
b11 &
b1 %
b11 '
b0 (
#119500
0!
#120000
1!
#120200
b10 $
b1 &
b0 %
b11 (
b1 '
#120500
0!
#121000
1!
#121200
b0 &
b11 %
b0 $
b0 '
b1 (
#121500
0!
#122000
1!
#122200
b11 &
b1 %
b0 (
b11 '
#122500
0!
#123000
1!
#123200
b1 &
b0 %
b1 '
b11 (
#123500
0!
#124000
1!
#124200
b0 &
b11 %
b1 (
b0 '
#124500
0!
#125000
1!
#125200
b1 $
b0 &
b1 %
b11 '
b0 (
#125500
0!
#126000
1!
#126200
b11 &
b0 $
b1 '
#126500
0!
#127000
1!
#127200
b1 &
b0 %
b11 (
#127500
0!
#128000
1!
#128200
b0 &
b11 %
b1 (
b0 '
#128500
0!
#129000
1!
#129200
b11 &
b1 %
b11 '
b0 (
#129500
0!
#130000
1!
#130200
1#
b111 "
b1 &
b0 %
b11 (
b1 '
#130500
0!
#131000
1!
#131200
0#
b1 $
b0 &
b11 %
b11 '
b1 (
#131500
0!
#132000
1!
#132200
b11 &
b0 $
b1 %
b0 (
#132500
0!
#133000
1!
#133200
b1 &
b0 %
b1 '
b11 (
#133500
0!
#134000
1!
#134200
b0 &
b11 %
b1 (
b0 '
#134500
0!
#135000
1!
#135200
b11 &
b1 %
b11 '
b0 (
#135500
0!
#136000
1!
#136200
b1 $
b1 &
b0 %
b11 (
b1 '
#136500
0!
#137000
1!
#137200
b0 $
b0 &
b11 %
b0 '
b1 (
#137500
0!
#138000
1!
#138200
b11 &
b1 %
b0 (
b11 '
#138500
0!
#139000
1!
#139200
b1 &
b0 %
b1 '
b11 (
#139500
0!
#140000
1!
#140200
b0 &
b11 %
b1 (
b0 '
#140500
0!
#141000
1!
#141200
b1 $
b0 &
b1 %
b11 '
b0 (
#141500
0!
#142000
1!
#142200
b11 &
b0 $
b1 '
#142500
0!
#143000
1!
#143200
b1 &
b0 %
b11 (
#143500
0!
#144000
1!
#144200
b0 &
b11 %
b1 (
b0 '
#144500
0!
#145000
1!
#145200
b11 &
b1 %
b11 '
b0 (
#145500
0!
#146000
1!
#146200
b10 $
b1 &
b0 %
b11 (
b1 '
#146500
0!
#147000
1!
#147200
b0 &
b11 %
b0 $
b0 '
b1 (
#147500
0!
#148000
1!
#148200
b11 &
b1 %
b0 (
b11 '
#148500
0!
#149000
1!
#149200
b1 &
b0 %
b1 '
b11 (
#149500
0!
#150000
1!
#150200
b0 &
b11 %
b1 (
b0 '
#150500
0!
#151000
1!
#151200
b10 $
b11 &
b1 %
b11 '
b0 (
#151500
0!
#152000
1!
#152200
b0 $
b1 &
b0 %
b11 (
b1 '
#152500
0!
#153000
1!
#153200
b0 &
b11 %
b0 '
b1 (
#153500
0!
#154000
1!
#154200
b11 &
b1 %
b0 (
b11 '
#154500
0!
#155000
1!
#155200
b1 &
b0 %
b1 '
b11 (
#155500
0!
#156000
1!
#156200
1#
b1100 "
b0 &
b11 %
b1 (
b0 '
#156500
0!
#157000
1!
#157200
0#
b10 $
b1 &
b0 %
b11 (
#157500
0!
#158000
1!
#158200
b0 &
b11 %
b0 $
b1 (
#158500
0!
#159000
1!
#159200
b11 &
b1 %
b11 '
b0 (
#159500
0!
#160000
1!
#160200
b1 &
b0 %
b11 (
b1 '
#160500
0!
#161000
1!
#161200
b0 &
b11 %
b0 '
b1 (
#161500
0!
#162000
1!
#162200
b1 $
b0 &
b1 %
b0 (
b11 '
#162500
0!
#163000
1!
#163200
b11 &
b0 $
b1 '
#163500
0!
#164000
1!
#164200
b1 &
b0 %
b11 (
#164500
0!
#165000
1!
#165200
b0 &
b11 %
b0 '
b1 (
#165500
0!
#166000
1!
#166200
b11 &
b1 %
b0 (
b11 '
#166500
0!
#167000
1!
#167200
b1 $
b1 &
b0 %
b1 '
b11 (
#167500
0!
#168000
1!
#168200
b0 $
b0 &
b11 %
b1 (
b0 '
#168500
0!
#169000
1!
#169200
b11 &
b1 %
b11 '
b0 (
#169500
0!
#170000
1!
#170200
b1 &
b0 %
b11 (
b1 '
#170500
0!
#171000
1!
#171200
b0 &
b11 %
b0 '
b1 (
#171500
0!
#172000
1!
#172200
b1 $
b0 &
b1 %
b0 (
b11 '
#172500
0!
#173000
1!
#173200
b11 &
b0 $
b1 '
#173500
0!
#174000
1!
#174200
b1 &
b0 %
b11 (
#174500
0!
#175000
1!
#175200
b0 &
b11 %
b0 '
b1 (
#175500
0!
#176000
1!
#176200
b11 &
b1 %
b0 (
b11 '
#176500
0!
#177000
1!
#177200
b1 $
b1 &
b0 %
b1 '
b11 (
#177500
0!
#178000
1!
#178200
b0 $
b0 &
b11 %
b1 (
b0 '
#178500
0!
#179000
1!
#179200
b11 &
b1 %
b11 '
b0 (
#179500
0!
#180000
1!
#180200
b1 &
b0 %
b11 (
b1 '
#180500
0!
#181000
1!
#181200
b0 &
b11 %
b0 '
b1 (
#181500
0!
#182000
1!
#182200
1#
b1101 "
b11 &
b1 %
b0 (
b11 '
#182500
0!
#183000
1!
#183200
0#
b10 $
b1 &
b0 %
b1 '
b11 (
#183500
0!
#184000
1!
#184200
b0 &
b11 %
b0 $
b1 (
b0 '
#184500
0!
#185000
1!
#185200
b11 &
b1 %
b11 '
b0 (
#185500
0!
#186000
1!
#186200
b1 &
b0 %
b11 (
b1 '
#186500
0!
#187000
1!
#187200
b0 &
b11 %
b0 '
b1 (
#187500
0!
#188000
1!
#188200
b10 $
b11 &
b1 %
b0 (
b11 '
#188500
0!
#189000
1!
#189200
b0 $
b1 &
b0 %
b1 '
b11 (
#189500
0!
#190000
1!
#190200
b0 &
b11 %
b1 (
b0 '
#190500
0!
#191000
1!
#191200
b11 &
b1 %
b11 '
b0 (
#191500
0!
#192000
1!
#192200
b1 &
b0 %
b11 (
b1 '
#192500
0!
#193000
1!
#193200
b1 $
b0 &
b11 %
b0 '
b1 (
#193500
0!
#194000
1!
#194200
b11 &
b0 $
b1 %
b0 (
b11 '
#194500
0!
#195000
1!
#195200
b1 &
b0 %
b1 '
b11 (
#195500
0!
#196000
1!
#196200
b0 &
b11 %
b1 (
b0 '
#196500
0!
#197000
1!
#197200
b11 &
b1 %
b11 '
b0 (
#197500
0!
#198000
1!
#198200
b10 $
b1 &
b0 %
b11 (
b1 '
#198500
0!
#199000
1!
#199200
b0 &
b11 %
b0 $
b0 '
b1 (
#199500
0!
#200000
1!
#200200
b11 &
b1 %
b0 (
b11 '
#200500
0!
#201000
1!
#201200
b1 &
b0 %
b1 '
b11 (
#201500
0!
#202000
1!
#202200
b0 &
b11 %
b1 (
b0 '
#202500
0!
#203000
1!
#203200
b1 $
b0 &
b1 %
b11 '
b0 (
#203500
0!
#204000
1!
#204200
b11 &
b0 $
b1 '
#204500
0!
#205000
1!
#205200
b1 &
b0 %
b11 (
#205500
0!
#206000
1!
#206200
b0 &
b11 %
b1 (
b0 '
#206500
0!
#207000
1!
#207200
b11 &
b1 %
b11 '
b0 (
#207500
0!
#208000
1!
#208200
1#
b1111 "
b1 &
b0 %
b11 (
b1 '
#208500
0!
#209000
1!
#209200
0#
b10 $
b11 '
#209500
0!
#210000
1!
#210200
b0 &
b11 %
b0 $
b1 (
b0 '
#210500
0!
#211000
1!
#211200
b11 &
b1 %
b11 '
b0 (
#211500
0!
#212000
1!
#212200
b1 &
b0 %
b11 (
b1 '
#212500
0!
#213000
1!
#213200
b0 &
b11 %
b0 '
b1 (
#213500
0!
#214000
1!
#214200
b1 $
b0 &
b1 %
b0 (
b11 '
#214500
0!
#215000
1!
#215200
b11 &
b0 $
b1 '
#215500
0!
#216000
1!
#216200
b1 &
b0 %
b11 (
#216500
0!
#217000
1!
#217200
b0 &
b11 %
b0 '
b1 (
#217500
0!
#218000
1!
#218200
b11 &
b1 %
b0 (
b11 '
#218500
0!
#219000
1!
#219200
b10 $
b1 &
b0 %
b1 '
b11 (
#219500
0!
#220000
1!
#220200
b0 &
b11 %
b0 $
b1 (
b0 '
#220500
0!
#221000
1!
#221200
b11 &
b1 %
b11 '
b0 (
#221500
0!
#222000
1!
#222200
b1 &
b0 %
b11 (
b1 '
#222500
0!
#223000
1!
#223200
b0 &
b11 %
b0 '
b1 (
#223500
0!
#224000
1!
#224200
b1 $
b0 &
b1 %
b0 (
b11 '
#224500
0!
#225000
1!
#225200
b11 &
b0 $
b1 '
#225500
0!
#226000
1!
#226200
b1 &
b0 %
b11 (
#226500
0!
#227000
1!
#227200
b0 &
b11 %
b0 '
b1 (
#227500
0!
#228000
1!
#228200
b11 &
b1 %
b0 (
b11 '
#228500
0!
#229000
1!
#229200
b1 $
b1 &
b0 %
b1 '
b11 (
#229500
0!
#230000
1!
#230200
b0 $
b0 &
b11 %
b1 (
b0 '
#230500
0!
#231000
1!
#231200
b11 &
b1 %
b11 '
b0 (
#231500
0!
#232000
1!
#232200
b1 &
b0 %
b11 (
b1 '
#232500
0!
#233000
1!
#233200
b0 &
b11 %
b0 '
b1 (
#233500
0!
#234000
1!
#234200
b11 &
b1 %
b0 (
b11 '
