Draft_Phuong/SHA3_256/keccak_p/keccak_p.sv
module testbench(rst1, rst2, clk, s, out, count);
//count = 24, break;
    input[1600:1] s;
    input rst1, rst2, clk;
    output reg [1600:1] out;
    output reg[7:0] count;
    wire[7:0] count_new;

    keccak_p KECCAK_P (rst1, rst2, clk, s, out);
    inc_i8_o8 INC (count, count_new);

    always @ (posedge clk) begin
        if(rst1)
            count <= 0;
        else
            count <= count_new;
    end

    initial begin
        $dumpfile("dump.vcd");
        $dumpvars(1);
    end
endmodule

module keccak_p(rst1, rst2, clk, s, out);
//b (len of s) = 1600, nr = 24, w = 64, l = 6
//"en" to change value of rc
    input[1600:1] s;
    input rst1, rst2, clk;
    output reg [1600:1] out;
    wire[1600:1] a, b, c, d, e;
    wire[6:0] rc;

    theta THETA ( .a(out), .out(a) );
    rho RHO ( .a(a), .out(b) );
    pi PI ( .a(b), .out(c) );
    chi CHI ( .a(c), .out(d) );
    rc RC ( .rst (rst1), .en(clk), .out( rc ) );
    iota IOTA ( .a(d), .rc(rc), .b(e) );

    always @ (negedge clk) begin
        if(rst2)
            out <= s;
        else
            out <= e;
    end
endmodule

module theta(a, out);
    input[1600:1] a;
    output[1600:1] out;
    wire[320:1] c,d;

    theta_step1 STEP1 ( .a(a), .c(c) );
    theta_step2 STEP2 ( .c(c), .d(d) );
    theta_step3 STEP3 ( .a(a), .d(d), .out(out) );

endmodule

module theta_step1(a, c);
    input[1599:0] a;
    output[319:0] c;

    genvar i;
    generate
        for (i = 0; i < 320; i = i+1) begin: loop1
            assign c[i] = a[i] ^ a[i + 320] ^ a[i + 640] ^ a[i + 960] ^ a[i + 1280];
        end
    endgenerate
endmodule

module theta_step2(c, d);
    input[319:0] c;
    output[319:0] d;

    genvar x, z;
    generate
        for (x = 0; x < 5; x = x+1) begin: loop1
            for (z = 0; z < 64; z = z+1)  begin: loop2
                assign d[64*x+z] = c[ 64*( (x+4)%5 ) + z ] ^ c[ 64*( (x+1)%5 ) + ( (z+63)%64 ) ];
            end
        end
    endgenerate
endmodule

module theta_step3(a, d, out);
    input[1599:0] a;
    input[319:0] d;
    output[1599:0] out;

    assign out[319:0] = a[319:0] ^ d[319:0];
    assign out[639:320] = a[639:320] ^ d[319:0];
    assign out[959:640] = a[959:640] ^ d[319:0];
    assign out[1279:960] = a[1279:960] ^ d[319:0];
    assign out[1599:1280] = a[1599:1280] ^ d[319:0];
endmodule

module rho(a, out);
    input[1599:0] a;
    output[1599:0] out;

    assign out[63:0] = a[63:0];
    genvar z;
    generate
        //t = 0. 320*y + 64*x,m = 64,1
        for (z = 0; z < 64; z = z+1) begin: loop0
            assign out[64 + z] = a[64 + ( (z - 1) & 63 ) ];
        end

        //t = 1. 320*y + 64*x,m = 640,3
        for (z = 0; z < 64; z = z+1) begin: loop1
            assign out[640 + z] = a[640 + ( (z - 3) & 63 ) ];
        end

        //t = 2. 320*y + 64*x,m = 448,6
        for (z = 0; z < 64; z = z+1) begin: loop2
            assign out[448 + z] = a[448 + ( (z - 6) & 63 ) ];
        end

        //t = 3. 320*y + 64*x,m = 704,10
        for (z = 0; z < 64; z = z+1) begin: loop3
            assign out[704 + z] = a[704 + ( (z - 10) & 63 ) ];
        end

        //t = 4. 320*y + 64*x,m = 1088,15
        for (z = 0; z < 64; z = z+1) begin: loop4
            assign out[1088 + z] = a[1088 + ( (z - 15) & 63 ) ];
        end

        //t = 5. 320*y + 64*x,m = 1152,21
        for (z = 0; z < 64; z = z+1) begin: loop5
            assign out[1152 + z] = a[1152 + ( (z - 21) & 63 ) ];
        end

        //t = 6. 320*y + 64*x,m = 192,28
        for (z = 0; z < 64; z = z+1) begin: loop6
            assign out[192 + z] = a[192 + ( (z - 28) & 63 ) ];
        end

        //t = 7. 320*y + 64*x,m = 320,36
        for (z = 0; z < 64; z = z+1) begin: loop7
            assign out[320 + z] = a[320 + ( (z - 36) & 63 ) ];
        end

        //t = 8. 320*y + 64*x,m = 1024,45
        for (z = 0; z < 64; z = z+1) begin: loop8
            assign out[1024 + z] = a[1024 + ( (z - 45) & 63 ) ];
        end

        //t = 9. 320*y + 64*x,m = 512,55
        for (z = 0; z < 64; z = z+1) begin: loop9
            assign out[512 + z] = a[512 + ( (z - 55) & 63 ) ];
        end

        //t = 10. 320*y + 64*x,m = 1344,66
        for (z = 0; z < 64; z = z+1) begin: loop10
            assign out[1344 + z] = a[1344 + ( (z - 66) & 63 ) ];
        end

        //t = 11. 320*y + 64*x,m = 1536,78
        for (z = 0; z < 64; z = z+1) begin: loop11
            assign out[1536 + z] = a[1536 + ( (z - 78) & 63 ) ];
        end

        //t = 12. 320*y + 64*x,m = 256,91
        for (z = 0; z < 64; z = z+1) begin: loop12
            assign out[256 + z] = a[256 + ( (z - 91) & 63 ) ];
        end

        //t = 13. 320*y + 64*x,m = 960,105
        for (z = 0; z < 64; z = z+1) begin: loop13
            assign out[960 + z] = a[960 + ( (z - 105) & 63 ) ];
        end

        //t = 14. 320*y + 64*x,m = 1472,120
        for (z = 0; z < 64; z = z+1) begin: loop14
            assign out[1472 + z] = a[1472 + ( (z - 120) & 63 ) ];
        end

        //t = 15. 320*y + 64*x,m = 1216,136
        for (z = 0; z < 64; z = z+1) begin: loop15
            assign out[1216 + z] = a[1216 + ( (z - 136) & 63 ) ];
        end

        //t = 16. 320*y + 64*x,m = 832,153
        for (z = 0; z < 64; z = z+1) begin: loop16
            assign out[832 + z] = a[832 + ( (z - 153) & 63 ) ];
        end

        //t = 17. 320*y + 64*x,m = 768,171
        for (z = 0; z < 64; z = z+1) begin: loop17
            assign out[768 + z] = a[768 + ( (z - 171) & 63 ) ];
        end

        //t = 18. 320*y + 64*x,m = 128,190
        for (z = 0; z < 64; z = z+1) begin: loop18
            assign out[128 + z] = a[128 + ( (z - 190) & 63 ) ];
        end

        //t = 19. 320*y + 64*x,m = 1280,210
        for (z = 0; z < 64; z = z+1) begin: loop19
            assign out[1280 + z] = a[1280 + ( (z - 210) & 63 ) ];
        end

        //t = 20. 320*y + 64*x,m = 896,231
        for (z = 0; z < 64; z = z+1) begin: loop20
            assign out[896 + z] = a[896 + ( (z - 231) & 63 ) ];
        end

        //t = 21. 320*y + 64*x,m = 1408,253
        for (z = 0; z < 64; z = z+1) begin: loop21
            assign out[1408 + z] = a[1408 + ( (z - 253) & 63 ) ];
        end

        //t = 22. 320*y + 64*x,m = 576,276
        for (z = 0; z < 64; z = z+1) begin: loop22
            assign out[576 + z] = a[576 + ( (z - 276) & 63 ) ];
        end

        //t = 23. 320*y + 64*x,m = 384,300
        for (z = 0; z < 64; z = z+1) begin: loop23
            assign out[384 + z] = a[384 + ( (z - 300) & 63 ) ];
        end
    endgenerate
endmodule

module pi(a, out);
    input[1599:0] a;
    output[1599:0] out;

    genvar x,y;
    generate
        for (x = 0; x < 5; x = x+1) begin: loop1
            for (y = 0; y < 5; y = y+1) begin: loop2
                assign out[320*y + 64*x + 63 : 320*y + 64*x] = a[320*x + 64*( (x+3*y)%5 ) + 63 : 320*x + 64*( (x+3*y)%5 )];
            end
        end
    endgenerate
endmodule

module chi(a, out);
    input[1599:0] a;
    output[1599:0] out;

    genvar x,y;
    generate
        for (x = 0; x < 5; x = x+1) begin: loop1
            for (y = 0; y < 1600; y = y+320) begin: loop2
                assign out[y+ 64*x + 63 : y + 64*x] = a[y + 64*x + 63 : y + 64*x] ^ ( (~a[y + 64*((x+1)%5) + 63 : y + 64*((x+1)%5)]) & a[y + 64*((x+2)%5) + 63 : y+ 64*((x+2)%5)] );
            end
        end
    endgenerate
endmodule

module rc(rst, en, out);
//include rc(0), rc(1), rc(2), rc(3), rc(4), rc(5), rc(6)
//when "en" rises, if "rst" = 0, this module releases new rc.
    input rst, en;
    output [6:0] out;
    wire [56:1] r;
    reg [56:1] a;

    always @ (posedge en) begin
        if (rst) begin   //rc_init
            a[8:1] <= 8'b1;
            a[16:9] <= 8'b10;
            a[24:17] <= 8'b100;
            a[32:25] <= 8'b1000;
            a[40:33] <= 8'b10000;
            a[48:41] <= 8'b100000;
            a[56:49] <= 8'b1000000;
        end
        else
            a <= r;
    end

    assign out = {a[49], a[41], a[33], a[25], a[17], a[9], a[1]};
    rc_7 RC1 ( .a( a[8:1] ) , .b( r[8:1] ) );
    rc_7 RC2 ( .a( a[16:9] ) , .b( r[16:9] ) );
    rc_7 RC3 ( .a( a[24:17] ) , .b( r[24:17] ) );
    rc_7 RC4 ( .a( a[32:25] ) , .b( r[32:25] ) );
    rc_7 RC5 ( .a( a[40:33] ) , .b( r[40:33] ) );
    rc_7 RC6 ( .a( a[48:41] ) , .b( r[48:41] ) );
    rc_7 RC7 ( .a( a[56:49] ) , .b( r[56:49] ) );
endmodule

module rc_7(a, b);
    input [7:0] a;
    output [7:0] b;

    assign b = { a[0]^a[7]^a[3]^a[2], a[7]^a[6]^a[2]^a[1], a[6]^a[2]^a[5]^a[1]^a[3], a[5]^a[7]^a[1]^a[4]^a[3], a[4]^a[7]^a[6], a[3]^a[6]^a[5], a[2]^a[5]^a[4], a[1]^a[4]^a[3] };
endmodule

module iota(a, rc, b);
    input[1599:0] a;
    input[6:0] rc;
    output[1599:0] b;

    assign b[1599:64] = a[1599:64];
    assign {b[63], b[31], b[15], b[7], b[3], b[1], b[0]} = {a[63], a[31], a[15], a[7], a[3], a[1], a[0]} ^ rc;

    genvar i;
    generate
        for (i = 4; i <= 64; i = i<<1) begin: loop1
            assign b[i-2 : (i>>1)] = a[i-2 : (i>>1)];
        end
    endgenerate

endmodule

module inc_i8_o8(a, out);
//Sklansky AND-prefix structure
    input[7:0] a;
    output[7:0] out;
    wire[10:0] b;

    assign b[0] = a[1]&a[2];
    assign b[1] = a[3]&a[4];
    assign b[2] = a[5]&a[6];
    assign b[3] = a[0]&a[1];
    assign b[4] = a[0]&b[0];
    assign b[5] = a[5]&b[1];
    assign b[6] = b[2]&b[1];
    assign b[7] = a[3]&b[4];
    assign b[8] = b[1]&b[4];
    assign b[9] = b[4]&b[5];
    assign b[10] = b[4]&b[6];
    assign out[0] = ~a[0];
    assign out[1] = a[1]^a[0];
    assign out[2] = a[2]^b[3];
    assign out[3] = a[3]^b[4];
    assign out[4] = a[4]^b[7];
    assign out[5] = a[5]^b[8];
    assign out[6] = a[6]^b[9];
    assign out[7] = a[7]^b[10];

endmodule

Draft_Phuong/SHA3_256/keccak_p/dump.vcd
$date
	Wed Oct 13 20:11:46 2021
$end
$version
	Icarus Verilog
$end
$timescale
	1ps
$end
$scope module testbench $end
$var wire 1 ! clk $end
$var wire 1 " rst1 $end
$var wire 1 # rst2 $end
$var wire 1600 $ s [1600:1] $end
$var wire 1600 % out [1600:1] $end
$var wire 8 & count_new [7:0] $end
$var reg 8 ' count [7:0] $end
$upscope $end
$enddefinitions $end
#0
$dumpvars
bx '
bx &
bx %
b101100111110011111100101000001100111001110011100011111010100100100001100011001110100011110101001101000111110010001100101011010011100011000000011010001101100010100111101111011010001101010000001001111011011100000010101100010111010001001100010000001100000100100111100001101111101000010010000010110001010010100011101001101011111100111110011111011000011000011000111011100001010111110110011001010001010011111101111001011010110101000110011101111101100000011110000001010101000000100000010000111000001111110111001100110000011110110001010010101011101101101100101010110011111000101000100100011110001110001001101010001110101100000110100000111111011101100010111010000011101011101011100101110011010000100101011100001010101001001011101001101010111000101111110001001000101111111001010110110000111100010101101000101100000100010010100001101011001010000101011001000000101110000000100111011001000001101101010100100100100001001010111010110101010010110101100011000110111101100110110001111100100011010101001100111110110001000011010000111110100110100110101001001010000000101010000110001100010110111000001110101100100011011111111011101011011110100110111111111000011100011111101111111000000001100100100110100010100001111111001100011100001001000001100000000010110110011010000110101001100011000111111101001101011100011000010000110000100110000101000111001001010101110110110101001001010011000011000011010010101111000100011010100110111100111111010011100110000011011101110011101010011101100110111001000000101110100111110011100011011000111001000001000110110011101100101110011001011110101101011010101111100111001010111011100111011110 $
1#
z"
1!
$end
#500
1"
b101100111110011111100101000001100111001110011100011111010100100100001100011001110100011110101001101000111110010001100101011010011100011000000011010001101100010100111101111011010001101010000001001111011011100000010101100010111010001001100010000001100000100100111100001101111101000010010000010110001010010100011101001101011111100111110011111011000011000011000111011100001010111110110011001010001010011111101111001011010110101000110011101111101100000011110000001010101000000100000010000111000001111110111001100110000011110110001010010101011101101101100101010110011111000101000100100011110001110001001101010001110101100000110100000111111011101100010111010000011101011101011100101110011010000100101011100001010101001001011101001101010111000101111110001001000101111111001010110110000111100010101101000101100000100010010100001101011001010000101011001000000101110000000100111011001000001101101010100100100100001001010111010110101010010110101100011000110111101100110110001111100100011010101001100111110110001000011010000111110100110100110101001001010000000101010000110001100010110111000001110101100100011011111111011101011011110100110111111111000011100011111101111111000000001100100100110100010100001111111001100011100001001000001100000000010110110011010000110101001100011000111111101001101011100011000010000110000100110000101000111001001010101110110110101001001010011000011000011010010101111000100011010100110111100111111010011100110000011011101110011101010011101100110111001000000101110100111110011100011011000111001000001000110110011101100101110011001011110101101011010101111100111001010111011100111011110 %
0!
#1000
0#
b1 &
b0 '
1!
#1500
0"
b1011001110110101110110101100010000101110100011001001000000100111010001111111001101001111010010001100001011100000111110101001111110110110100100010000001111010001111100111011000010011110111111101010001010011110011110101011000111101000000010001011101110110001000100111100110110101001100011000100011011100000011010011000110010001000011101000000110011000110101010001010011100011001101100010001010111100000110010111111100110101000011110100000100101001010001111010100101111101111000110110100001001011010101100011100111110011101101011001100101101111110101001000101010011000100000001101000110111111100010111110101100110111010011110100101010100001101010011100010001010011111100111000111011101001101111111101111000000110111001100001000101110000010101011011110101100011101101110001100100100011010110101110111100011000000101101111100000010110011011010111100001010101010101110110010100111000100001001001010110001001001010111001100001100000100001110110011000001100010001101010010100000100001000110010110010010001000000001100100010000110010010110101011001001001000000101100000100001101010001010101000001100110111011000111000110110110110001110000101011000101011101101101110110111000101011010110000001000010100000001010101011010001100110111111111010110110110010111011010001001011100111001111111011011010000010001001010011000010100111010100011000100000110111011011001110001000001101001100000100011001101000011001011010010010010001100011011011010010110011001011000101110100110111010011011000101000000000000001110001001001001100011101011000100010101000101000011000000101011010111110111001111000101100101101000000101111101 %
0!
#2000
b10 &
b1 '
1!
#2500
b101000000011101110111100111010111110101100111010101000010010100010001010110001101000110011001000010101100111011100101011100110011000101011000111110000101011101010111100010001111000101000010100001100000000010110100111110001011110100011011100010001000010010001001101011010110011001100011000001011010101000100000010111101010101001000000001110111100001010111101011010011010101111101101001100101111111000010011001001100100101100110010111101000110101101010011001101101010111111001100010010100100111010010010010111110101100110011110110111010000000110000001010100011011001100010011100011110111000111001110000000011010000000000011111011110011010111111100001011000110101111101101010011010011101001101000111010000111000010010101100100010010100000001100110000111111111111000110000101000010110011011000111011001100011000000100000101000000001101111111101011001101100000101110001011010100111101010100000111000011100001001100100111010011101101010111111101011011101100110011111001100001101100001010100110011010000010000111000110010110010100100101100111011001110000101001101110011011001001110000100000011010110100100010000000011011111010101100001101110100111000100010010101101100001010110011000001000001001001001011111110100101000000111001100001000000111111100011001111110011110101100000101010001000010000100111001000101100000011101000110110100100111010010100001000011111101011100010100100100111111111000111111101101010000011100010011100001001011010101010100111010000111000111010011001110110110011011100100001000111010100010011001111001011110101000100110100011101000010110001111100101010011000100101110000110110001101 %
0!
#3000
b11 &
b10 '
1!
#3500
b100111101001000111100100101001000011010100001101010111011101010111000110100001011010000110111100111111100001101011100110010100011111111010111100100010010101101111000100011000000101010001000111111000100011000110111110110010100100111111101100010010111101000100101001011001001101010110111010101101111101000010000010000011100000001101111111101101111001010111101011010101110001001100011100111000001100110101110010111000111010100001010010000110101000101100011111011101100011011001101111111100111010001000100010010111011001100011110001101000111011011011001001010111100011111011101101001010010100001001110010000110100101111100011111100001110101111111010100101001000000010010100011000101010000001110110101010111101110101100000000000011000000110110011011100001011110011010000101110101100101001010110111001000011101000010011000101010010000000101100101101110111100001101010001101000000000111110000011101101100000000111000111110010110010100010001100011101101111111001000101110101011101010000100100111010110100001100100010000010010010101101101000000101000010011101111110111010101000111001001101011100110001010101101111111001111010110010001111011010101011011101001010111100001110111010111010001111010011111011001010011010111011100000001111111101101111111100101100010011000010001011100110110100000000100101001000010000000101100000100111111111000001111110100100101101001001111010000000110101001000101000001001110000000101110010110011000110001110100100100011001001001111010011101101100110001001010110011001000010110100011110010110010011101101011001111001000001001011010100111010100000100001110001000011101101010111100 %
0!
#4000
b100 &
b11 '
1!
#4500
b1010000111110101001001011000010000100100011111001000110111011100000111011110011011011000010001011011010011111100101001110100001101010000111101111000111000101010010011010101111000100111001110010001001010100100101011101100101101101111010100100000101001100001000010101101001001110110101001011111000001010100101011011011010011000000011101000001111110001111100110011011001101000110010001000100110110010010101011100010110011001111111001000010010011100110110101100001010100100001110101001111001000011010111101101100111011110100011001010001100110010011100000111110000010100001100011011001111001110000110110110111000110100001101100001111100100011011100000110001000001000010000011011001111000010100110010101110101110000110010110011011110000011110111100111011111101111000000111101010010101000010001101111000101011100010100010101001100111000101101001010100110110001010011011111101011110000110101000000101011111100111001011110000111100101001111100001111001110110001100001101100001000011011010110111110110000000000001001100001110000110110111010101000000001111100110001111100000001000011010100100000010000010000001111101101011111111111111110000101010010110001101110000101100100100001111111100111001111001011111101100101011011000111011001100111010010100111011011010111001110110111110100010000110010101100000100001101001110110010100110101101111001011110001100000000110010110010110000001010001010011101101011000110011011000000010110111001010101100000101011110100011101100010011110001001011111110110011011011011101001100100001111110000011011100011111010011001110001111111000111011010110111111110111011110011101111011 %
0!
#5000
b101 &
b100 '
1!
#5500
b10010010011010110101000001110111100111010100100000011011000001000111001001000011011011010100101100101010110111111000100010011100011101001010111000001011010111000000010111000001000111100000011001110110111001111010111100101111101111101000110001011111110101110111101011101101011011101111010101000100000001111110101100011100110110001001010100110100100010101111100101010011000000001111000111001101011111000110011111100011111101111000010001011000101111011010101110011010001111100111010001111001010010010000110010111000111011001100101100111011000010100001111111010101011110011010001001111011010011000010011001001110101010100011011000001010000011111111100101111001101011101011111000000111110111001010111111000001101101010010100010100011100010101110001011101011001000010101111111000011001100100000110100001010111010101110001111111001111100111010100010000100101011011101001110110000001110100011101001110000101011001001111011111100001111001001100101111101101010110010110100001001110001001111110100110100101101101000001110111000011101010101101011101100110110001101011001010100100100100011011010101110110011011101010000110101111000111111101101100110101111110011010111001110001001001010010110011010011000010001111101001000110000111011100010111000100000110100100010111011100011000101011101011100110011100011010110000101001100001100101001101011111010010100110100111011000101111111111101101000000101010000001111001000010001111011101010001110101001001011001110111000001000100010111000000110010000111100100101001001000001011000110011000001111110011101001011011000100101000010101101111000000111100010101010000110111000 %
0!
#6000
b110 &
b101 '
1!
#6500
b10110110010111111010000101110101000010011010100001010010111000101000010111101010010000001110101111000100011010101001000110010111001001000101111000101110000100000100000100001100111001001100111110100110010011001111111001101001101101110010111011100001010100100110010010000111100110100011110011100110101101110110000110100001001110101111001111110011111000011001001111000001101010110111100101111011000111101011000011010101000101110111110110110001000001000011111101101111010001010000001010011001110101000011100011110110100111011001111000111111000100100110001001011010011111001100011000111010100011001111111010101110110100001111101111111011100111001001101110111111111010010101110101010110111100011000001001100001011111111100001101111111100000000000111100110010010010000011000001101100000101111011011101101111001011001010110010110010100111000100000110111111001001001011111001100101010100110000011100001000000111001100011000011101101011111111000011000111000111011000111111100011100101101001100000011001101001001010001001010101010000000010111010111010111110010110111001100101101000110010111011000110011100100001101100100101010000100111100101001100011100010111110010101100101101100000110111010100000010001010110010001100011001000101110011101110000101111000000110011010110010100100001100110010010110011111001111011101101111110000111001100100110110001111000011000001111010111011110011011101111010111101001111111000101101001101101001011110011011000111111101110110000011101101111100011011101100111101101001101111110110001110011101111101100000010011110110010010011011010011001111101011111010000111110001100111100001 %
0!
#7000
b111 &
b110 '
1!
#7500
b1100010001000001110010011011111111100011011101001000011111010101100001100010100100001011011011101111010000000110100110011000011010001011001010111101011110101100101010011100101101111101101111000111011010000101010011101001000001001010000011101100010100000000001011110101001100110110110101110110100001100100000010011011101001110100000001100111001010011010111101010101110101110000110011100110000010110010101010000001000100111000010100001101001111000100001001110101001101111001001011010100011000001001101001100101100001000101011011100110111110000000110101100011110111001001011101010000100001111001100101000110011101010111010111100001010101011000010101101001001101011110000111001001100101101111001000111111001010000010010010000101000011101001001110010100010000111000000111110110011010011101011100111011011010110000110111110010010101101011101111010001001111101001010100000110101000011001011110011101110011000010101001011001100010100101010000100111001011010111110111111100110001100010100010011100111000111011101110001100100011010111010100011110001101100111011010010011101001000111001101100000000011011011011010110100100000100010010101110111100100000000111001011010001001111110011111110110101000011110011011000111010010110011010110100111000011100011110101111101000110010000000111110101010111011111101001001111100101000000000110110010101110011100001000011110101000011011000001110011000101101110111111111001011100010110111101111011010110001101101000111011011101001001011100011010011111111010111100111000100001101100101101010100111010001101001010111111110101000110010001010000011000001110011100100001111110010101 %
0!
#8000
b1000 &
b111 '
1!
#8500
b111100100100001100101100100011000001011110101000010010110000111001100111101111000101001101110110010001011111111101010101100010100001000000100100010010111000010001111001111101001101000101001001100110000100110101101101000101101011010011010011111000011011101011001111111010011100100010110100000111111010111000110111110001000110100100010100110011100101000100011111001010010001100010100101011101110001111101011001110111001000110010101000100010100110000001101010001001111110101110010110001001110110110011010001100100111000101101000000111101010110000011111001100100110001001111111000000111111101101001000101000111100000110000110011000001010011011011001011011010111000010110100100100111100011001110110101100101111010110100100001101010000011001001100100101001001011111001111100100000010010010101001111110110110011110000101010010110001000111110011000001110001100110010000100110100100101010110000111100010011001001110110111100101010100111010000010110101010011110100110000110110001111001010111011001111001110110111110111110101001000011000000110010010011111001011101000011000001000101001100000101010110000110101010101001110001111000011110110000000010110111101111100011100110011101100101010111110011000110001011000110001111100011010010101000010110011001000011000111011111110010010011110101001000000010111111110101000100100000111101001101000100011111100001101101110100011011101101001101011010001101111010110001010111111010000100001001101001101001010101011000101101001011010011110111000010110011000011000100000001000001000110011010100010101100101010100010010011001100100001100000100111111001111001010100011010110100 %
0!
#9000
b1001 &
b1000 '
1!
#9500
b1101001110001010000100011011100010110111011111000000010000111111111010011100111101111011111011011100011111000100100010001101111010000110000010010101000000101101000101101100010100111101100101011110101001100100111110100000000000011101111100111101100000111110010000111001001001001011110011100001000101110110101001011000010101110110000101010110010011011101011101101110010000001010010100110101000100101011001010101010100110010011110111101000110011111010110001111001011011011001111000101001010110110001001010010101001011110001111110110000111100010000001010101111001110011100110100010000110010010111100101000001000110111001111010001001100001011011100101110011001110001010111001101001100110000100110111011101101000100010110111010000110011100001100001110111110100111011001010100011110011000011110111010000110010000001111000101100001010010001010101010110101010011000101011100100110001111111000011111101100011111111000000011110101001001000001010110111110000010110110010000110000011001100101011000100111101011111010011000101111111101110011100001110011100011011001011010000110100111010001001110000101010000010101100001111110100100011001000100110111011011000001010000001110010110111000011100010101010111111000001110001111000010101001101111110100110111101100010111100101110010000000001000100100101101011000100010100101101101100011000110000101010001001101110101001000000110000101100001011000100011100110110111000000110001111110010001001100001011011001110110100110000101011101111101111010110101000001000000111011000010101100110000110100110011001001000011111111111011011010001111110000010110111100010000000110101111001 %
0!
#10000
b1010 &
b1001 '
1!
#10500
b1111000011111101010100010110010011110100101010100100001010111101001000110000101111010101000100000100010000001010111101101000101110101011111001000000111010100110011100101100000110011011011000100010001010010001110010011110110001011110010110101100101001000111011010001100100111101110101100001110010101101100110000010110100010001101101001000100000111110100011101101010001111000001101100111111001001011011101001000101010101100010001011111111010000010000110101110110111111001000000000001001110101110011101000100010110101111110100110011011110010011001110001111100100010100110100000011110001010110001110000111000001111100111001111111001000000011011111000111011001000110000011111000110000100000010011100111101110110001010010000011001010111001000100010101011111000010000110111101001010111110100000101010011010010101011110011101011111110011111010000011100100000111100001101011100100010011000110011110000001111001001111110001011100110111111011111100010111110100100101111110100000101000010111101010111101111011011011111111011100010011100011100010111010100111110011000001000000010101011000001101011011110010101101001000000111001001100110000010111110001100001001010010001001010101110000100110100100000100110000111011010010001101000001011101000101100001111101110111001010101111010001111100011001111011011100011100010001000100111001101100111100000011111010000110000011000100110101000110110011010111111001000110001011100100001101010011111010000100001000110101110000101111011111100101000010110100011110100001000011010000010100101001100011000001100101011010110001001000010010101010101101100001010110100000110001001010110 %
0!
#11000
b1011 &
b1010 '
1!
#11500
b11011010011011111100000011011111110111101101010110010000001000111000101100001000101110111111111101111100011000010101111101110111000010000011000111111001101000101100010000101110110111000110001100100001110100000010111000000110100100011011000010110000011011110000010111001000100111110010011101100010100001101011001000100010101011101111111010101001000111100111000010100001101000100010011111001111001110101111000111101001010100000001110000011110011000011101000001111100000100000010100100000100001001001001111101011001001110100001110101101110100111001010110101000010000001110011011001101100111110001101100111011011010111011010111011000000101001111000100101010010100111000010100000000110000110101101100100111001111000001011011110011011100111011000111101100000111011000011110101100110110101101010100101111101110100101010101000011101001100010000111000100001110000011000010010101111001010010100110110101110010101111010001110100111011011001010111110100100011111111111101000100101110011001100000011110111110110101001011100001011001001001000001011111000110001101100011111100001111111100101001001100100101110010101100111110011010011101110101000111101101111111101000000001000110000111111110011111011000000101101111010100100111000100010010111001100001010000001010110000110111100011011111000100011101101011011100010100000000100000001001000111111110000000010111110110000110011010110100111001100101101111101011110010000100110110011001001010101101011000010100111000111011111010110111111100011100000010100011000101111111010000011000100101001100100110101010011001010010000010110111111101000110010111010111010100001110010 %
0!
#12000
b1100 &
b1011 '
1!
#12500
b1001110101101000101101110100010100010010101000101101111010001001111110001010100001001001101011101000011010100101011001100110111000010010010100101100111010010110100010101111011101010110111010010000111000100000100000010001011000101101010000111101001101000101111110010010011110111000111100111100101001100111100110111111100001000000110110010111110001101011110111100000010010000111011001100010000111000100101010101101100000110000101101001110010000101110010110010100000110011111001011101011011101000011010010111111010000111111000111000011001010011101110000100001000011100000000010001001011011111001100100100001010110011100010000010110001110010000001011100011011011000110001100010000111010010100010000011010110110001101011011111100100000001101010011011111001110111000101101100010101000101000100001000000000100110110100000110110011111011110000100011100001110010101011001001000111111100010110000111111000000010101100000110101100101000010111110011001100011101010110111101011111101011001110100101011000101110110011101110101011001110010100000000110100010101001010010110110011010110110000110010111101101110000000011000110111001000111000011100011011011001100100110100100101011110000110100000001010101100110111001000101010101100111000000000010101111000001100110010011010101101011010111111110100100111111000010000100100101000100111110001011111101001110111011100110001111100100011001010011110110000011110110010000111000000111110100000001011110110001101011111100001000101000001100111101100100010001100010000101010011001011110011000000011111011110100001011010101111011110101111101001101111001000110001000110011111100101 %
0!
#13000
b1101 &
b1100 '
1!
#13500
b111010111110010011001001100100110100110000000111111101011110011101111110010101001110011000001000100100111011001001111001000110001011101100111001010110101010110111100001001101011111011001010111000000111110000001100101110011101100111000111010011010101001110111011010010111101111110011110010001110111011000000011001111010010000011100101000011110101100110011011011111100101111000111001001101000110000010001000001001010100110101110110011010001111110100101011000110100110000000001001001000100110001001011101010000101010000010110110001011100010011001011110110111011100110011111010100000011000110101100001001111011000001001110101101011000110111000100010001110100001001010110001111110100101010001111101111111100000000010100000101011101101111100101010110111010110010001010100001011100101001110000111001111100000000001010101111010001101110110001000111000000010111001001110101111010100010011001011000001100110010100111001101101110111011101001000001100111100111111101110100010001011010101110100010101011111100111001111111100011010010100110101010011011001100101001111101001010100010011000100111110000110101010000111010100111000011000001001001001010000001001111000001001111100101110111011000000010001101001100110011011101001101000100011010000000001011010111110101011001001110110110100011011111110010010000010011010101110000010111001011001110010101000010001111000011010101011100010010011110000010010010000101111100010110001000010100111110010000011111101101110111011011100010101000100001011000110110011001000110110011001100011001000000110100010100110110011011100110111010011000111011010010011110110100100010100001010 %
0!
#14000
b1110 &
b1101 '
1!
#14500
b1110001011111011011011111100000101011001101000011000111100011010001110001001100000100000010010011110011010001101110100100100011110010001101111001100110000011110011111011011010011000011110100011001111011010000100101000100010010010010001100101011011110001000010000100001100100110101101001100011010000111001011000110111111000100011110010111011010010101110000001101111001111101100011000100110000110100001100100011101000100000111110110100101011100100010111110011000101011110010000111011000001101001111010001001000011110101111110110111110000100111011010110001111100101111110011110001101110011111011000001010000110101000010001101111100011011100001110000111101100111010010101010111100100101000111000100100010111010010001011111100011110000000011001101010001100110110011011101101000110000110010010100111110011101110000101011111011110110101000001111110000110101100011111100100010100000101100010101011011110001100101110101100001100100010000011010110010100100000010011001111110101100111111000010101101101000001011000001100110010101111011010111001000100010110011111101010001101000011000110110110100000011100010011101111000001010011010111000011010110000000000111001110111100011000001100011000101010011111000101010001010111001001011001011110000010111101001011000111101111100101111010110101111011000000100111010101011111110111011010011001000001000110001011100001111101001101001111110001111110000001100000001001011010100001011111110100101100001000010111110000001001011111100111111010001111111000101111111001011000010110001101011110101000100110011000011101011000111110011110001010011001111111011001111101111011001000000 %
0!
#15000
b1111 &
b1110 '
1!
#15500
b101011110100011011011101001111111010000000101101100011100101110100101011100101111001111110011110110101100011011111000111111001010110100101110100101010100110011011110011010101111111111101100000111111111111100011001111011111110011110001100100001111101101000001001010000100110101001011011010010100101011100011100111011110111111010000111001101001011110110110001001100100010111011001111110010111101001001011110000111001111011011100110010000101101111110101100001110001011010101001010000100101101100011010111101000101101000010001011111101001111011000111101000110110000010000000000101101111100110101111001111101100110101110000011011010110100011111011101110100001000011111000000010001010111100011001101100110111001101001111010000010101000011010000001011011111011101110000101101000101111010100011010100011110010000111001011110101100010011000011000000110000011110101011101100100110100101100111100011010010100101101010001011101011010100101010010101001111101100100110010100111111100110000110111010110101011111011101101011000111101010001110111110110010101000100110010001101001110111001101000111111101001110100011111111000001000000100101011000010000101100101010010101111001011101011110101111100101111101000001011100111001111101100000110010010011000101011101011110110100111000010101110101100000000101000101000011111100001110111111111010101111110110011010001111011000110000011001110101001101101010011011010001011111001100000111000000100000011001111011101101000011110110010010100111001111001110001001010111011111011011100000111010110001110011111110110010011001011111001001011000100010101100010000101110001000110000111 %
0!
