Draft_Phuong/mod3_i8_o1_ver2/mod3_i8_o1.sv
module mod3_i8_o1(in, out);
	input [7:0] in;
	output [1:0] out;
    wire [3:0] node;

	stage1 MOD3_1 ( .in( in[3:0] ), .out( node[1:0] ) );
	stage1 MOD3_2 ( .in( in[7:4] ), .out( node[3:2] ) );
	stage2 MOD3_3 ( .in( node[3:0] ), .out( out[1:0] ) );

endmodule

module stage1(in, out);
	input [3:0] in;
	output [1:0] out;
    wire [4:0] node;

	assign node[0] = ~(in[3]^in[2]);
	assign node[1] = ~(in[1]^in[0]);
	assign node[2] = in[1] & (~in[0]);
	assign node[3] = in[3] & (~in[2]);
	assign node[4] = (~in[3]) & in[2] & (~in[1]) & in[0];
	assign out[0] = ( node[1] ^ node[0] ) | ( node[3] & node[2] ) | node[4];
	assign out[1] = ( node[2] & node[0] ) | ( node[3] & node[1] ) | node[4];

endmodule

module stage2(in, out);
	input [3:0] in;
	output [1:0] out;

	assign out[0] = ( in[2] ^ in[0] ) | ( in[3] & in[1] ) | ( in[2] & ( ~(in[3] | in[1]) ) );
	assign out[1] = ( in[3] ^ in[0] ) & ( in[2] ^ in[1] ) & ( ~(in[3] & in[1]) );

endmodule

Draft_Phuong/mod3_i8_o1_ver2/mod3_tb.sv
`include "mod3_i8_o1.sv"
module mod3_tb(input [7:0] in_sig, 
               output [1:0] out_sig);
    
    mod3_i8_o1 MOD3 (in_sig, out_sig);
    
    initial begin
        $dumpfile("dump.vcd");
        $dumpvars(1);
    end
endmodule

Draft_Phuong/mod3_i8_o1_ver2/dump.vcd
$date
	Fri Oct 15 01:18:44 2021
$end
$version
	Icarus Verilog
$end
$timescale
	1ps
$end
$scope module mod3_tb $end
$var wire 8 ! in_sig [7:0] $end
$var wire 2 " out_sig [1:0] $end
$upscope $end
$enddefinitions $end
#0
$dumpvars
b0 "
b0 !
$end
#2000
b1 "
b1 !
#4000
b11 "
b10 !
#6000
b0 "
b11 !
#8000
b1 "
b100 !
#10000
b11 "
b101 !
#12000
b0 "
b110 !
#14000
b1 "
b111 !
#16000
b11 "
b1000 !
#18000
b0 "
b1001 !
#20000
b1 "
b1010 !
#22000
b11 "
b1011 !
#24000
b0 "
b1100 !
#26000
b1 "
b1101 !
#28000
b11 "
b1110 !
#30000
b0 "
b1111 !
#32000
b1 "
b10000 !
#34000
b11 "
b10001 !
#36000
b0 "
b10010 !
#38000
b1 "
b10011 !
#40000
b11 "
b10100 !
#42000
b0 "
b10101 !
#44000
b1 "
b10110 !
#46000
b11 "
b10111 !
#48000
b0 "
b11000 !
#50000
b1 "
b11001 !
#52000
b11 "
b11010 !
#54000
b0 "
b11011 !
#56000
b1 "
b11100 !
#58000
b11 "
b11101 !
#60000
b0 "
b11110 !
#62000
b1 "
b11111 !
#64000
b11 "
b100000 !
#66000
b0 "
b100001 !
#68000
b1 "
b100010 !
#70000
b11 "
b100011 !
#72000
b0 "
b100100 !
#74000
b1 "
b100101 !
#76000
b11 "
b100110 !
#78000
b0 "
b100111 !
#80000
b1 "
b101000 !
#82000
b11 "
b101001 !
#84000
b0 "
b101010 !
#86000
b1 "
b101011 !
#88000
b11 "
b101100 !
#90000
b0 "
b101101 !
#92000
b1 "
b101110 !
#94000
b11 "
b101111 !
#96000
b0 "
b110000 !
#98000
b1 "
b110001 !
#100000
b11 "
b110010 !
#102000
b0 "
b110011 !
#104000
b1 "
b110100 !
#106000
b11 "
b110101 !
#108000
b0 "
b110110 !
#110000
b1 "
b110111 !
#112000
b11 "
b111000 !
#114000
b0 "
b111001 !
#116000
b1 "
b111010 !
#118000
b11 "
b111011 !
#120000
b0 "
b111100 !
#122000
b1 "
b111101 !
#124000
b11 "
b111110 !
#126000
b0 "
b111111 !
#128000
b1 "
b1000000 !
#130000
b11 "
b1000001 !
#132000
b0 "
b1000010 !
#134000
b1 "
b1000011 !
#136000
b11 "
b1000100 !
#138000
b0 "
b1000101 !
#140000
b1 "
b1000110 !
#142000
b11 "
b1000111 !
#144000
b0 "
b1001000 !
#146000
b1 "
b1001001 !
#148000
b11 "
b1001010 !
#150000
b0 "
b1001011 !
#152000
b1 "
b1001100 !
#154000
b11 "
b1001101 !
#156000
b0 "
b1001110 !
#158000
b1 "
b1001111 !
#160000
b11 "
b1010000 !
#162000
b0 "
b1010001 !
#164000
b1 "
b1010010 !
#166000
b11 "
b1010011 !
#168000
b0 "
b1010100 !
#170000
b1 "
b1010101 !
#172000
b11 "
b1010110 !
#174000
b0 "
b1010111 !
#176000
b1 "
b1011000 !
#178000
b11 "
b1011001 !
#180000
b0 "
b1011010 !
#182000
b1 "
b1011011 !
#184000
b11 "
b1011100 !
#186000
b0 "
b1011101 !
#188000
b1 "
b1011110 !
#190000
b11 "
b1011111 !
#192000
b0 "
b1100000 !
#194000
b1 "
b1100001 !
#196000
b11 "
b1100010 !
#198000
b0 "
b1100011 !
#200000
b1 "
b1100100 !
#202000
b11 "
b1100101 !
#204000
b0 "
b1100110 !
#206000
b1 "
b1100111 !
#208000
b11 "
b1101000 !
#210000
b0 "
b1101001 !
#212000
b1 "
b1101010 !
#214000
b11 "
b1101011 !
#216000
b0 "
b1101100 !
#218000
b1 "
b1101101 !
#220000
b11 "
b1101110 !
#222000
b0 "
b1101111 !
#224000
b1 "
b1110000 !
#226000
b11 "
b1110001 !
#228000
b0 "
b1110010 !
#230000
b1 "
b1110011 !
#232000
b11 "
b1110100 !
#234000
b0 "
b1110101 !
#236000
b1 "
b1110110 !
#238000
b11 "
b1110111 !
#240000
b0 "
b1111000 !
#242000
b1 "
b1111001 !
#244000
b11 "
b1111010 !
#246000
b0 "
b1111011 !
#248000
b1 "
b1111100 !
#250000
b11 "
b1111101 !
#252000
b0 "
b1111110 !
#254000
b1 "
b1111111 !
#256000
b11 "
b10000000 !
#258000
b0 "
b10000001 !
#260000
b1 "
b10000010 !
#262000
b11 "
b10000011 !
#264000
b0 "
b10000100 !
#266000
b1 "
b10000101 !
#268000
b11 "
b10000110 !
#270000
b0 "
b10000111 !
#272000
b1 "
b10001000 !
#274000
b11 "
b10001001 !
#276000
b0 "
b10001010 !
#278000
b1 "
b10001011 !
#280000
b11 "
b10001100 !
#282000
b0 "
b10001101 !
#284000
b1 "
b10001110 !
#286000
b11 "
b10001111 !
#288000
b0 "
b10010000 !
#290000
b1 "
b10010001 !
#292000
b11 "
b10010010 !
#294000
b0 "
b10010011 !
#296000
b1 "
b10010100 !
#298000
b11 "
b10010101 !
#300000
b0 "
b10010110 !
#302000
b1 "
b10010111 !
#304000
b11 "
b10011000 !
#306000
b0 "
b10011001 !
#308000
b1 "
b10011010 !
#310000
b11 "
b10011011 !
#312000
b0 "
b10011100 !
#314000
b1 "
b10011101 !
#316000
b11 "
b10011110 !
#318000
b0 "
b10011111 !
#320000
b1 "
b10100000 !
#322000
b11 "
b10100001 !
#324000
b0 "
b10100010 !
#326000
b1 "
b10100011 !
#328000
b11 "
b10100100 !
#330000
b0 "
b10100101 !
#332000
b1 "
b10100110 !
#334000
b11 "
b10100111 !
#336000
b0 "
b10101000 !
#338000
b1 "
b10101001 !
#340000
b11 "
b10101010 !
#342000
b0 "
b10101011 !
#344000
b1 "
b10101100 !
#346000
b11 "
b10101101 !
#348000
b0 "
b10101110 !
#350000
b1 "
b10101111 !
#352000
b11 "
b10110000 !
#354000
b0 "
b10110001 !
#356000
b1 "
b10110010 !
#358000
b11 "
b10110011 !
#360000
b0 "
b10110100 !
#362000
b1 "
b10110101 !
#364000
b11 "
b10110110 !
#366000
b0 "
b10110111 !
#368000
b1 "
b10111000 !
#370000
b11 "
b10111001 !
#372000
b0 "
b10111010 !
#374000
b1 "
b10111011 !
#376000
b11 "
b10111100 !
#378000
b0 "
b10111101 !
#380000
b1 "
b10111110 !
#382000
b11 "
b10111111 !
#384000
b0 "
b11000000 !
#386000
b1 "
b11000001 !
#388000
b11 "
b11000010 !
#390000
b0 "
b11000011 !
#392000
b1 "
b11000100 !
#394000
b11 "
b11000101 !
#396000
b0 "
b11000110 !
#398000
b1 "
b11000111 !
#400000
b11 "
b11001000 !
#402000
b0 "
b11001001 !
#404000
b1 "
b11001010 !
#406000
b11 "
b11001011 !
#408000
b0 "
b11001100 !
#410000
b1 "
b11001101 !
#412000
b11 "
b11001110 !
#414000
b0 "
b11001111 !
#416000
b1 "
b11010000 !
#418000
b11 "
b11010001 !
#420000
b0 "
b11010010 !
#422000
b1 "
b11010011 !
#424000
b11 "
b11010100 !
#426000
b0 "
b11010101 !
#428000
b1 "
b11010110 !
#430000
b11 "
b11010111 !
#432000
b0 "
b11011000 !
#434000
b1 "
b11011001 !
#436000
b11 "
b11011010 !
#438000
b0 "
b11011011 !
#440000
b1 "
b11011100 !
#442000
b11 "
b11011101 !
#444000
b0 "
b11011110 !
#446000
b1 "
b11011111 !
#448000
b11 "
b11100000 !
#450000
b0 "
b11100001 !
#452000
b1 "
b11100010 !
#454000
b11 "
b11100011 !
#456000
b0 "
b11100100 !
#458000
b1 "
b11100101 !
#460000
b11 "
b11100110 !
#462000
b0 "
b11100111 !
#464000
b1 "
b11101000 !
#466000
b11 "
b11101001 !
#468000
b0 "
b11101010 !
#470000
b1 "
b11101011 !
#472000
b11 "
b11101100 !
#474000
b0 "
b11101101 !
#476000
b1 "
b11101110 !
#478000
b11 "
b11101111 !
#480000
b0 "
b11110000 !
#482000
b1 "
b11110001 !
#484000
b11 "
b11110010 !
#486000
b0 "
b11110011 !
#488000
b1 "
b11110100 !
#490000
b11 "
b11110101 !
#492000
b0 "
b11110110 !
#494000
b1 "
b11110111 !
#496000
b11 "
b11111000 !
#498000
b0 "
b11111001 !
#500000
b1 "
b11111010 !
#502000
b11 "
b11111011 !
#504000
b0 "
b11111100 !
#506000
b1 "
b11111101 !
#508000
b11 "
b11111110 !
